Workbook

Sheet Read Me
A1: Barbourville, KY — Public EV Charging Station Analysis
B3: Prepared for: Barbourville City Tourism / City of Barbourville
B4: Prepared by: Mountain Association — Energy Team, Central Appalachia Internship Program
B5: Report period: July 12, 2025 – July 11, 2026 (12 months, ChargePoint dashboard export)
B6: Stations covered: BARBOURVILLE / CITY HALL (Level 3 / DCFC fast charger) and BARBOURVILLE / TOURISM (Level 2 charger), both on the Barbourville City Tourism ChargePoint account.
B7: These are two physically different chargers, so this workbook analyzes them separately first (Tourism (Level 2) and City Hall (Level 3) tabs - Tourism is the primary station of interest), then presents an All Stations Combined view (Daily Summary / Time of Day / Revenue / Visitor Origin tabs).
B8: Data sources
B9: • Energy-vs-Time-chart export — daily energy (kWh) delivered by the charger, ChargePoint dashboard (2 overlapping exports, deduplicated to 365 daily records).
B10: • Sessions export — 288 individual charging sessions: start/end time, energy delivered, peak power, payment method.
B11: • Charging Session Updates export — 1,119 fifteen-minute interval power readings tied to 278 of the sessions, used to measure how much of each session was actively drawing "car load" power.
B12: • Organization Statement export — 237 billed transactions with driver ZIP/county, revenue, fees, and payout — matched to sessions by transaction/session ID (235 of 237 matched).
B13: • GHG Savings chart (ChargePoint) — reference exhibit only; underlying data points are not machine-readable from the chart file, so figures from it are cited qualitatively, not recomputed.
B15: Key definitions & assumptions used throughout this workbook
... B39: • Raw - Sessions, Raw - Daily Energy, Raw - Zip-County-State — the underlying cleaned data every formula in this workbook points back to (Raw - Sessions column K identifies which station each session belongs to)

Sheet Dashboard
A1: Barbourville, KY — Public EV Charging: 12-Month Snapshot
A2: BARBOURVILLE / CITY HALL (Level 3 DCFC) + BARBOURVILLE / TOURISM (Level 2) | Jul 2025 - Jul 2026 | Prepared as a benchmark example of what a Level 2 charger could bring to a city
A4: Total Sessions | C4: Total Energy (kWh) | E4: Avg Energy / Day (kWh) | G4: Avg Energy / Active Day (kWh) | I4: Avg Power While Charging (kW) | K4: Total Revenue | M4: Owner Payout | O4: Out-of-State Sessions | Q4: Avg Session Length (min)
A5: =COUNTA('Raw - Sessions'!A5:A292) -> 288 | C5: =SUM('Raw - Sessions'!E5:E292) -> 6216.7055 | E5: =SUM('Raw - Sessions'!E5:E292)/'Daily Summary'!C5 -> 17.03207 | G5: =SUM('Raw - Sessions'!E5:E292)/SUM('Raw - Sessions'!AF5:AF292) -> 45.048591 | I5: =SUM('Raw - Sessions'!E5:E292)/SUM('Raw - Sessions'!D5:D292) -> 29.183252 | K5: =SUM('Raw - Sessions'!P5:P292) -> 4036.12 | M5: =SUM('Raw - Sessions'!Q5:Q292) -> 3415.92 | O5: =COUNTIFS('Raw - Sessions'!$O$5:$O$292,"<>",'Raw - Sessions'!$O$5:$O$292,"<>KY") -> 68 | Q5: =AVERAGE('Raw - Sessions'!D5:D292)*60 -> 44.379803
A9: Level 2 (Tourism) vs. Level 3 (City Hall) at a Glance
A10: Metric | B10: Tourism (Level 2) | C10: City Hall (Level 3) | D10: Combined
A11: Sessions | B11: =COUNTIF('Raw - Sessions'!$K$5:$K$292,"BARBOURVILLE / TOURISM") -> 49 | C11: =COUNTIF('Raw - Sessions'!$K$5:$K$292,"BARBOURVILLE / CITY HALL") -> 239 | D11: =COUNTA('Raw - Sessions'!$K$5:$K$292) -> 288
A12: Energy (kWh) | B12: =SUMIF('Raw - Sessions'!$K$5:$K$292,"BARBOURVILLE / TOURISM",'Raw - Sessions'!$E$5:$E$292) -> 392.20674 | C12: =SUMIF('Raw - Sessions'!$K$5:$K$292,"BARBOURVILLE / CITY HALL",'Raw - Sessions'!$E$5:$E$292) -> 5824.4988 | D12: =SUM('Raw - Sessions'!$E$5:$E$292) -> 6216.7055
A13: Active Days (kWh > 0) | B13: =SUMIF('Raw - Sessions'!$K$5:$K$292,"BARBOURVILLE / TOURISM",'Raw - Sessions'!$AG$5:$AG$292) -> 27 | C13: =SUMIF('Raw - Sessions'!$K$5:$K$292,"BARBOURVILLE / CITY HALL",'Raw - Sessions'!$AG$5:$AG$292) -> 127 | D13: =SUM('Raw - Sessions'!$AF$5:$AF$292) -> 138
A14: Avg Energy / Day (kWh) | B14: =SUMIF('Raw - Sessions'!$K$5:$K$292,"BARBOURVILLE / TOURISM",'Raw - Sessions'!$E$5:$E$292)/'Daily Summary'!C5 -> 1.074539 | C14: =SUMIF('Raw - Sessions'!$K$5:$K$292,"BARBOURVILLE / CITY HALL",'Raw - Sessions'!$E$5:$E$292)/'Daily Summary'!C5 -> 15.957531 | D14: =SUM('Raw - Sessions'!$E$5:$E$292)/'Daily Summary'!C5 -> 17.03207
A15: Avg Energy / Active Day (kWh) | B15: =SUMIF('Raw - Sessions'!$K$5:$K$292,"BARBOURVILLE / TOURISM",'Raw - Sessions'!$E$5:$E$292)/SUMIF('Raw - Sessions'!$K$5:$K$292,"BARBOURVILLE / TOURISM",'Raw - Sessions'!$AG$5:$AG$292) -> 14.526176 | C15: =SUMIF('Raw - Sessions'!$K$5:$K$292,"BARBOURVILLE / CITY HALL",'Raw - Sessions'!$E$5:$E$292)/SUMIF('Raw - Sessions'!$K$5:$K$292,"BARBOURVILLE / CITY HALL",'Raw - Sessions'!$AG$5:$AG$292) -> 45.862195 | D15: =SUM('Raw - Sessions'!$E$5:$E$292)/SUM('Raw - Sessions'!$AF$5:$AF$292) -> 45.048591
A16: Avg Power While Charging (kW) | B16: =SUMIF('Raw - Sessions'!$K$5:$K$292,"BARBOURVILLE / TOURISM",'Raw - Sessions'!$E$5:$E$292)/SUMIF('Raw - Sessions'!$K$5:$K$292,"BARBOURVILLE / TOURISM",'Raw - Sessions'!$D$5:$D$292) -> 6.1936888 | C16: =SUMIF('Raw - Sessions'!$K$5:$K$292,"BARBOURVILLE / CITY HALL",'Raw - Sessions'!$E$5:$E$292)/SUMIF('Raw - Sessions'!$K$5:$K$292,"BARBOURVILLE / CITY HALL",'Raw - Sessions'!$D$5:$D$292) -> 38.907952 | D16: =SUM('Raw - Sessions'!$E$5:$E$292)/SUM('Raw - Sessions'!$D$5:$D$292) -> 29.183252
A17: Revenue ($) | B17: =SUMIF('Raw - Sessions'!$K$5:$K$292,"BARBOURVILLE / TOURISM",'Raw - Sessions'!$P$5:$P$292) -> 458.21 | C17: =SUMIF('Raw - Sessions'!$K$5:$K$292,"BARBOURVILLE / CITY HALL",'Raw - Sessions'!$P$5:$P$292) -> 3577.91 | D17: =SUM('Raw - Sessions'!$P$5:$P$292) -> 4036.12
A18: Avg Session Length (min) | B18: =AVERAGEIFS('Raw - Sessions'!$D$5:$D$292,'Raw - Sessions'!$K$5:$K$292,"BARBOURVILLE / TOURISM")*60 -> 77.539116 | C18: =AVERAGEIFS('Raw - Sessions'!$D$5:$D$292,'Raw - Sessions'!$K$5:$K$292,"BARBOURVILLE / CITY HALL")*60 -> 37.58145 | D18: =AVERAGE('Raw - Sessions'!$D$5:$D$292)*60 -> 44.379803
A19: Max Power (kW) | B19: =SUMPRODUCT(MAX(('Raw - Sessions'!$K$5:$K$292="BARBOURVILLE / TOURISM")*'Raw - Sessions'!F5:F292)) -> 7.4007 | C19: =SUMPRODUCT(MAX(('Raw - Sessions'!$K$5:$K$292="BARBOURVILLE / CITY HALL")*'Raw - Sessions'!F5:F292)) -> 62.882 | D19: =MAX('Raw - Sessions'!F5:F292) -> 62.882
A21: Why this matters for a new Level 2 charger: Tourism (L2) sessions run almost twice as long as City Hall (L3) sessions on average, and cap out near 7.4 kW - it draws fewer visits but holds drivers downtown longer per visit, which is the profile that benefits nearby shops and restaurants most. See the Tourism (Level 2) tab for the full breakdown.

Sheet Tourism (Level 2)
A1: BARBOURVILLE / TOURISM — Level 2 Charger Snapshot
A2: All figures below are filtered to this station only, pulled live from Raw - Sessions (Station = "BARBOURVILLE / TOURISM").
A3: Note on the >10 kW "car load" threshold: this Level 2 charger tops out at about 7.4 kW, so it can never register a session above 10 kW - the combined-workbook threshold (built for the Level 3 charger) does not apply here. The KPI below instead uses a Level-2-appropriate 3 kW threshold to separate active charging from trickle/near-idle time.
A5: Sessions | C5: Total Energy (kWh) | E5: Total Gross Revenue | G5: Avg Session Length (min) | I5: % Sessions Peak Power > 3 kW
A6: =COUNTIF('Raw - Sessions'!$K$5:$K$292,"BARBOURVILLE / TOURISM") -> 49 | C6: =SUMIF('Raw - Sessions'!$K$5:$K$292,"BARBOURVILLE / TOURISM",'Raw - Sessions'!$E$5:$E$292) -> 392.20674 | E6: =SUMIF('Raw - Sessions'!$K$5:$K$292,"BARBOURVILLE / TOURISM",'Raw - Sessions'!$P$5:$P$292) -> 458.21 | G6: =AVERAGEIFS('Raw - Sessions'!$D$5:$D$292,'Raw - Sessions'!$K$5:$K$292,"BARBOURVILLE / TOURISM")*60 -> 77.539116 | I6: =IFERROR(COUNTIFS('Raw - Sessions'!$K$5:$K$292,"BARBOURVILLE / TOURISM",'Raw - Sessions'!$F$5:$F$292,">3")/COUNTIFS('Raw - Sessions'!$K$5:$K$292,"BARBOURVILLE / TOURISM",'Raw - Sessions'!$F$5:$F$292,"<>"),0) -> 0.77777778
A10: By Time of Day
A11: Day Segment | B11: Sessions | C11: Avg Duration (hr) | D11: Total Energy (kWh)
A12: Morning (6-12) | B12: =COUNTIFS('Raw - Sessions'!$K$5:$K$292,"BARBOURVILLE / TOURISM",'Raw - Sessions'!$G$5:$G$292,A12) -> 0 | C12: =IFERROR(AVERAGEIFS('Raw - Sessions'!$D$5:$D$292,'Raw - Sessions'!$K$5:$K$292,"BARBOURVILLE / TOURISM",'Raw - Sessions'!$G$5:$G$292,A12),0) -> 0 | D12: =SUMIFS('Raw - Sessions'!$E$5:$E$292,'Raw - Sessions'!$K$5:$K$292,"BARBOURVILLE / TOURISM",'Raw - Sessions'!$G$5:$G$292,A12) -> 0
A13: Day (12-18) | B13: =COUNTIFS('Raw - Sessions'!$K$5:$K$292,"BARBOURVILLE / TOURISM",'Raw - Sessions'!$G$5:$G$292,A13) -> 17 | C13: =IFERROR(AVERAGEIFS('Raw - Sessions'!$D$5:$D$292,'Raw - Sessions'!$K$5:$K$292,"BARBOURVILLE / TOURISM",'Raw - Sessions'!$G$5:$G$292,A13),0) -> 1.0963399 | D13: =SUMIFS('Raw - Sessions'!$E$5:$E$292,'Raw - Sessions'!$K$5:$K$292,"BARBOURVILLE / TOURISM",'Raw - Sessions'!$G$5:$G$292,A13) -> 130.90719
A14: Evening (18-22) | B14: =COUNTIFS('Raw - Sessions'!$K$5:$K$292,"BARBOURVILLE / TOURISM",'Raw - Sessions'!$G$5:$G$292,A14) -> 15 | C14: =IFERROR(AVERAGEIFS('Raw - Sessions'!$D$5:$D$292,'Raw - Sessions'!$K$5:$K$292,"BARBOURVILLE / TOURISM",'Raw - Sessions'!$G$5:$G$292,A14),0) -> 1.6253519 | D14: =SUMIFS('Raw - Sessions'!$E$5:$E$292,'Raw - Sessions'!$K$5:$K$292,"BARBOURVILLE / TOURISM",'Raw - Sessions'!$G$5:$G$292,A14) -> 142.40364
A15: Night (22-6) | B15: =COUNTIFS('Raw - Sessions'!$K$5:$K$292,"BARBOURVILLE / TOURISM",'Raw - Sessions'!$G$5:$G$292,A15) -> 17 | C15: =IFERROR(AVERAGEIFS('Raw - Sessions'!$D$5:$D$292,'Raw - Sessions'!$K$5:$K$292,"BARBOURVILLE / TOURISM",'Raw - Sessions'!$G$5:$G$292,A15),0) -> 1.1944444 | D15: =SUMIFS('Raw - Sessions'!$E$5:$E$292,'Raw - Sessions'!$K$5:$K$292,"BARBOURVILLE / TOURISM",'Raw - Sessions'!$G$5:$G$292,A15) -> 118.89591
A17: Overnight sessions (started 22:00-6:00) | C17: =COUNTIFS('Raw - Sessions'!$K$5:$K$292,"BARBOURVILLE / TOURISM",'Raw - Sessions'!$I$5:$I$292,TRUE()) -> 17
A20: Monthly Trend
A21: Month | B21: Sessions | C21: Revenue ($) | D21: Energy (kWh)
A22: 45931 | B22: =COUNTIFS('Raw - Sessions'!$K$5:$K$292,"BARBOURVILLE / TOURISM",'Raw - Sessions'!$B$5:$B$292,">="&A22,'Raw - Sessions'!$B$5:$B$292,"<"&DATE(YEAR(A22),MONTH(A22)+1,1)) -> 5 | C22: =SUMIFS('Raw - Sessions'!$P$5:$P$292,'Raw - Sessions'!$K$5:$K$292,"BARBOURVILLE / TOURISM",'Raw - Sessions'!$B$5:$B$292,">="&A22,'Raw - Sessions'!$B$5:$B$292,"<"&DATE(YEAR(A22),MONTH(A22)+1,1)) -> 5.8 | D22: =SUMIFS('Raw - Sessions'!$E$5:$E$292,'Raw - Sessions'!$K$5:$K$292,"BARBOURVILLE / TOURISM",'Raw - Sessions'!$B$5:$B$292,">="&A22,'Raw - Sessions'!$B$5:$B$292,"<"&DATE(YEAR(A22),MONTH(A22)+1,1)) -> 21.88127
A23: 45962 | B23: =COUNTIFS('Raw - Sessions'!$K$5:$K$292,"BARBOURVILLE / TOURISM",'Raw - Sessions'!$B$5:$B$292,">="&A23,'Raw - Sessions'!$B$5:$B$292,"<"&DATE(YEAR(A23),MONTH(A23)+1,1)) -> 5 | C23: =SUMIFS('Raw - Sessions'!$P$5:$P$292,'Raw - Sessions'!$K$5:$K$292,"BARBOURVILLE / TOURISM",'Raw - Sessions'!$B$5:$B$292,">="&A23,'Raw - Sessions'!$B$5:$B$292,"<"&DATE(YEAR(A23),MONTH(A23)+1,1)) -> 7.28 | D23: =SUMIFS('Raw - Sessions'!$E$5:$E$292,'Raw - Sessions'!$K$5:$K$292,"BARBOURVILLE / TOURISM",'Raw - Sessions'!$B$5:$B$292,">="&A23,'Raw - Sessions'!$B$5:$B$292,"<"&DATE(YEAR(A23),MONTH(A23)+1,1)) -> 7.177646
A24: 45992 | B24: =COUNTIFS('Raw - Sessions'!$K$5:$K$292,"BARBOURVILLE / TOURISM",'Raw - Sessions'!$B$5:$B$292,">="&A24,'Raw - Sessions'!$B$5:$B$292,"<"&DATE(YEAR(A24),MONTH(A24)+1,1)) -> 7 | C24: =SUMIFS('Raw - Sessions'!$P$5:$P$292,'Raw - Sessions'!$K$5:$K$292,"BARBOURVILLE / TOURISM",'Raw - Sessions'!$B$5:$B$292,">="&A24,'Raw - Sessions'!$B$5:$B$292,"<"&DATE(YEAR(A24),MONTH(A24)+1,1)) -> 152.82 | D24: =SUMIFS('Raw - Sessions'!$E$5:$E$292,'Raw - Sessions'!$K$5:$K$292,"BARBOURVILLE / TOURISM",'Raw - Sessions'!$B$5:$B$292,">="&A24,'Raw - Sessions'!$B$5:$B$292,"<"&DATE(YEAR(A24),MONTH(A24)+1,1)) -> 151.48866
A25: 46023 | B25: =COUNTIFS('Raw - Sessions'!$K$5:$K$292,"BARBOURVILLE / TOURISM",'Raw - Sessions'!$B$5:$B$292,">="&A25,'Raw - Sessions'!$B$5:$B$292,"<"&DATE(YEAR(A25),MONTH(A25)+1,1)) -> 0 | C25: =SUMIFS('Raw - Sessions'!$P$5:$P$292,'Raw - Sessions'!$K$5:$K$292,"BARBOURVILLE / TOURISM",'Raw - Sessions'!$B$5:$B$292,">="&A25,'Raw - Sessions'!$B$5:$B$292,"<"&DATE(YEAR(A25),MONTH(A25)+1,1)) -> 0 | D25: =SUMIFS('Raw - Sessions'!$E$5:$E$292,'Raw - Sessions'!$K$5:$K$292,"BARBOURVILLE / TOURISM",'Raw - Sessions'!$B$5:$B$292,">="&A25,'Raw - Sessions'!$B$5:$B$292,"<"&DATE(YEAR(A25),MONTH(A25)+1,1)) -> 0
A26: 46054 | B26: =COUNTIFS('Raw - Sessions'!$K$5:$K$292,"BARBOURVILLE / TOURISM",'Raw - Sessions'!$B$5:$B$292,">="&A26,'Raw - Sessions'!$B$5:$B$292,"<"&DATE(YEAR(A26),MONTH(A26)+1,1)) -> 3 | C26: =SUMIFS('Raw - Sessions'!$P$5:$P$292,'Raw - Sessions'!$K$5:$K$292,"BARBOURVILLE / TOURISM",'Raw - Sessions'!$B$5:$B$292,">="&A26,'Raw - Sessions'!$B$5:$B$292,"<"&DATE(YEAR(A26),MONTH(A26)+1,1)) -> 35.46 | D26: =SUMIFS('Raw - Sessions'!$E$5:$E$292,'Raw - Sessions'!$K$5:$K$292,"BARBOURVILLE / TOURISM",'Raw - Sessions'!$B$5:$B$292,">="&A26,'Raw - Sessions'!$B$5:$B$292,"<"&DATE(YEAR(A26),MONTH(A26)+1,1)) -> 22.638451
A27: 46082 | B27: =COUNTIFS('Raw - Sessions'!$K$5:$K$292,"BARBOURVILLE / TOURISM",'Raw - Sessions'!$B$5:$B$292,">="&A27,'Raw - Sessions'!$B$5:$B$292,"<"&DATE(YEAR(A27),MONTH(A27)+1,1)) -> 3 | C27: =SUMIFS('Raw - Sessions'!$P$5:$P$292,'Raw - Sessions'!$K$5:$K$292,"BARBOURVILLE / TOURISM",'Raw - Sessions'!$B$5:$B$292,">="&A27,'Raw - Sessions'!$B$5:$B$292,"<"&DATE(YEAR(A27),MONTH(A27)+1,1)) -> 52.15 | D27: =SUMIFS('Raw - Sessions'!$E$5:$E$292,'Raw - Sessions'!$K$5:$K$292,"BARBOURVILLE / TOURISM",'Raw - Sessions'!$B$5:$B$292,">="&A27,'Raw - Sessions'!$B$5:$B$292,"<"&DATE(YEAR(A27),MONTH(A27)+1,1)) -> 41.212752
A28: 46113 | B28: =COUNTIFS('Raw - Sessions'!$K$5:$K$292,"BARBOURVILLE / TOURISM",'Raw - Sessions'!$B$5:$B$292,">="&A28,'Raw - Sessions'!$B$5:$B$292,"<"&DATE(YEAR(A28),MONTH(A28)+1,1)) -> 10 | C28: =SUMIFS('Raw - Sessions'!$P$5:$P$292,'Raw - Sessions'!$K$5:$K$292,"BARBOURVILLE / TOURISM",'Raw - Sessions'!$B$5:$B$292,">="&A28,'Raw - Sessions'!$B$5:$B$292,"<"&DATE(YEAR(A28),MONTH(A28)+1,1)) -> 88.35 | D28: =SUMIFS('Raw - Sessions'!$E$5:$E$292,'Raw - Sessions'!$K$5:$K$292,"BARBOURVILLE / TOURISM",'Raw - Sessions'!$B$5:$B$292,">="&A28,'Raw - Sessions'!$B$5:$B$292,"<"&DATE(YEAR(A28),MONTH(A28)+1,1)) -> 69.705949
A29: 46143 | B29: =COUNTIFS('Raw - Sessions'!$K$5:$K$292,"BARBOURVILLE / TOURISM",'Raw - Sessions'!$B$5:$B$292,">="&A29,'Raw - Sessions'!$B$5:$B$292,"<"&DATE(YEAR(A29),MONTH(A29)+1,1)) -> 9 | C29: =SUMIFS('Raw - Sessions'!$P$5:$P$292,'Raw - Sessions'!$K$5:$K$292,"BARBOURVILLE / TOURISM",'Raw - Sessions'!$B$5:$B$292,">="&A29,'Raw - Sessions'!$B$5:$B$292,"<"&DATE(YEAR(A29),MONTH(A29)+1,1)) -> 68.98 | D29: =SUMIFS('Raw - Sessions'!$E$5:$E$292,'Raw - Sessions'!$K$5:$K$292,"BARBOURVILLE / TOURISM",'Raw - Sessions'!$B$5:$B$292,">="&A29,'Raw - Sessions'!$B$5:$B$292,"<"&DATE(YEAR(A29),MONTH(A29)+1,1)) -> 52.069591
A30: 46174 | B30: =COUNTIFS('Raw - Sessions'!$K$5:$K$292,"BARBOURVILLE / TOURISM",'Raw - Sessions'!$B$5:$B$292,">="&A30,'Raw - Sessions'!$B$5:$B$292,"<"&DATE(YEAR(A30),MONTH(A30)+1,1)) -> 6 | C30: =SUMIFS('Raw - Sessions'!$P$5:$P$292,'Raw - Sessions'!$K$5:$K$292,"BARBOURVILLE / TOURISM",'Raw - Sessions'!$B$5:$B$292,">="&A30,'Raw - Sessions'!$B$5:$B$292,"<"&DATE(YEAR(A30),MONTH(A30)+1,1)) -> 20.67 | D30: =SUMIFS('Raw - Sessions'!$E$5:$E$292,'Raw - Sessions'!$K$5:$K$292,"BARBOURVILLE / TOURISM",'Raw - Sessions'!$B$5:$B$292,">="&A30,'Raw - Sessions'!$B$5:$B$292,"<"&DATE(YEAR(A30),MONTH(A30)+1,1)) -> 13.727628
A31: 46204 | B31: =COUNTIFS('Raw - Sessions'!$K$5:$K$292,"BARBOURVILLE / TOURISM",'Raw - Sessions'!$B$5:$B$292,">="&A31,'Raw - Sessions'!$B$5:$B$292,"<"&DATE(YEAR(A31),MONTH(A31)+1,1)) -> 1 | C31: =SUMIFS('Raw - Sessions'!$P$5:$P$292,'Raw - Sessions'!$K$5:$K$292,"BARBOURVILLE / TOURISM",'Raw - Sessions'!$B$5:$B$292,">="&A31,'Raw - Sessions'!$B$5:$B$292,"<"&DATE(YEAR(A31),MONTH(A31)+1,1)) -> 26.7 | D31: =SUMIFS('Raw - Sessions'!$E$5:$E$292,'Raw - Sessions'!$K$5:$K$292,"BARBOURVILLE / TOURISM",'Raw - Sessions'!$B$5:$B$292,">="&A31,'Raw - Sessions'!$B$5:$B$292,"<"&DATE(YEAR(A31),MONTH(A31)+1,1)) -> 12.304789
A34: Top States of Origin (sessions with known ZIP)
A35: Est. State | B35: Sessions
A36: ='Visitor Origin'!A5 -> KY | B36: =COUNTIFS('Raw - Sessions'!$K$5:$K$292,"BARBOURVILLE / TOURISM",'Raw - Sessions'!$O$5:$O$292,A36) -> 7
A37: ='Visitor Origin'!A6 -> TN | B37: =COUNTIFS('Raw - Sessions'!$K$5:$K$292,"BARBOURVILLE / TOURISM",'Raw - Sessions'!$O$5:$O$292,A37) -> 1
A38: ='Visitor Origin'!A7 -> OH | B38: =COUNTIFS('Raw - Sessions'!$K$5:$K$292,"BARBOURVILLE / TOURISM",'Raw - Sessions'!$O$5:$O$292,A38) -> 1
A39: ='Visitor Origin'!A8 -> NC | B39: =COUNTIFS('Raw - Sessions'!$K$5:$K$292,"BARBOURVILLE / TOURISM",'Raw - Sessions'!$O$5:$O$292,A39) -> 0
A40: ='Visitor Origin'!A9 -> IL | B40: =COUNTIFS('Raw - Sessions'!$K$5:$K$292,"BARBOURVILLE / TOURISM",'Raw - Sessions'!$O$5:$O$292,A40) -> 4
A41: ='Visitor Origin'!A10 -> FL | B41: =COUNTIFS('Raw - Sessions'!$K$5:$K$292,"BARBOURVILLE / TOURISM",'Raw - Sessions'!$O$5:$O$292,A41) -> 0
A42: ='Visitor Origin'!A11 -> SC | B42: =COUNTIFS('Raw - Sessions'!$K$5:$K$292,"BARBOURVILLE / TOURISM",'Raw - Sessions'!$O$5:$O$292,A42) -> 0
A43: ='Visitor Origin'!A12 -> MI | B43: =COUNTIFS('Raw - Sessions'!$K$5:$K$292,"BARBOURVILLE / TOURISM",'Raw - Sessions'!$O$5:$O$292,A43) -> 0
A44: ='Visitor Origin'!A13 -> WI | B44: =COUNTIFS('Raw - Sessions'!$K$5:$K$292,"BARBOURVILLE / TOURISM",'Raw - Sessions'!$O$5:$O$292,A44) -> 0
A45: ='Visitor Origin'!A14 -> IN | B45: =COUNTIFS('Raw - Sessions'!$K$5:$K$292,"BARBOURVILLE / TOURISM",'Raw - Sessions'!$O$5:$O$292,A45) -> 0
A46: ='Visitor Origin'!A15 -> GA | B46: =COUNTIFS('Raw - Sessions'!$K$5:$K$292,"BARBOURVILLE / TOURISM",'Raw - Sessions'!$O$5:$O$292,A46) -> 0
A47: ='Visitor Origin'!A16 -> TX | B47: =COUNTIFS('Raw - Sessions'!$K$5:$K$292,"BARBOURVILLE / TOURISM",'Raw - Sessions'!$O$5:$O$292,A47) -> 0
... A54: ='Visitor Origin'!A23 -> OK | B54: =COUNTIFS('Raw - Sessions'!$K$5:$K$292,"BARBOURVILLE / TOURISM",'Raw - Sessions'!$O$5:$O$292,A54) -> 0
A56: States with 0 sessions for this charger are still listed for consistency with the combined Visitor Origin tab.

Sheet City Hall (Level 3)
A1: BARBOURVILLE / CITY HALL — Level 3 (DCFC) Charger Snapshot
A2: All figures below are filtered to this station only, pulled live from Raw - Sessions (Station = "BARBOURVILLE / CITY HALL").
A5: Sessions | C5: Total Energy (kWh) | E5: Total Gross Revenue | G5: Avg Session Length (min) | I5: % Sessions Peak Power > 10 kW
A6: =COUNTIF('Raw - Sessions'!$K$5:$K$292,"BARBOURVILLE / CITY HALL") -> 239 | C6: =SUMIF('Raw - Sessions'!$K$5:$K$292,"BARBOURVILLE / CITY HALL",'Raw - Sessions'!$E$5:$E$292) -> 5824.4988 | E6: =SUMIF('Raw - Sessions'!$K$5:$K$292,"BARBOURVILLE / CITY HALL",'Raw - Sessions'!$P$5:$P$292) -> 3577.91 | G6: =AVERAGEIFS('Raw - Sessions'!$D$5:$D$292,'Raw - Sessions'!$K$5:$K$292,"BARBOURVILLE / CITY HALL")*60 -> 37.58145 | I6: =IFERROR(COUNTIFS('Raw - Sessions'!$K$5:$K$292,"BARBOURVILLE / CITY HALL",'Raw - Sessions'!$F$5:$F$292,">10")/COUNTIFS('Raw - Sessions'!$K$5:$K$292,"BARBOURVILLE / CITY HALL",'Raw - Sessions'!$F$5:$F$292,"<>"),0) -> 0.78540773
A10: By Time of Day
A11: Day Segment | B11: Sessions | C11: Avg Duration (hr) | D11: Total Energy (kWh)
A12: Morning (6-12) | B12: =COUNTIFS('Raw - Sessions'!$K$5:$K$292,"BARBOURVILLE / CITY HALL",'Raw - Sessions'!$G$5:$G$292,A12) -> 4 | C12: =IFERROR(AVERAGEIFS('Raw - Sessions'!$D$5:$D$292,'Raw - Sessions'!$K$5:$K$292,"BARBOURVILLE / CITY HALL",'Raw - Sessions'!$G$5:$G$292,A12),0) -> 0.54180556 | D12: =SUMIFS('Raw - Sessions'!$E$5:$E$292,'Raw - Sessions'!$K$5:$K$292,"BARBOURVILLE / CITY HALL",'Raw - Sessions'!$G$5:$G$292,A12) -> 57.8262
A13: Day (12-18) | B13: =COUNTIFS('Raw - Sessions'!$K$5:$K$292,"BARBOURVILLE / CITY HALL",'Raw - Sessions'!$G$5:$G$292,A13) -> 79 | C13: =IFERROR(AVERAGEIFS('Raw - Sessions'!$D$5:$D$292,'Raw - Sessions'!$K$5:$K$292,"BARBOURVILLE / CITY HALL",'Raw - Sessions'!$G$5:$G$292,A13),0) -> 0.64993671 | D13: =SUMIFS('Raw - Sessions'!$E$5:$E$292,'Raw - Sessions'!$K$5:$K$292,"BARBOURVILLE / CITY HALL",'Raw - Sessions'!$G$5:$G$292,A13) -> 2101.0725
A14: Evening (18-22) | B14: =COUNTIFS('Raw - Sessions'!$K$5:$K$292,"BARBOURVILLE / CITY HALL",'Raw - Sessions'!$G$5:$G$292,A14) -> 87 | C14: =IFERROR(AVERAGEIFS('Raw - Sessions'!$D$5:$D$292,'Raw - Sessions'!$K$5:$K$292,"BARBOURVILLE / CITY HALL",'Raw - Sessions'!$G$5:$G$292,A14),0) -> 0.6467401 | D14: =SUMIFS('Raw - Sessions'!$E$5:$E$292,'Raw - Sessions'!$K$5:$K$292,"BARBOURVILLE / CITY HALL",'Raw - Sessions'!$G$5:$G$292,A14) -> 2123.8601
A15: Night (22-6) | B15: =COUNTIFS('Raw - Sessions'!$K$5:$K$292,"BARBOURVILLE / CITY HALL",'Raw - Sessions'!$G$5:$G$292,A15) -> 69 | C15: =IFERROR(AVERAGEIFS('Raw - Sessions'!$D$5:$D$292,'Raw - Sessions'!$K$5:$K$292,"BARBOURVILLE / CITY HALL",'Raw - Sessions'!$G$5:$G$292,A15),0) -> 0.5785628 | D15: =SUMIFS('Raw - Sessions'!$E$5:$E$292,'Raw - Sessions'!$K$5:$K$292,"BARBOURVILLE / CITY HALL",'Raw - Sessions'!$G$5:$G$292,A15) -> 1541.74
A17: Overnight sessions (started 22:00-6:00) | C17: =COUNTIFS('Raw - Sessions'!$K$5:$K$292,"BARBOURVILLE / CITY HALL",'Raw - Sessions'!$I$5:$I$292,TRUE()) -> 69
A20: Monthly Trend
A21: Month | B21: Sessions | C21: Revenue ($) | D21: Energy (kWh)
A22: 45931 | B22: =COUNTIFS('Raw - Sessions'!$K$5:$K$292,"BARBOURVILLE / CITY HALL",'Raw - Sessions'!$B$5:$B$292,">="&A22,'Raw - Sessions'!$B$5:$B$292,"<"&DATE(YEAR(A22),MONTH(A22)+1,1)) -> 22 | C22: =SUMIFS('Raw - Sessions'!$P$5:$P$292,'Raw - Sessions'!$K$5:$K$292,"BARBOURVILLE / CITY HALL",'Raw - Sessions'!$B$5:$B$292,">="&A22,'Raw - Sessions'!$B$5:$B$292,"<"&DATE(YEAR(A22),MONTH(A22)+1,1)) -> 182.76 | D22: =SUMIFS('Raw - Sessions'!$E$5:$E$292,'Raw - Sessions'!$K$5:$K$292,"BARBOURVILLE / CITY HALL",'Raw - Sessions'!$B$5:$B$292,">="&A22,'Raw - Sessions'!$B$5:$B$292,"<"&DATE(YEAR(A22),MONTH(A22)+1,1)) -> 385.2387
A23: 45962 | B23: =COUNTIFS('Raw - Sessions'!$K$5:$K$292,"BARBOURVILLE / CITY HALL",'Raw - Sessions'!$B$5:$B$292,">="&A23,'Raw - Sessions'!$B$5:$B$292,"<"&DATE(YEAR(A23),MONTH(A23)+1,1)) -> 24 | C23: =SUMIFS('Raw - Sessions'!$P$5:$P$292,'Raw - Sessions'!$K$5:$K$292,"BARBOURVILLE / CITY HALL",'Raw - Sessions'!$B$5:$B$292,">="&A23,'Raw - Sessions'!$B$5:$B$292,"<"&DATE(YEAR(A23),MONTH(A23)+1,1)) -> 394.07 | D23: =SUMIFS('Raw - Sessions'!$E$5:$E$292,'Raw - Sessions'!$K$5:$K$292,"BARBOURVILLE / CITY HALL",'Raw - Sessions'!$B$5:$B$292,">="&A23,'Raw - Sessions'!$B$5:$B$292,"<"&DATE(YEAR(A23),MONTH(A23)+1,1)) -> 775.995
A24: 45992 | B24: =COUNTIFS('Raw - Sessions'!$K$5:$K$292,"BARBOURVILLE / CITY HALL",'Raw - Sessions'!$B$5:$B$292,">="&A24,'Raw - Sessions'!$B$5:$B$292,"<"&DATE(YEAR(A24),MONTH(A24)+1,1)) -> 26 | C24: =SUMIFS('Raw - Sessions'!$P$5:$P$292,'Raw - Sessions'!$K$5:$K$292,"BARBOURVILLE / CITY HALL",'Raw - Sessions'!$B$5:$B$292,">="&A24,'Raw - Sessions'!$B$5:$B$292,"<"&DATE(YEAR(A24),MONTH(A24)+1,1)) -> 326.83 | D24: =SUMIFS('Raw - Sessions'!$E$5:$E$292,'Raw - Sessions'!$K$5:$K$292,"BARBOURVILLE / CITY HALL",'Raw - Sessions'!$B$5:$B$292,">="&A24,'Raw - Sessions'!$B$5:$B$292,"<"&DATE(YEAR(A24),MONTH(A24)+1,1)) -> 612.6473
A25: 46023 | B25: =COUNTIFS('Raw - Sessions'!$K$5:$K$292,"BARBOURVILLE / CITY HALL",'Raw - Sessions'!$B$5:$B$292,">="&A25,'Raw - Sessions'!$B$5:$B$292,"<"&DATE(YEAR(A25),MONTH(A25)+1,1)) -> 11 | C25: =SUMIFS('Raw - Sessions'!$P$5:$P$292,'Raw - Sessions'!$K$5:$K$292,"BARBOURVILLE / CITY HALL",'Raw - Sessions'!$B$5:$B$292,">="&A25,'Raw - Sessions'!$B$5:$B$292,"<"&DATE(YEAR(A25),MONTH(A25)+1,1)) -> 50.49 | D25: =SUMIFS('Raw - Sessions'!$E$5:$E$292,'Raw - Sessions'!$K$5:$K$292,"BARBOURVILLE / CITY HALL",'Raw - Sessions'!$B$5:$B$292,">="&A25,'Raw - Sessions'!$B$5:$B$292,"<"&DATE(YEAR(A25),MONTH(A25)+1,1)) -> 98.330102
A26: 46054 | B26: =COUNTIFS('Raw - Sessions'!$K$5:$K$292,"BARBOURVILLE / CITY HALL",'Raw - Sessions'!$B$5:$B$292,">="&A26,'Raw - Sessions'!$B$5:$B$292,"<"&DATE(YEAR(A26),MONTH(A26)+1,1)) -> 24 | C26: =SUMIFS('Raw - Sessions'!$P$5:$P$292,'Raw - Sessions'!$K$5:$K$292,"BARBOURVILLE / CITY HALL",'Raw - Sessions'!$B$5:$B$292,">="&A26,'Raw - Sessions'!$B$5:$B$292,"<"&DATE(YEAR(A26),MONTH(A26)+1,1)) -> 467.93 | D26: =SUMIFS('Raw - Sessions'!$E$5:$E$292,'Raw - Sessions'!$K$5:$K$292,"BARBOURVILLE / CITY HALL",'Raw - Sessions'!$B$5:$B$292,">="&A26,'Raw - Sessions'!$B$5:$B$292,"<"&DATE(YEAR(A26),MONTH(A26)+1,1)) -> 784.6669
A27: 46082 | B27: =COUNTIFS('Raw - Sessions'!$K$5:$K$292,"BARBOURVILLE / CITY HALL",'Raw - Sessions'!$B$5:$B$292,">="&A27,'Raw - Sessions'!$B$5:$B$292,"<"&DATE(YEAR(A27),MONTH(A27)+1,1)) -> 18 | C27: =SUMIFS('Raw - Sessions'!$P$5:$P$292,'Raw - Sessions'!$K$5:$K$292,"BARBOURVILLE / CITY HALL",'Raw - Sessions'!$B$5:$B$292,">="&A27,'Raw - Sessions'!$B$5:$B$292,"<"&DATE(YEAR(A27),MONTH(A27)+1,1)) -> 410.2 | D27: =SUMIFS('Raw - Sessions'!$E$5:$E$292,'Raw - Sessions'!$K$5:$K$292,"BARBOURVILLE / CITY HALL",'Raw - Sessions'!$B$5:$B$292,">="&A27,'Raw - Sessions'!$B$5:$B$292,"<"&DATE(YEAR(A27),MONTH(A27)+1,1)) -> 613.9706
A28: 46113 | B28: =COUNTIFS('Raw - Sessions'!$K$5:$K$292,"BARBOURVILLE / CITY HALL",'Raw - Sessions'!$B$5:$B$292,">="&A28,'Raw - Sessions'!$B$5:$B$292,"<"&DATE(YEAR(A28),MONTH(A28)+1,1)) -> 37 | C28: =SUMIFS('Raw - Sessions'!$P$5:$P$292,'Raw - Sessions'!$K$5:$K$292,"BARBOURVILLE / CITY HALL",'Raw - Sessions'!$B$5:$B$292,">="&A28,'Raw - Sessions'!$B$5:$B$292,"<"&DATE(YEAR(A28),MONTH(A28)+1,1)) -> 736.86 | D28: =SUMIFS('Raw - Sessions'!$E$5:$E$292,'Raw - Sessions'!$K$5:$K$292,"BARBOURVILLE / CITY HALL",'Raw - Sessions'!$B$5:$B$292,">="&A28,'Raw - Sessions'!$B$5:$B$292,"<"&DATE(YEAR(A28),MONTH(A28)+1,1)) -> 1125.8821
A29: 46143 | B29: =COUNTIFS('Raw - Sessions'!$K$5:$K$292,"BARBOURVILLE / CITY HALL",'Raw - Sessions'!$B$5:$B$292,">="&A29,'Raw - Sessions'!$B$5:$B$292,"<"&DATE(YEAR(A29),MONTH(A29)+1,1)) -> 31 | C29: =SUMIFS('Raw - Sessions'!$P$5:$P$292,'Raw - Sessions'!$K$5:$K$292,"BARBOURVILLE / CITY HALL",'Raw - Sessions'!$B$5:$B$292,">="&A29,'Raw - Sessions'!$B$5:$B$292,"<"&DATE(YEAR(A29),MONTH(A29)+1,1)) -> 537.16 | D29: =SUMIFS('Raw - Sessions'!$E$5:$E$292,'Raw - Sessions'!$K$5:$K$292,"BARBOURVILLE / CITY HALL",'Raw - Sessions'!$B$5:$B$292,">="&A29,'Raw - Sessions'!$B$5:$B$292,"<"&DATE(YEAR(A29),MONTH(A29)+1,1)) -> 766.1055
A30: 46174 | B30: =COUNTIFS('Raw - Sessions'!$K$5:$K$292,"BARBOURVILLE / CITY HALL",'Raw - Sessions'!$B$5:$B$292,">="&A30,'Raw - Sessions'!$B$5:$B$292,"<"&DATE(YEAR(A30),MONTH(A30)+1,1)) -> 40 | C30: =SUMIFS('Raw - Sessions'!$P$5:$P$292,'Raw - Sessions'!$K$5:$K$292,"BARBOURVILLE / CITY HALL",'Raw - Sessions'!$B$5:$B$292,">="&A30,'Raw - Sessions'!$B$5:$B$292,"<"&DATE(YEAR(A30),MONTH(A30)+1,1)) -> 405.05 | D30: =SUMIFS('Raw - Sessions'!$E$5:$E$292,'Raw - Sessions'!$K$5:$K$292,"BARBOURVILLE / CITY HALL",'Raw - Sessions'!$B$5:$B$292,">="&A30,'Raw - Sessions'!$B$5:$B$292,"<"&DATE(YEAR(A30),MONTH(A30)+1,1)) -> 568.0701
A31: 46204 | B31: =COUNTIFS('Raw - Sessions'!$K$5:$K$292,"BARBOURVILLE / CITY HALL",'Raw - Sessions'!$B$5:$B$292,">="&A31,'Raw - Sessions'!$B$5:$B$292,"<"&DATE(YEAR(A31),MONTH(A31)+1,1)) -> 6 | C31: =SUMIFS('Raw - Sessions'!$P$5:$P$292,'Raw - Sessions'!$K$5:$K$292,"BARBOURVILLE / CITY HALL",'Raw - Sessions'!$B$5:$B$292,">="&A31,'Raw - Sessions'!$B$5:$B$292,"<"&DATE(YEAR(A31),MONTH(A31)+1,1)) -> 66.56 | D31: =SUMIFS('Raw - Sessions'!$E$5:$E$292,'Raw - Sessions'!$K$5:$K$292,"BARBOURVILLE / CITY HALL",'Raw - Sessions'!$B$5:$B$292,">="&A31,'Raw - Sessions'!$B$5:$B$292,"<"&DATE(YEAR(A31),MONTH(A31)+1,1)) -> 93.5925
A34: Top States of Origin (sessions with known ZIP)
A35: Est. State | B35: Sessions
A36: ='Visitor Origin'!A5 -> KY | B36: =COUNTIFS('Raw - Sessions'!$K$5:$K$292,"BARBOURVILLE / CITY HALL",'Raw - Sessions'!$O$5:$O$292,A36) -> 89
A37: ='Visitor Origin'!A6 -> TN | B37: =COUNTIFS('Raw - Sessions'!$K$5:$K$292,"BARBOURVILLE / CITY HALL",'Raw - Sessions'!$O$5:$O$292,A37) -> 17
A38: ='Visitor Origin'!A7 -> OH | B38: =COUNTIFS('Raw - Sessions'!$K$5:$K$292,"BARBOURVILLE / CITY HALL",'Raw - Sessions'!$O$5:$O$292,A38) -> 9
A39: ='Visitor Origin'!A8 -> NC | B39: =COUNTIFS('Raw - Sessions'!$K$5:$K$292,"BARBOURVILLE / CITY HALL",'Raw - Sessions'!$O$5:$O$292,A39) -> 9
A40: ='Visitor Origin'!A9 -> IL | B40: =COUNTIFS('Raw - Sessions'!$K$5:$K$292,"BARBOURVILLE / CITY HALL",'Raw - Sessions'!$O$5:$O$292,A40) -> 1
A41: ='Visitor Origin'!A10 -> FL | B41: =COUNTIFS('Raw - Sessions'!$K$5:$K$292,"BARBOURVILLE / CITY HALL",'Raw - Sessions'!$O$5:$O$292,A41) -> 3
A42: ='Visitor Origin'!A11 -> SC | B42: =COUNTIFS('Raw - Sessions'!$K$5:$K$292,"BARBOURVILLE / CITY HALL",'Raw - Sessions'!$O$5:$O$292,A42) -> 3
A43: ='Visitor Origin'!A12 -> MI | B43: =COUNTIFS('Raw - Sessions'!$K$5:$K$292,"BARBOURVILLE / CITY HALL",'Raw - Sessions'!$O$5:$O$292,A43) -> 3
A44: ='Visitor Origin'!A13 -> WI | B44: =COUNTIFS('Raw - Sessions'!$K$5:$K$292,"BARBOURVILLE / CITY HALL",'Raw - Sessions'!$O$5:$O$292,A44) -> 3
A45: ='Visitor Origin'!A14 -> IN | B45: =COUNTIFS('Raw - Sessions'!$K$5:$K$292,"BARBOURVILLE / CITY HALL",'Raw - Sessions'!$O$5:$O$292,A45) -> 2
A46: ='Visitor Origin'!A15 -> GA | B46: =COUNTIFS('Raw - Sessions'!$K$5:$K$292,"BARBOURVILLE / CITY HALL",'Raw - Sessions'!$O$5:$O$292,A46) -> 2
A47: ='Visitor Origin'!A16 -> TX | B47: =COUNTIFS('Raw - Sessions'!$K$5:$K$292,"BARBOURVILLE / CITY HALL",'Raw - Sessions'!$O$5:$O$292,A47) -> 2
... A54: ='Visitor Origin'!A23 -> OK | B54: =COUNTIFS('Raw - Sessions'!$K$5:$K$292,"BARBOURVILLE / CITY HALL",'Raw - Sessions'!$O$5:$O$292,A54) -> 1
A56: States with 0 sessions for this charger are still listed for consistency with the combined Visitor Origin tab.

Sheet Daily Summary
A1: Daily Charging Activity Summary (All Stations Combined)
A2: One row per calendar day across the full 12-month export. Sessions/duration/energy pull live from Raw - Sessions; Charger Energy pulls live from Raw - Daily Energy.
A4: Total Sessions | C4: Days in Reporting Period | E4: Avg Sessions / Active Day | G4: Avg Charging Hours / Day (full period) | I4: Avg Energy / Day (kWh, full period) | K4: Avg Energy / Active Day (kWh) | M4: Avg Power While Charging (kW) | O4: Rural Benchmark (hrs/day, per requester)
A5: =COUNTA('Raw - Sessions'!A5:A292) -> 288 | C5: ='Raw - Daily Energy'!A369-'Raw - Daily Energy'!A5+1 -> 365 | E5: =SUM(B10:B374)/COUNTIF(B10:B374,">0") -> 2.028169 | G5: =SUM(C10:C374)/(A374-A10+1) -> 0.58362481 | I5: =SUM('Raw - Sessions'!E5:E292)/C5 -> 17.03207 | K5: =SUM('Raw - Sessions'!E5:E292)/SUM('Raw - Sessions'!AF5:AF292) -> 45.048591 | M5: =SUM('Raw - Sessions'!E5:E292)/SUM('Raw - Sessions'!D5:D292) -> 29.183252 | O5: 1.2
A8: Day-by-day detail
A9: Date | B9: Sessions | C9: Total Session Duration (hr) | D9: Total Session Energy (kWh) | E9: Charger Meter Energy (kWh) | F9: Total Revenue ($)
A10: ='Raw - Daily Energy'!A5 -> 45850 | B10: =COUNTIF('Raw - Sessions'!$R$5:$R$292,A10) -> 0 | C10: =SUMIF('Raw - Sessions'!$R$5:$R$292,A10,'Raw - Sessions'!$D$5:$D$292) -> 0 | D10: =SUMIF('Raw - Sessions'!$R$5:$R$292,A10,'Raw - Sessions'!$E$5:$E$292) -> 0 | E10: ='Raw - Daily Energy'!B5 -> 0 | F10: =SUMIF('Raw - Sessions'!$R$5:$R$292,A10,'Raw - Sessions'!$P$5:$P$292) -> 0
A11: ='Raw - Daily Energy'!A6 -> 45851 | B11: =COUNTIF('Raw - Sessions'!$R$5:$R$292,A11) -> 0 | C11: =SUMIF('Raw - Sessions'!$R$5:$R$292,A11,'Raw - Sessions'!$D$5:$D$292) -> 0 | D11: =SUMIF('Raw - Sessions'!$R$5:$R$292,A11,'Raw - Sessions'!$E$5:$E$292) -> 0 | E11: ='Raw - Daily Energy'!B6 -> 0 | F11: =SUMIF('Raw - Sessions'!$R$5:$R$292,A11,'Raw - Sessions'!$P$5:$P$292) -> 0
A12: ='Raw - Daily Energy'!A7 -> 45852 | B12: =COUNTIF('Raw - Sessions'!$R$5:$R$292,A12) -> 0 | C12: =SUMIF('Raw - Sessions'!$R$5:$R$292,A12,'Raw - Sessions'!$D$5:$D$292) -> 0 | D12: =SUMIF('Raw - Sessions'!$R$5:$R$292,A12,'Raw - Sessions'!$E$5:$E$292) -> 0 | E12: ='Raw - Daily Energy'!B7 -> 0 | F12: =SUMIF('Raw - Sessions'!$R$5:$R$292,A12,'Raw - Sessions'!$P$5:$P$292) -> 0
A13: ='Raw - Daily Energy'!A8 -> 45853 | B13: =COUNTIF('Raw - Sessions'!$R$5:$R$292,A13) -> 0 | C13: =SUMIF('Raw - Sessions'!$R$5:$R$292,A13,'Raw - Sessions'!$D$5:$D$292) -> 0 | D13: =SUMIF('Raw - Sessions'!$R$5:$R$292,A13,'Raw - Sessions'!$E$5:$E$292) -> 0 | E13: ='Raw - Daily Energy'!B8 -> 0 | F13: =SUMIF('Raw - Sessions'!$R$5:$R$292,A13,'Raw - Sessions'!$P$5:$P$292) -> 0
A14: ='Raw - Daily Energy'!A9 -> 45854 | B14: =COUNTIF('Raw - Sessions'!$R$5:$R$292,A14) -> 0 | C14: =SUMIF('Raw - Sessions'!$R$5:$R$292,A14,'Raw - Sessions'!$D$5:$D$292) -> 0 | D14: =SUMIF('Raw - Sessions'!$R$5:$R$292,A14,'Raw - Sessions'!$E$5:$E$292) -> 0 | E14: ='Raw - Daily Energy'!B9 -> 0 | F14: =SUMIF('Raw - Sessions'!$R$5:$R$292,A14,'Raw - Sessions'!$P$5:$P$292) -> 0
A15: ='Raw - Daily Energy'!A10 -> 45855 | B15: =COUNTIF('Raw - Sessions'!$R$5:$R$292,A15) -> 0 | C15: =SUMIF('Raw - Sessions'!$R$5:$R$292,A15,'Raw - Sessions'!$D$5:$D$292) -> 0 | D15: =SUMIF('Raw - Sessions'!$R$5:$R$292,A15,'Raw - Sessions'!$E$5:$E$292) -> 0 | E15: ='Raw - Daily Energy'!B10 -> 0 | F15: =SUMIF('Raw - Sessions'!$R$5:$R$292,A15,'Raw - Sessions'!$P$5:$P$292) -> 0
A16: ='Raw - Daily Energy'!A11 -> 45856 | B16: =COUNTIF('Raw - Sessions'!$R$5:$R$292,A16) -> 0 | C16: =SUMIF('Raw - Sessions'!$R$5:$R$292,A16,'Raw - Sessions'!$D$5:$D$292) -> 0 | D16: =SUMIF('Raw - Sessions'!$R$5:$R$292,A16,'Raw - Sessions'!$E$5:$E$292) -> 0 | E16: ='Raw - Daily Energy'!B11 -> 0 | F16: =SUMIF('Raw - Sessions'!$R$5:$R$292,A16,'Raw - Sessions'!$P$5:$P$292) -> 0
A17: ='Raw - Daily Energy'!A12 -> 45857 | B17: =COUNTIF('Raw - Sessions'!$R$5:$R$292,A17) -> 0 | C17: =SUMIF('Raw - Sessions'!$R$5:$R$292,A17,'Raw - Sessions'!$D$5:$D$292) -> 0 | D17: =SUMIF('Raw - Sessions'!$R$5:$R$292,A17,'Raw - Sessions'!$E$5:$E$292) -> 0 | E17: ='Raw - Daily Energy'!B12 -> 0 | F17: =SUMIF('Raw - Sessions'!$R$5:$R$292,A17,'Raw - Sessions'!$P$5:$P$292) -> 0
A18: ='Raw - Daily Energy'!A13 -> 45858 | B18: =COUNTIF('Raw - Sessions'!$R$5:$R$292,A18) -> 0 | C18: =SUMIF('Raw - Sessions'!$R$5:$R$292,A18,'Raw - Sessions'!$D$5:$D$292) -> 0 | D18: =SUMIF('Raw - Sessions'!$R$5:$R$292,A18,'Raw - Sessions'!$E$5:$E$292) -> 0 | E18: ='Raw - Daily Energy'!B13 -> 0 | F18: =SUMIF('Raw - Sessions'!$R$5:$R$292,A18,'Raw - Sessions'!$P$5:$P$292) -> 0
A19: ='Raw - Daily Energy'!A14 -> 45859 | B19: =COUNTIF('Raw - Sessions'!$R$5:$R$292,A19) -> 0 | C19: =SUMIF('Raw - Sessions'!$R$5:$R$292,A19,'Raw - Sessions'!$D$5:$D$292) -> 0 | D19: =SUMIF('Raw - Sessions'!$R$5:$R$292,A19,'Raw - Sessions'!$E$5:$E$292) -> 0 | E19: ='Raw - Daily Energy'!B14 -> 0 | F19: =SUMIF('Raw - Sessions'!$R$5:$R$292,A19,'Raw - Sessions'!$P$5:$P$292) -> 0
A20: ='Raw - Daily Energy'!A15 -> 45860 | B20: =COUNTIF('Raw - Sessions'!$R$5:$R$292,A20) -> 0 | C20: =SUMIF('Raw - Sessions'!$R$5:$R$292,A20,'Raw - Sessions'!$D$5:$D$292) -> 0 | D20: =SUMIF('Raw - Sessions'!$R$5:$R$292,A20,'Raw - Sessions'!$E$5:$E$292) -> 0 | E20: ='Raw - Daily Energy'!B15 -> 0 | F20: =SUMIF('Raw - Sessions'!$R$5:$R$292,A20,'Raw - Sessions'!$P$5:$P$292) -> 0
A21: ='Raw - Daily Energy'!A16 -> 45861 | B21: =COUNTIF('Raw - Sessions'!$R$5:$R$292,A21) -> 0 | C21: =SUMIF('Raw - Sessions'!$R$5:$R$292,A21,'Raw - Sessions'!$D$5:$D$292) -> 0 | D21: =SUMIF('Raw - Sessions'!$R$5:$R$292,A21,'Raw - Sessions'!$E$5:$E$292) -> 0 | E21: ='Raw - Daily Energy'!B16 -> 0 | F21: =SUMIF('Raw - Sessions'!$R$5:$R$292,A21,'Raw - Sessions'!$P$5:$P$292) -> 0
... A374: ='Raw - Daily Energy'!A369 -> 46214 | B374: =COUNTIF('Raw - Sessions'!$R$5:$R$292,A374) -> 0 | C374: =SUMIF('Raw - Sessions'!$R$5:$R$292,A374,'Raw - Sessions'!$D$5:$D$292) -> 0 | D374: =SUMIF('Raw - Sessions'!$R$5:$R$292,A374,'Raw - Sessions'!$E$5:$E$292) -> 0 | E374: ='Raw - Daily Energy'!B369 -> 0 | F374: =SUMIF('Raw - Sessions'!$R$5:$R$292,A374,'Raw - Sessions'!$P$5:$P$292) -> 0

Sheet Time of Day
A1: When People Charge (All Stations Combined): Time-of-Day & Overnight Patterns
A2: Day Segment: Morning 6:00-12:00, Day 12:00-18:00, Evening 18:00-22:00, Night 22:00-6:00 (based on Session Start).
A4: Day Segment | B4: Sessions | C4: % of All Sessions | D4: Avg Duration (hr) | E4: Total Energy (kWh) | F4: Avg % of Session Time >10kW
A5: Morning (6-12) | B5: =COUNTIF('Raw - Sessions'!$G$5:$G$292,A5) -> 4 | C5: =B5/SUM($B$5:$B$8) -> 0.013888889 | D5: =AVERAGEIF('Raw - Sessions'!$G$5:$G$292,A5,'Raw - Sessions'!$D$5:$D$292) -> 0.54180556 | E5: =SUMIF('Raw - Sessions'!$G$5:$G$292,A5,'Raw - Sessions'!$E$5:$E$292) -> 57.8262 | F5: =AVERAGEIF('Raw - Sessions'!$G$5:$G$292,A5,'Raw - Sessions'!$J$5:$J$292) -> 0.92745446
A6: Day (12-18) | B6: =COUNTIF('Raw - Sessions'!$G$5:$G$292,A6) -> 96 | C6: =B6/SUM($B$5:$B$8) -> 0.33333333 | D6: =AVERAGEIF('Raw - Sessions'!$G$5:$G$292,A6,'Raw - Sessions'!$D$5:$D$292) -> 0.72898727 | E6: =SUMIF('Raw - Sessions'!$G$5:$G$292,A6,'Raw - Sessions'!$E$5:$E$292) -> 2231.9797 | F6: =AVERAGEIF('Raw - Sessions'!$G$5:$G$292,A6,'Raw - Sessions'!$J$5:$J$292) -> 0.81222661
A7: Evening (18-22) | B7: =COUNTIF('Raw - Sessions'!$G$5:$G$292,A7) -> 102 | C7: =B7/SUM($B$5:$B$8) -> 0.35416667 | D7: =AVERAGEIF('Raw - Sessions'!$G$5:$G$292,A7,'Raw - Sessions'!$D$5:$D$292) -> 0.79065359 | E7: =SUMIF('Raw - Sessions'!$G$5:$G$292,A7,'Raw - Sessions'!$E$5:$E$292) -> 2266.2637 | F7: =AVERAGEIF('Raw - Sessions'!$G$5:$G$292,A7,'Raw - Sessions'!$J$5:$J$292) -> 0.8383424
A8: Night (22-6) | B8: =COUNTIF('Raw - Sessions'!$G$5:$G$292,A8) -> 86 | C8: =B8/SUM($B$5:$B$8) -> 0.29861111 | D8: =AVERAGEIF('Raw - Sessions'!$G$5:$G$292,A8,'Raw - Sessions'!$D$5:$D$292) -> 0.70030685 | E8: =SUMIF('Raw - Sessions'!$G$5:$G$292,A8,'Raw - Sessions'!$E$5:$E$292) -> 1660.6359 | F8: =AVERAGEIF('Raw - Sessions'!$G$5:$G$292,A8,'Raw - Sessions'!$J$5:$J$292) -> 0.75658178
A28: Overnight Charging Frequency
A29: Overnight sessions (started 22:00-6:00) | C29: =COUNTIF('Raw - Sessions'!$I$5:$I$292,TRUE()) -> 86
A30: Total days in reporting period | C30: ='Raw - Daily Energy'!A369-'Raw - Daily Energy'!A5+1 -> 365
A31: Distinct nights with at least one overnight session | C31: =SUM('Raw - Sessions'!$S$5:$S$292) -> 61 | D31: Counted directly from Raw - Sessions overnight-flagged rows grouped by calendar date (see Raw - Sessions column R).
A32: % of nights with overnight charging | C32: =C31/C30 -> 0.16712329

Sheet Frequency & Day of Week
A1: How Often the Charger Is Used (All Stations Combined)
A2: "Sessions" is used as the count of visits/uses - the export has no unique driver ID, so repeat visits by the same person cannot be told apart from different people. Formulas pull live from Raw - Sessions.
A5: Sessions by Day of Week
A6: Day of Week | B6: Sessions | C6: % of Total
A7: Monday | B7: =COUNTIF('Raw - Sessions'!$X$5:$X$292,A7) -> 32 | C7: =B7/SUM($B$7:$B$13) -> 0.11111111
A8: Tuesday | B8: =COUNTIF('Raw - Sessions'!$X$5:$X$292,A8) -> 42 | C8: =B8/SUM($B$7:$B$13) -> 0.14583333
A9: Wednesday | B9: =COUNTIF('Raw - Sessions'!$X$5:$X$292,A9) -> 28 | C9: =B9/SUM($B$7:$B$13) -> 0.097222222
A10: Thursday | B10: =COUNTIF('Raw - Sessions'!$X$5:$X$292,A10) -> 32 | C10: =B10/SUM($B$7:$B$13) -> 0.11111111
A11: Friday | B11: =COUNTIF('Raw - Sessions'!$X$5:$X$292,A11) -> 52 | C11: =B11/SUM($B$7:$B$13) -> 0.18055556
A12: Saturday | B12: =COUNTIF('Raw - Sessions'!$X$5:$X$292,A12) -> 53 | C12: =B12/SUM($B$7:$B$13) -> 0.18402778
A13: Sunday | B13: =COUNTIF('Raw - Sessions'!$X$5:$X$292,A13) -> 49 | C13: =B13/SUM($B$7:$B$13) -> 0.17013889
A16: Sessions per Week (Mon-start weeks)
A17: Week Start | B17: Sessions | C17: Energy (kWh) | D17: Revenue ($)
A18: 45943 | B18: =COUNTIF('Raw - Sessions'!$Y$5:$Y$292,A18) -> 3 | C18: =SUMIF('Raw - Sessions'!$Y$5:$Y$292,A18,'Raw - Sessions'!$E$5:$E$292) -> 22.571108 | D18: =SUMIF('Raw - Sessions'!$Y$5:$Y$292,A18,'Raw - Sessions'!$P$5:$P$292) -> 3.53
A19: 45950 | B19: =COUNTIF('Raw - Sessions'!$Y$5:$Y$292,A19) -> 17 | C19: =SUMIF('Raw - Sessions'!$Y$5:$Y$292,A19,'Raw - Sessions'!$E$5:$E$292) -> 225.06146 | D19: =SUMIF('Raw - Sessions'!$Y$5:$Y$292,A19,'Raw - Sessions'!$P$5:$P$292) -> 98.16
A20: 45957 | B20: =COUNTIF('Raw - Sessions'!$Y$5:$Y$292,A20) -> 11 | C20: =SUMIF('Raw - Sessions'!$Y$5:$Y$292,A20,'Raw - Sessions'!$E$5:$E$292) -> 235.2913 | D20: =SUMIF('Raw - Sessions'!$Y$5:$Y$292,A20,'Raw - Sessions'!$P$5:$P$292) -> 126.14
A21: 45964 | B21: =COUNTIF('Raw - Sessions'!$Y$5:$Y$292,A21) -> 6 | C21: =SUMIF('Raw - Sessions'!$Y$5:$Y$292,A21,'Raw - Sessions'!$E$5:$E$292) -> 186.2436 | D21: =SUMIF('Raw - Sessions'!$Y$5:$Y$292,A21,'Raw - Sessions'!$P$5:$P$292) -> 94.05
A22: 45971 | B22: =COUNTIF('Raw - Sessions'!$Y$5:$Y$292,A22) -> 7 | C22: =SUMIF('Raw - Sessions'!$Y$5:$Y$292,A22,'Raw - Sessions'!$E$5:$E$292) -> 182.08606 | D22: =SUMIF('Raw - Sessions'!$Y$5:$Y$292,A22,'Raw - Sessions'!$P$5:$P$292) -> 92.64
A23: 45978 | B23: =COUNTIF('Raw - Sessions'!$Y$5:$Y$292,A23) -> 3 | C23: =SUMIF('Raw - Sessions'!$Y$5:$Y$292,A23,'Raw - Sessions'!$E$5:$E$292) -> 134.1563 | D23: =SUMIF('Raw - Sessions'!$Y$5:$Y$292,A23,'Raw - Sessions'!$P$5:$P$292) -> 70.5
A24: 45985 | B24: =COUNTIF('Raw - Sessions'!$Y$5:$Y$292,A24) -> 9 | C24: =SUMIF('Raw - Sessions'!$Y$5:$Y$292,A24,'Raw - Sessions'!$E$5:$E$292) -> 204.88278 | D24: =SUMIF('Raw - Sessions'!$Y$5:$Y$292,A24,'Raw - Sessions'!$P$5:$P$292) -> 104.89
A25: 45992 | B25: =COUNTIF('Raw - Sessions'!$Y$5:$Y$292,A25) -> 3 | C25: =SUMIF('Raw - Sessions'!$Y$5:$Y$292,A25,'Raw - Sessions'!$E$5:$E$292) -> 45.4715 | D25: =SUMIF('Raw - Sessions'!$Y$5:$Y$292,A25,'Raw - Sessions'!$P$5:$P$292) -> 23.17
A26: 45999 | B26: =COUNTIF('Raw - Sessions'!$Y$5:$Y$292,A26) -> 4 | C26: =SUMIF('Raw - Sessions'!$Y$5:$Y$292,A26,'Raw - Sessions'!$E$5:$E$292) -> 145.33441 | D26: =SUMIF('Raw - Sessions'!$Y$5:$Y$292,A26,'Raw - Sessions'!$P$5:$P$292) -> 104.5
A27: 46006 | B27: =COUNTIF('Raw - Sessions'!$Y$5:$Y$292,A27) -> 11 | C27: =SUMIF('Raw - Sessions'!$Y$5:$Y$292,A27,'Raw - Sessions'!$E$5:$E$292) -> 217.19 | D27: =SUMIF('Raw - Sessions'!$Y$5:$Y$292,A27,'Raw - Sessions'!$P$5:$P$292) -> 138.42
A28: 46013 | B28: =COUNTIF('Raw - Sessions'!$Y$5:$Y$292,A28) -> 14 | C28: =SUMIF('Raw - Sessions'!$Y$5:$Y$292,A28,'Raw - Sessions'!$E$5:$E$292) -> 325.92236 | D28: =SUMIF('Raw - Sessions'!$Y$5:$Y$292,A28,'Raw - Sessions'!$P$5:$P$292) -> 201.67
A29: 46020 | B29: =COUNTIF('Raw - Sessions'!$Y$5:$Y$292,A29) -> 3 | C29: =SUMIF('Raw - Sessions'!$Y$5:$Y$292,A29,'Raw - Sessions'!$E$5:$E$292) -> 42.590099 | D29: =SUMIF('Raw - Sessions'!$Y$5:$Y$292,A29,'Raw - Sessions'!$P$5:$P$292) -> 18.25
... A56: 46209 | B56: =COUNTIF('Raw - Sessions'!$Y$5:$Y$292,A56) -> 2 | C56: =SUMIF('Raw - Sessions'!$Y$5:$Y$292,A56,'Raw - Sessions'!$E$5:$E$292) -> 41.392389 | D56: =SUMIF('Raw - Sessions'!$Y$5:$Y$292,A56,'Raw - Sessions'!$P$5:$P$292) -> 46.17
A57: Average / week | B57: =AVERAGE(B18:B56) -> 7.3846154

Sheet Revenue & Economic Impact
A1: Revenue & Economic Impact (All Stations Combined)
A2: Figures pull live from Raw - Sessions billing columns (Gross/Payout Amount, matched from the Organization Statement export).
A4: Total Gross Revenue | C4: Total Payout to Host | E4: Avg Revenue / Session | G4: Avg $ per kWh Delivered
A5: =SUM('Raw - Sessions'!P5:P292) -> 4036.12 | C5: =SUM('Raw - Sessions'!Q5:Q292) -> 3415.92 | E5: =AVERAGE('Raw - Sessions'!P5:P292) -> 17.174979 | G5: =C5/SUM('Raw - Sessions'!E5:E292) -> 0.54947431
A9: Monthly Trend
A10: Month Start | B10: Sessions | C10: Revenue ($) | D10: Energy (kWh)
A11: 45931 | B11: =COUNTIFS('Raw - Sessions'!$B$5:$B$292,">="&A11,'Raw - Sessions'!$B$5:$B$292,"<"&DATE(YEAR(A11),MONTH(A11)+1,1)) -> 27 | C11: =SUMIFS('Raw - Sessions'!$P$5:$P$292,'Raw - Sessions'!$B$5:$B$292,">="&A11,'Raw - Sessions'!$B$5:$B$292,"<"&DATE(YEAR(A11),MONTH(A11)+1,1)) -> 188.56 | D11: =SUMIFS('Raw - Sessions'!$E$5:$E$292,'Raw - Sessions'!$B$5:$B$292,">="&A11,'Raw - Sessions'!$B$5:$B$292,"<"&DATE(YEAR(A11),MONTH(A11)+1,1)) -> 407.11997
A12: 45962 | B12: =COUNTIFS('Raw - Sessions'!$B$5:$B$292,">="&A12,'Raw - Sessions'!$B$5:$B$292,"<"&DATE(YEAR(A12),MONTH(A12)+1,1)) -> 29 | C12: =SUMIFS('Raw - Sessions'!$P$5:$P$292,'Raw - Sessions'!$B$5:$B$292,">="&A12,'Raw - Sessions'!$B$5:$B$292,"<"&DATE(YEAR(A12),MONTH(A12)+1,1)) -> 401.35 | D12: =SUMIFS('Raw - Sessions'!$E$5:$E$292,'Raw - Sessions'!$B$5:$B$292,">="&A12,'Raw - Sessions'!$B$5:$B$292,"<"&DATE(YEAR(A12),MONTH(A12)+1,1)) -> 783.17265
A13: 45992 | B13: =COUNTIFS('Raw - Sessions'!$B$5:$B$292,">="&A13,'Raw - Sessions'!$B$5:$B$292,"<"&DATE(YEAR(A13),MONTH(A13)+1,1)) -> 33 | C13: =SUMIFS('Raw - Sessions'!$P$5:$P$292,'Raw - Sessions'!$B$5:$B$292,">="&A13,'Raw - Sessions'!$B$5:$B$292,"<"&DATE(YEAR(A13),MONTH(A13)+1,1)) -> 479.65 | D13: =SUMIFS('Raw - Sessions'!$E$5:$E$292,'Raw - Sessions'!$B$5:$B$292,">="&A13,'Raw - Sessions'!$B$5:$B$292,"<"&DATE(YEAR(A13),MONTH(A13)+1,1)) -> 764.13596
A14: 46023 | B14: =COUNTIFS('Raw - Sessions'!$B$5:$B$292,">="&A14,'Raw - Sessions'!$B$5:$B$292,"<"&DATE(YEAR(A14),MONTH(A14)+1,1)) -> 11 | C14: =SUMIFS('Raw - Sessions'!$P$5:$P$292,'Raw - Sessions'!$B$5:$B$292,">="&A14,'Raw - Sessions'!$B$5:$B$292,"<"&DATE(YEAR(A14),MONTH(A14)+1,1)) -> 50.49 | D14: =SUMIFS('Raw - Sessions'!$E$5:$E$292,'Raw - Sessions'!$B$5:$B$292,">="&A14,'Raw - Sessions'!$B$5:$B$292,"<"&DATE(YEAR(A14),MONTH(A14)+1,1)) -> 98.330102
A15: 46054 | B15: =COUNTIFS('Raw - Sessions'!$B$5:$B$292,">="&A15,'Raw - Sessions'!$B$5:$B$292,"<"&DATE(YEAR(A15),MONTH(A15)+1,1)) -> 27 | C15: =SUMIFS('Raw - Sessions'!$P$5:$P$292,'Raw - Sessions'!$B$5:$B$292,">="&A15,'Raw - Sessions'!$B$5:$B$292,"<"&DATE(YEAR(A15),MONTH(A15)+1,1)) -> 503.39 | D15: =SUMIFS('Raw - Sessions'!$E$5:$E$292,'Raw - Sessions'!$B$5:$B$292,">="&A15,'Raw - Sessions'!$B$5:$B$292,"<"&DATE(YEAR(A15),MONTH(A15)+1,1)) -> 807.30535
A16: 46082 | B16: =COUNTIFS('Raw - Sessions'!$B$5:$B$292,">="&A16,'Raw - Sessions'!$B$5:$B$292,"<"&DATE(YEAR(A16),MONTH(A16)+1,1)) -> 21 | C16: =SUMIFS('Raw - Sessions'!$P$5:$P$292,'Raw - Sessions'!$B$5:$B$292,">="&A16,'Raw - Sessions'!$B$5:$B$292,"<"&DATE(YEAR(A16),MONTH(A16)+1,1)) -> 462.35 | D16: =SUMIFS('Raw - Sessions'!$E$5:$E$292,'Raw - Sessions'!$B$5:$B$292,">="&A16,'Raw - Sessions'!$B$5:$B$292,"<"&DATE(YEAR(A16),MONTH(A16)+1,1)) -> 655.18335
A17: 46113 | B17: =COUNTIFS('Raw - Sessions'!$B$5:$B$292,">="&A17,'Raw - Sessions'!$B$5:$B$292,"<"&DATE(YEAR(A17),MONTH(A17)+1,1)) -> 47 | C17: =SUMIFS('Raw - Sessions'!$P$5:$P$292,'Raw - Sessions'!$B$5:$B$292,">="&A17,'Raw - Sessions'!$B$5:$B$292,"<"&DATE(YEAR(A17),MONTH(A17)+1,1)) -> 825.21 | D17: =SUMIFS('Raw - Sessions'!$E$5:$E$292,'Raw - Sessions'!$B$5:$B$292,">="&A17,'Raw - Sessions'!$B$5:$B$292,"<"&DATE(YEAR(A17),MONTH(A17)+1,1)) -> 1195.588
A18: 46143 | B18: =COUNTIFS('Raw - Sessions'!$B$5:$B$292,">="&A18,'Raw - Sessions'!$B$5:$B$292,"<"&DATE(YEAR(A18),MONTH(A18)+1,1)) -> 40 | C18: =SUMIFS('Raw - Sessions'!$P$5:$P$292,'Raw - Sessions'!$B$5:$B$292,">="&A18,'Raw - Sessions'!$B$5:$B$292,"<"&DATE(YEAR(A18),MONTH(A18)+1,1)) -> 606.14 | D18: =SUMIFS('Raw - Sessions'!$E$5:$E$292,'Raw - Sessions'!$B$5:$B$292,">="&A18,'Raw - Sessions'!$B$5:$B$292,"<"&DATE(YEAR(A18),MONTH(A18)+1,1)) -> 818.17509
A19: 46174 | B19: =COUNTIFS('Raw - Sessions'!$B$5:$B$292,">="&A19,'Raw - Sessions'!$B$5:$B$292,"<"&DATE(YEAR(A19),MONTH(A19)+1,1)) -> 46 | C19: =SUMIFS('Raw - Sessions'!$P$5:$P$292,'Raw - Sessions'!$B$5:$B$292,">="&A19,'Raw - Sessions'!$B$5:$B$292,"<"&DATE(YEAR(A19),MONTH(A19)+1,1)) -> 425.72 | D19: =SUMIFS('Raw - Sessions'!$E$5:$E$292,'Raw - Sessions'!$B$5:$B$292,">="&A19,'Raw - Sessions'!$B$5:$B$292,"<"&DATE(YEAR(A19),MONTH(A19)+1,1)) -> 581.79773
A20: 46204 | B20: =COUNTIFS('Raw - Sessions'!$B$5:$B$292,">="&A20,'Raw - Sessions'!$B$5:$B$292,"<"&DATE(YEAR(A20),MONTH(A20)+1,1)) -> 7 | C20: =SUMIFS('Raw - Sessions'!$P$5:$P$292,'Raw - Sessions'!$B$5:$B$292,">="&A20,'Raw - Sessions'!$B$5:$B$292,"<"&DATE(YEAR(A20),MONTH(A20)+1,1)) -> 93.26 | D20: =SUMIFS('Raw - Sessions'!$E$5:$E$292,'Raw - Sessions'!$B$5:$B$292,">="&A20,'Raw - Sessions'!$B$5:$B$292,"<"&DATE(YEAR(A20),MONTH(A20)+1,1)) -> 105.89729
A23: Economic Impact Context (for presentation to the mayor)
A24: This charging site generated the totals above directly through session fees. Separately, published research on EV charging and local business activity provides a benchmark for the wider "dwell time" effect:
A25: A 2024 MIT/Nature Communications study of over 4,000 California charging stations found that installing a charger boosted annual spending at each nearby business by roughly $1,478 (2019 data) to $404 (2021-2023 data), as drivers use charging time to shop or dine nearby (source: MIT News / Nature Communications, "Effects of electric vehicle charging stations on the economic vitality of local businesses," 2024).
A26: The U.S. DOT Rural EV Toolkit similarly notes that because fast charging still takes meaningful time, rural EV drivers tend to combine a charging stop with visits to nearby stores, restaurants, or attractions - a "captive dwell time" that downtown businesses can capture.
A27: ="Barbourville-specific signal: of the "&(COUNTIF('Raw - Sessions'!$O$5:$O$292,"KY")+COUNTIFS('Raw - Sessions'!$O$5:$O$292,"<>",'Raw - Sessions'!$O$5:$O$292,"<>KY"))&" sessions with a known driver location, "&COUNTIF('Raw - Sessions'!$O$5:$O$292,"KY")&" originated in Kentucky and "&COUNTIFS('Raw - Sessions'!$O$5:$O$292,"<>",'Raw - Sessions'!$O$5:$O$292,"<>KY")&" came from other states (see Visitor Origin tab) - consistent with the station drawing highway/through traffic near US-25E, not only local drivers." -> Barbourville-specific signal: of the 164 sessions with a known driver location, 96 originated in Kentucky and 68 came from other states (see Visitor Origin tab) - consistent with the station drawing highway/through traffic near US-25E, not only local drivers.
A28: These figures are provided as directional context, not a Barbourville-specific economic study - the city would need its own downtown-business survey to quantify local spend per charging stop.

Sheet Financial Reconciliation
A1: Financial Reconciliation: What Drivers Pay, What Fees/Taxes Take, What the Owner Keeps
A2: Figures pull live from Raw - Sessions billing/rate columns (matched from the Organization Statement export, 235 of 288 sessions have billing data).
A4: Total Gross (What Drivers Paid) | C4: Total Fees + Taxes Withheld | E4: Total Payout (What Owner Kept) | G4: Fees+Taxes as % of Gross
A5: =SUM('Raw - Sessions'!$P$5:$P$292) -> 4036.12 | C5: =SUM('Raw - Sessions'!$W$5:$W$292) -> 619.21 | E5: =SUM('Raw - Sessions'!$Q$5:$Q$292) -> 3415.92 | G5: =C5/A5 -> 0.15341714
A9: Where the Fees & Taxes Go
A10: Component | B10: Total ($) | C10: What it is
A11: Sales Tax | B11: =SUM('Raw - Sessions'!Z5:Z292) -> 212.16 | C11: State/local sales tax collected on the transaction
A12: Service Fee (ChargePoint) | B12: =SUM('Raw - Sessions'!AE5:AE292) -> 30.57 | C12: ChargePoint's per-session service fee
A13: Flex Billing Service Fee | B13: =SUM('Raw - Sessions'!AD5:AD292) -> 376.48 | C13: ChargePoint's payment-processing fee
A14: Excise Tax | B14: =SUM('Raw - Sessions'!AA5:AA292) -> 0 | C14: Not applied in this dataset (all $0)
A15: Other Taxes | B15: =SUM('Raw - Sessions'!AB5:AB292) -> 0 | C15: Not applied in this dataset (all $0)
A16: Service Fee Tax | B16: =SUM('Raw - Sessions'!AC5:AC292) -> 0 | C16: Not applied in this dataset (all $0)
A17: Every total above is a live SUM formula against Raw - Sessions columns Z:AE - edit a fee/tax value there and these update automatically.
A20: Full Reconciliation Check — Every Session
A21: The posted per-kWh rate changed over time at both stations, per the Pricing Rule Name on each session: $0.25/kWh at launch (Oct 15-21, 2025), $0.40/kWh from Oct 22, 2025 to Mar 8, 2026, and $0.50/kWh from Mar 11, 2026 onward. Multiplying Rate × Energy (kWh) gives the pure energy charge - it does NOT equal the pre-tax session charge (Net Session Fee) for most sessions; the gap grows with session length (correlation with duration ≈ 0.88), consistent with a time-based add-on layered on top of the per-kWh rate (roughly $3.60/hour, R² ≈ 0.97 in a one-time regression against duration - this specific regression is not a live formula, since Excel has no native regression-against-duration function; re-run it in Python if the underlying data changes materially).
A22: ="CHECK 1 — Gross Amount = Net Session Fee + Sales Tax + Service Fee (+ Excise/Other/Service Fee Tax, all $0 here): this reconciles exactly for "&(A27-C27)&" of "&A27&" billed sessions. "&C27&" session(s) fail this check by more than $0.02." -> CHECK 1 — Gross Amount = Net Session Fee + Sales Tax + Service Fee (+ Excise/Other/Service Fee Tax, all $0 here): this reconciles exactly for 235 of 235 billed sessions. 0 session(s) fail this check by more than $0.02.
A23: ="CHECK 2 — Payout Amount = Gross Amount − Service Fee − Flex Billing Service Fee − Sales Tax: this reconciles for "&(A27-E27)&" of "&A27&" billed sessions. "&E27&" session(s) do NOT reconcile and are flagged in red in the table below." -> CHECK 2 — Payout Amount = Gross Amount − Service Fee − Flex Billing Service Fee − Sales Tax: this reconciles for 234 of 235 billed sessions. 1 session(s) do NOT reconcile and are flagged in red in the table below.
A24: =IF(AND(C27=0,E27=0),"✓ All sessions reconcile - no discrepancies found.","⚠ "&(C27+E27)&" check(s) failed - total discrepancy found: $"&TEXT(G27,"0.00")&". Use the filter arrows on the Gross Check / Payout Check columns below to isolate the flagged row(s).") -> ⚠ 1 check(s) failed - total discrepancy found: $0.99. Use the filter arrows on the Gross Check / Payout Check columns below to isolate the flagged row(s).
A26: Billed Sessions Checked | C26: Gross Amount Mismatches | E26: Payout Amount Mismatches | G26: Total $ Discrepancy Found
A27: =COUNT(E31:E318) -> 235 | C27: =COUNTIF(L31:L318,"MISMATCH") -> 0 | E27: =COUNTIF(P31:P318,"MISMATCH") -> 1 | G27: =SUMPRODUCT((L31:L318="MISMATCH")*ABS(N(K31:K318)))+SUMPRODUCT((P31:P318="MISMATCH")*ABS(N(O31:O318))) -> 0.99
A29: Full Reconciliation Table — All 288 Sessions (blank = no billing data for that session)
A30: Session ID | B30: Station | C30: Rate ($/kWh) | D30: Energy (kWh) | E30: Net Session Fee | F30: Sales Tax | G30: Service Fee | H30: Flex Billing Fee | I30: Gross Amount | J30: Calc. Gross | K30: Gross Diff | L30: Gross Check | M30: Payout Amount | N30: Calc. Payout | O30: Payout Diff | P30: Payout Check
A31: ='Raw - Sessions'!A5 -> 4511566811 | B31: ='Raw - Sessions'!K5 -> BARBOURVILLE / TOURISM | C31: =IF(ISBLANK('Raw - Sessions'!U5),"",'Raw - Sessions'!T5) -> 0.25 | D31: ='Raw - Sessions'!E5 -> 8.483508 | E31: =IF(ISBLANK('Raw - Sessions'!U5),"",'Raw - Sessions'!U5) -> 2.12 | F31: =IF(ISBLANK('Raw - Sessions'!U5),"",'Raw - Sessions'!Z5) -> 0.13 | G31: =IF(ISBLANK('Raw - Sessions'!U5),"",'Raw - Sessions'!AE5) -> 0 | H31: =IF(ISBLANK('Raw - Sessions'!U5),"",'Raw - Sessions'!AD5) -> 0.21 | I31: =IF(ISBLANK('Raw - Sessions'!U5),"",'Raw - Sessions'!P5) -> 2.25 | J31: =IF(E31="","",E31+F31+G31+'Raw - Sessions'!AA5+'Raw - Sessions'!AB5+'Raw - Sessions'!AC5) -> 2.25 | K31: =IF(E31="","",I31-J31) -> 0 | L31: =IF(E31="","",IF(ABS(K31)>0.02,"MISMATCH","OK")) -> OK | M31: =IF(ISBLANK('Raw - Sessions'!U5),"",'Raw - Sessions'!Q5) -> 1.91 | N31: =IF(E31="","",I31-G31-H31-F31) -> 1.91 | O31: =IF(E31="","",M31-N31) -> 0 | P31: =IF(E31="","",IF(ABS(O31)>0.02,"MISMATCH","OK")) -> OK
A32: ='Raw - Sessions'!A6 -> 4523627951 | B32: ='Raw - Sessions'!K6 -> BARBOURVILLE / CITY HALL | C32: =IF(ISBLANK('Raw - Sessions'!U6),"",'Raw - Sessions'!T6) -> 0.25 | D32: ='Raw - Sessions'!E6 -> 4.8593 | E32: =IF(ISBLANK('Raw - Sessions'!U6),"",'Raw - Sessions'!U6) -> 1.21 | F32: =IF(ISBLANK('Raw - Sessions'!U6),"",'Raw - Sessions'!Z6) -> 0.07 | G32: =IF(ISBLANK('Raw - Sessions'!U6),"",'Raw - Sessions'!AE6) -> 0 | H32: =IF(ISBLANK('Raw - Sessions'!U6),"",'Raw - Sessions'!AD6) -> 0.12 | I32: =IF(ISBLANK('Raw - Sessions'!U6),"",'Raw - Sessions'!P6) -> 1.28 | J32: =IF(E32="","",E32+F32+G32+'Raw - Sessions'!AA6+'Raw - Sessions'!AB6+'Raw - Sessions'!AC6) -> 1.28 | K32: =IF(E32="","",I32-J32) -> 0 | L32: =IF(E32="","",IF(ABS(K32)>0.02,"MISMATCH","OK")) -> OK | M32: =IF(ISBLANK('Raw - Sessions'!U6),"",'Raw - Sessions'!Q6) -> 1.09 | N32: =IF(E32="","",I32-G32-H32-F32) -> 1.09 | O32: =IF(E32="","",M32-N32) -> 0 | P32: =IF(E32="","",IF(ABS(O32)>0.02,"MISMATCH","OK")) -> OK
A33: ='Raw - Sessions'!A7 -> 4524317961 | B33: ='Raw - Sessions'!K7 -> BARBOURVILLE / CITY HALL | C33: =IF(ISBLANK('Raw - Sessions'!U7),"",'Raw - Sessions'!T7) | D33: ='Raw - Sessions'!E7 -> 9.2283 | E33: =IF(ISBLANK('Raw - Sessions'!U7),"",'Raw - Sessions'!U7) | F33: =IF(ISBLANK('Raw - Sessions'!U7),"",'Raw - Sessions'!Z7) | G33: =IF(ISBLANK('Raw - Sessions'!U7),"",'Raw - Sessions'!AE7) | H33: =IF(ISBLANK('Raw - Sessions'!U7),"",'Raw - Sessions'!AD7) | I33: =IF(ISBLANK('Raw - Sessions'!U7),"",'Raw - Sessions'!P7) | J33: =IF(E33="","",E33+F33+G33+'Raw - Sessions'!AA7+'Raw - Sessions'!AB7+'Raw - Sessions'!AC7) | K33: =IF(E33="","",I33-J33) | L33: =IF(E33="","",IF(ABS(K33)>0.02,"MISMATCH","OK")) | M33: =IF(ISBLANK('Raw - Sessions'!U7),"",'Raw - Sessions'!Q7) | N33: =IF(E33="","",I33-G33-H33-F33) | O33: =IF(E33="","",M33-N33) | P33: =IF(E33="","",IF(ABS(O33)>0.02,"MISMATCH","OK"))
A34: ='Raw - Sessions'!A8 -> 4526984361 | B34: ='Raw - Sessions'!K8 -> BARBOURVILLE / CITY HALL | C34: =IF(ISBLANK('Raw - Sessions'!U8),"",'Raw - Sessions'!T8) | D34: ='Raw - Sessions'!E8 -> 0 | E34: =IF(ISBLANK('Raw - Sessions'!U8),"",'Raw - Sessions'!U8) | F34: =IF(ISBLANK('Raw - Sessions'!U8),"",'Raw - Sessions'!Z8) | G34: =IF(ISBLANK('Raw - Sessions'!U8),"",'Raw - Sessions'!AE8) | H34: =IF(ISBLANK('Raw - Sessions'!U8),"",'Raw - Sessions'!AD8) | I34: =IF(ISBLANK('Raw - Sessions'!U8),"",'Raw - Sessions'!P8) | J34: =IF(E34="","",E34+F34+G34+'Raw - Sessions'!AA8+'Raw - Sessions'!AB8+'Raw - Sessions'!AC8) | K34: =IF(E34="","",I34-J34) | L34: =IF(E34="","",IF(ABS(K34)>0.02,"MISMATCH","OK")) | M34: =IF(ISBLANK('Raw - Sessions'!U8),"",'Raw - Sessions'!Q8) | N34: =IF(E34="","",I34-G34-H34-F34) | O34: =IF(E34="","",M34-N34) | P34: =IF(E34="","",IF(ABS(O34)>0.02,"MISMATCH","OK"))
A35: ='Raw - Sessions'!A9 -> 4526989521 | B35: ='Raw - Sessions'!K9 -> BARBOURVILLE / CITY HALL | C35: =IF(ISBLANK('Raw - Sessions'!U9),"",'Raw - Sessions'!T9) -> 0.25 | D35: ='Raw - Sessions'!E9 -> 26.1175 | E35: =IF(ISBLANK('Raw - Sessions'!U9),"",'Raw - Sessions'!U9) -> 6.53 | F35: =IF(ISBLANK('Raw - Sessions'!U9),"",'Raw - Sessions'!Z9) -> 0.39 | G35: =IF(ISBLANK('Raw - Sessions'!U9),"",'Raw - Sessions'!AE9) -> 0 | H35: =IF(ISBLANK('Raw - Sessions'!U9),"",'Raw - Sessions'!AD9) -> 0.65 | I35: =IF(ISBLANK('Raw - Sessions'!U9),"",'Raw - Sessions'!P9) -> 6.92 | J35: =IF(E35="","",E35+F35+G35+'Raw - Sessions'!AA9+'Raw - Sessions'!AB9+'Raw - Sessions'!AC9) -> 6.92 | K35: =IF(E35="","",I35-J35) -> 0 | L35: =IF(E35="","",IF(ABS(K35)>0.02,"MISMATCH","OK")) -> OK | M35: =IF(ISBLANK('Raw - Sessions'!U9),"",'Raw - Sessions'!Q9) -> 5.88 | N35: =IF(E35="","",I35-G35-H35-F35) -> 5.88 | O35: =IF(E35="","",M35-N35) -> 0 | P35: =IF(E35="","",IF(ABS(O35)>0.02,"MISMATCH","OK")) -> OK
A36: ='Raw - Sessions'!A10 -> 4530183221 | B36: ='Raw - Sessions'!K10 -> BARBOURVILLE / CITY HALL | C36: =IF(ISBLANK('Raw - Sessions'!U10),"",'Raw - Sessions'!T10) -> 0.25 | D36: ='Raw - Sessions'!E10 -> 42.2076 | E36: =IF(ISBLANK('Raw - Sessions'!U10),"",'Raw - Sessions'!U10) -> 10.55 | F36: =IF(ISBLANK('Raw - Sessions'!U10),"",'Raw - Sessions'!Z10) -> 0.63 | G36: =IF(ISBLANK('Raw - Sessions'!U10),"",'Raw - Sessions'!AE10) -> 0 | H36: =IF(ISBLANK('Raw - Sessions'!U10),"",'Raw - Sessions'!AD10) -> 1.05 | I36: =IF(ISBLANK('Raw - Sessions'!U10),"",'Raw - Sessions'!P10) -> 11.18 | J36: =IF(E36="","",E36+F36+G36+'Raw - Sessions'!AA10+'Raw - Sessions'!AB10+'Raw - Sessions'!AC10) -> 11.18 | K36: =IF(E36="","",I36-J36) -> 0 | L36: =IF(E36="","",IF(ABS(K36)>0.02,"MISMATCH","OK")) -> OK | M36: =IF(ISBLANK('Raw - Sessions'!U10),"",'Raw - Sessions'!Q10) -> 9.5 | N36: =IF(E36="","",I36-G36-H36-F36) -> 9.5 | O36: =IF(E36="","",M36-N36) -> 0 | P36: =IF(E36="","",IF(ABS(O36)>0.02,"MISMATCH","OK")) -> OK
A37: ='Raw - Sessions'!A11 -> 4530304121 | B37: ='Raw - Sessions'!K11 -> BARBOURVILLE / TOURISM | C37: =IF(ISBLANK('Raw - Sessions'!U11),"",'Raw - Sessions'!T11) -> 0.25 | D37: ='Raw - Sessions'!E11 -> 0.583891 | E37: =IF(ISBLANK('Raw - Sessions'!U11),"",'Raw - Sessions'!U11) -> 0.15 | F37: =IF(ISBLANK('Raw - Sessions'!U11),"",'Raw - Sessions'!Z11) -> 0.01 | G37: =IF(ISBLANK('Raw - Sessions'!U11),"",'Raw - Sessions'!AE11) -> 0 | H37: =IF(ISBLANK('Raw - Sessions'!U11),"",'Raw - Sessions'!AD11) -> 0.01 | I37: =IF(ISBLANK('Raw - Sessions'!U11),"",'Raw - Sessions'!P11) -> 0.16 | J37: =IF(E37="","",E37+F37+G37+'Raw - Sessions'!AA11+'Raw - Sessions'!AB11+'Raw - Sessions'!AC11) -> 0.16 | K37: =IF(E37="","",I37-J37) -> 0 | L37: =IF(E37="","",IF(ABS(K37)>0.02,"MISMATCH","OK")) -> OK | M37: =IF(ISBLANK('Raw - Sessions'!U11),"",'Raw - Sessions'!Q11) -> 0.14 | N37: =IF(E37="","",I37-G37-H37-F37) -> 0.14 | O37: =IF(E37="","",M37-N37) -> 0 | P37: =IF(E37="","",IF(ABS(O37)>0.02,"MISMATCH","OK")) -> OK
A38: ='Raw - Sessions'!A12 -> 4530323111 | B38: ='Raw - Sessions'!K12 -> BARBOURVILLE / TOURISM | C38: =IF(ISBLANK('Raw - Sessions'!U12),"",'Raw - Sessions'!T12) | D38: ='Raw - Sessions'!E12 -> 0 | E38: =IF(ISBLANK('Raw - Sessions'!U12),"",'Raw - Sessions'!U12) | F38: =IF(ISBLANK('Raw - Sessions'!U12),"",'Raw - Sessions'!Z12) | G38: =IF(ISBLANK('Raw - Sessions'!U12),"",'Raw - Sessions'!AE12) | H38: =IF(ISBLANK('Raw - Sessions'!U12),"",'Raw - Sessions'!AD12) | I38: =IF(ISBLANK('Raw - Sessions'!U12),"",'Raw - Sessions'!P12) | J38: =IF(E38="","",E38+F38+G38+'Raw - Sessions'!AA12+'Raw - Sessions'!AB12+'Raw - Sessions'!AC12) | K38: =IF(E38="","",I38-J38) | L38: =IF(E38="","",IF(ABS(K38)>0.02,"MISMATCH","OK")) | M38: =IF(ISBLANK('Raw - Sessions'!U12),"",'Raw - Sessions'!Q12) | N38: =IF(E38="","",I38-G38-H38-F38) | O38: =IF(E38="","",M38-N38) | P38: =IF(E38="","",IF(ABS(O38)>0.02,"MISMATCH","OK"))
A39: ='Raw - Sessions'!A13 -> 4530350941 | B39: ='Raw - Sessions'!K13 -> BARBOURVILLE / TOURISM | C39: =IF(ISBLANK('Raw - Sessions'!U13),"",'Raw - Sessions'!T13) | D39: ='Raw - Sessions'!E13 -> 0 | E39: =IF(ISBLANK('Raw - Sessions'!U13),"",'Raw - Sessions'!U13) | F39: =IF(ISBLANK('Raw - Sessions'!U13),"",'Raw - Sessions'!Z13) | G39: =IF(ISBLANK('Raw - Sessions'!U13),"",'Raw - Sessions'!AE13) | H39: =IF(ISBLANK('Raw - Sessions'!U13),"",'Raw - Sessions'!AD13) | I39: =IF(ISBLANK('Raw - Sessions'!U13),"",'Raw - Sessions'!P13) | J39: =IF(E39="","",E39+F39+G39+'Raw - Sessions'!AA13+'Raw - Sessions'!AB13+'Raw - Sessions'!AC13) | K39: =IF(E39="","",I39-J39) | L39: =IF(E39="","",IF(ABS(K39)>0.02,"MISMATCH","OK")) | M39: =IF(ISBLANK('Raw - Sessions'!U13),"",'Raw - Sessions'!Q13) | N39: =IF(E39="","",I39-G39-H39-F39) | O39: =IF(E39="","",M39-N39) | P39: =IF(E39="","",IF(ABS(O39)>0.02,"MISMATCH","OK"))
A40: ='Raw - Sessions'!A14 -> 4530386071 | B40: ='Raw - Sessions'!K14 -> BARBOURVILLE / TOURISM | C40: =IF(ISBLANK('Raw - Sessions'!U14),"",'Raw - Sessions'!T14) -> 0.25 | D40: ='Raw - Sessions'!E14 -> 12.813871 | E40: =IF(ISBLANK('Raw - Sessions'!U14),"",'Raw - Sessions'!U14) -> 3.2 | F40: =IF(ISBLANK('Raw - Sessions'!U14),"",'Raw - Sessions'!Z14) -> 0.19 | G40: =IF(ISBLANK('Raw - Sessions'!U14),"",'Raw - Sessions'!AE14) -> 0 | H40: =IF(ISBLANK('Raw - Sessions'!U14),"",'Raw - Sessions'!AD14) -> 0.32 | I40: =IF(ISBLANK('Raw - Sessions'!U14),"",'Raw - Sessions'!P14) -> 3.39 | J40: =IF(E40="","",E40+F40+G40+'Raw - Sessions'!AA14+'Raw - Sessions'!AB14+'Raw - Sessions'!AC14) -> 3.39 | K40: =IF(E40="","",I40-J40) -> 0 | L40: =IF(E40="","",IF(ABS(K40)>0.02,"MISMATCH","OK")) -> OK | M40: =IF(ISBLANK('Raw - Sessions'!U14),"",'Raw - Sessions'!Q14) -> 2.88 | N40: =IF(E40="","",I40-G40-H40-F40) -> 2.88 | O40: =IF(E40="","",M40-N40) -> 0 | P40: =IF(E40="","",IF(ABS(O40)>0.02,"MISMATCH","OK")) -> OK
A41: ='Raw - Sessions'!A15 -> 4533809491 | B41: ='Raw - Sessions'!K15 -> BARBOURVILLE / CITY HALL | C41: =IF(ISBLANK('Raw - Sessions'!U15),"",'Raw - Sessions'!T15) -> 0.4 | D41: ='Raw - Sessions'!E15 -> 42.079498 | E41: =IF(ISBLANK('Raw - Sessions'!U15),"",'Raw - Sessions'!U15) -> 22.08 | F41: =IF(ISBLANK('Raw - Sessions'!U15),"",'Raw - Sessions'!Z15) -> 1.01 | G41: =IF(ISBLANK('Raw - Sessions'!U15),"",'Raw - Sessions'!AE15) -> 0 | H41: =IF(ISBLANK('Raw - Sessions'!U15),"",'Raw - Sessions'!AD15) -> 2.21 | I41: =IF(ISBLANK('Raw - Sessions'!U15),"",'Raw - Sessions'!P15) -> 23.09 | J41: =IF(E41="","",E41+F41+G41+'Raw - Sessions'!AA15+'Raw - Sessions'!AB15+'Raw - Sessions'!AC15) -> 23.09 | K41: =IF(E41="","",I41-J41) -> 0 | L41: =IF(E41="","",IF(ABS(K41)>0.02,"MISMATCH","OK")) -> OK | M41: =IF(ISBLANK('Raw - Sessions'!U15),"",'Raw - Sessions'!Q15) -> 19.87 | N41: =IF(E41="","",I41-G41-H41-F41) -> 19.87 | O41: =IF(E41="","",M41-N41) -> 0 | P41: =IF(E41="","",IF(ABS(O41)>0.02,"MISMATCH","OK")) -> OK
A42: ='Raw - Sessions'!A16 -> 4540153751 | B42: ='Raw - Sessions'!K16 -> BARBOURVILLE / CITY HALL | C42: =IF(ISBLANK('Raw - Sessions'!U16),"",'Raw - Sessions'!T16) -> 0.4 | D42: ='Raw - Sessions'!E16 -> 8.8275 | E42: =IF(ISBLANK('Raw - Sessions'!U16),"",'Raw - Sessions'!U16) -> 5.01 | F42: =IF(ISBLANK('Raw - Sessions'!U16),"",'Raw - Sessions'!Z16) -> 0.21 | G42: =IF(ISBLANK('Raw - Sessions'!U16),"",'Raw - Sessions'!AE16) -> 0 | H42: =IF(ISBLANK('Raw - Sessions'!U16),"",'Raw - Sessions'!AD16) -> 0.5 | I42: =IF(ISBLANK('Raw - Sessions'!U16),"",'Raw - Sessions'!P16) -> 5.22 | J42: =IF(E42="","",E42+F42+G42+'Raw - Sessions'!AA16+'Raw - Sessions'!AB16+'Raw - Sessions'!AC16) -> 5.22 | K42: =IF(E42="","",I42-J42) -> 0 | L42: =IF(E42="","",IF(ABS(K42)>0.02,"MISMATCH","OK")) -> OK | M42: =IF(ISBLANK('Raw - Sessions'!U16),"",'Raw - Sessions'!Q16) -> 4.51 | N42: =IF(E42="","",I42-G42-H42-F42) -> 4.51 | O42: =IF(E42="","",M42-N42) -> 0 | P42: =IF(E42="","",IF(ABS(O42)>0.02,"MISMATCH","OK")) -> OK
... A318: ='Raw - Sessions'!A292 -> 5312043551 | B318: ='Raw - Sessions'!K292 -> BARBOURVILLE / TOURISM | C318: =IF(ISBLANK('Raw - Sessions'!U292),"",'Raw - Sessions'!T292) -> 0.5 | D318: ='Raw - Sessions'!E292 -> 12.304789 | E318: =IF(ISBLANK('Raw - Sessions'!U292),"",'Raw - Sessions'!U292) -> 24.73 | F318: =IF(ISBLANK('Raw - Sessions'!U292),"",'Raw - Sessions'!Z292) -> 1.48 | G318: =IF(ISBLANK('Raw - Sessions'!U292),"",'Raw - Sessions'!AE292) -> 0.49 | H318: =IF(ISBLANK('Raw - Sessions'!U292),"",'Raw - Sessions'!AD292) -> 2.47 | I318: =IF(ISBLANK('Raw - Sessions'!U292),"",'Raw - Sessions'!P292) -> 26.7 | J318: =IF(E318="","",E318+F318+G318+'Raw - Sessions'!AA292+'Raw - Sessions'!AB292+'Raw - Sessions'!AC292) -> 26.7 | K318: =IF(E318="","",I318-J318) -> 0 | L318: =IF(E318="","",IF(ABS(K318)>0.02,"MISMATCH","OK")) -> OK | M318: =IF(ISBLANK('Raw - Sessions'!U292),"",'Raw - Sessions'!Q292) -> 22.26 | N318: =IF(E318="","",I318-G318-H318-F318) -> 22.26 | O318: =IF(E318="","",M318-N318) -> 0 | P318: =IF(E318="","",IF(ABS(O318)>0.02,"MISMATCH","OK")) -> OK
A320: Every column in this table is a live formula against Raw - Sessions - edit any session's Gross Amount, Payout Amount, or fee/tax columns there and this whole table (and the KPIs and sentences above) recalculates automatically. Blank rows are sessions with no billing data (guest/unmatched checkout). Use the column filter arrows on Gross Check / Payout Check to isolate MISMATCH rows.

Sheet Visitor Origin
A1: Where Charging Customers Come From (All Stations Combined)
A2: Based on 165 of 288 sessions with a driver ZIP on file (124 checked out without an account/ZIP). State is estimated from ZIP3 prefix (see Read Me for method).
A4: Est. State | B4: Sessions | C4: Revenue ($)
A5: ='Raw - Zip-County-State'!K5 -> KY | B5: ='Raw - Zip-County-State'!L5 -> 96 | C5: ='Raw - Zip-County-State'!M5 -> 1775.37
A6: ='Raw - Zip-County-State'!K6 -> TN | B6: ='Raw - Zip-County-State'!L6 -> 18 | C6: ='Raw - Zip-County-State'!M6 -> 212.02
A7: ='Raw - Zip-County-State'!K7 -> OH | B7: ='Raw - Zip-County-State'!L7 -> 10 | C7: ='Raw - Zip-County-State'!M7 -> 159.73
A8: ='Raw - Zip-County-State'!K8 -> NC | B8: ='Raw - Zip-County-State'!L8 -> 9 | C8: ='Raw - Zip-County-State'!M8 -> 176.72
A9: ='Raw - Zip-County-State'!K9 -> IL | B9: ='Raw - Zip-County-State'!L9 -> 5 | C9: ='Raw - Zip-County-State'!M9 -> 37.59
A10: ='Raw - Zip-County-State'!K10 -> FL | B10: ='Raw - Zip-County-State'!L10 -> 3 | C10: ='Raw - Zip-County-State'!M10 -> 76.03
A11: ='Raw - Zip-County-State'!K11 -> SC | B11: ='Raw - Zip-County-State'!L11 -> 3 | C11: ='Raw - Zip-County-State'!M11 -> 30.12
A12: ='Raw - Zip-County-State'!K12 -> MI | B12: ='Raw - Zip-County-State'!L12 -> 3 | C12: ='Raw - Zip-County-State'!M12 -> 65.07
A13: ='Raw - Zip-County-State'!K13 -> WI | B13: ='Raw - Zip-County-State'!L13 -> 3 | C13: ='Raw - Zip-County-State'!M13 -> 50.77
A14: ='Raw - Zip-County-State'!K14 -> IN | B14: ='Raw - Zip-County-State'!L14 -> 2 | C14: ='Raw - Zip-County-State'!M14 -> 55.22
A15: ='Raw - Zip-County-State'!K15 -> GA | B15: ='Raw - Zip-County-State'!L15 -> 2 | C15: ='Raw - Zip-County-State'!M15 -> 45.25
A16: ='Raw - Zip-County-State'!K16 -> TX | B16: ='Raw - Zip-County-State'!L16 -> 2 | C16: ='Raw - Zip-County-State'!M16 -> 39.78
... A23: ='Raw - Zip-County-State'!K23 -> OK | B23: ='Raw - Zip-County-State'!L23 -> 1 | C23: ='Raw - Zip-County-State'!M23 -> 8.45
A25: Local vs. Regional vs. Out-of-State
A26: Group | B26: Sessions
A27: Local (ZIP 40906) | B27: =COUNTIF('Raw - Sessions'!$M$5:$M$292,"40906") -> 37
A28: Rest of Kentucky | B28: =COUNTIF('Raw - Sessions'!$O$5:$O$292,"KY")-B27 -> 59
A29: Out of State | B29: =COUNTIFS('Raw - Sessions'!$O$5:$O$292,"<>",'Raw - Sessions'!$O$5:$O$292,"<>KY") -> 68
A30: Unknown (no ZIP / guest checkout) | B30: =(288)-COUNT('Raw - Sessions'!$O$5:$O$292) -> 288
A32: "Unknown" sessions are guest/anonymous checkouts with no account ZIP captured by ChargePoint - not necessarily local.

Sheet Net Zero & Recommendations
A1: Net Zero & Recommendations for the Charger Owner
B3: What the data shows
B4: ="Usage: "&COUNTA('Raw - Sessions'!$A$5:$A$292)&" sessions over the reporting period, averaging "&TEXT(AVERAGE('Raw - Sessions'!$D$5:$D$292)*60,"0")&" minutes per session (median "&TEXT(MEDIAN('Raw - Sessions'!$D$5:$D$292)*60,"0")&" min) and about "&TEXT('Daily Summary'!E5,"0.0")&" sessions on an active day." -> Usage: 288 sessions over the reporting period, averaging 44 minutes per session (median 31 min) and about 2.0 sessions on an active day.
B5: ="Load intensity: "&TEXT(COUNTIF('Raw - Sessions'!$H$5:$H$292,TRUE())/COUNTA('Raw - Sessions'!$A$5:$A$292),"0%")&" of sessions reached a peak power draw above 10 kW, and on average "&TEXT(AVERAGE('Raw - Sessions'!$J$5:$J$292),"0%")&" of a session's plugged-in time was spent actively drawing more than 10 kW (the rest is likely finishing/trickle charging or idle plug-in time)." -> Load intensity: 64% of sessions reached a peak power draw above 10 kW, and on average 81% of a session's plugged-in time was spent actively drawing more than 10 kW (the rest is likely finishing/trickle charging or idle plug-in time).
B6: • Time of day: Evening (18:00-22:00) and Day (12:00-18:00) see the most sessions; overnight (22:00-6:00) charging happens on roughly 1 in 5 nights in the period, suggesting the station is mostly a daytime/evening stop rather than an overnight-dwell charger.
B7: • Solar vs. grid: the uploaded export only contains the charger's own delivered-energy meter, not a separate solar production meter, so this workbook cannot confirm whether solar generation is currently matching charging consumption (see Read Me).
B8: ="Two very different chargers: City Hall (Level 3/DCFC) does the vast majority of the volume - "&COUNTIF('Raw - Sessions'!$K$5:$K$292,"BARBOURVILLE / CITY HALL")&" of "&COUNTA('Raw - Sessions'!$A$5:$A$292)&" sessions and about "&TEXT(SUMIF('Raw - Sessions'!$K$5:$K$292,"BARBOURVILLE / CITY HALL",'Raw - Sessions'!$E$5:$E$292),"#,##0")&" of "&TEXT(SUM('Raw - Sessions'!$E$5:$E$292),"#,##0")&" kWh - while Tourism (Level 2) sees far fewer, longer sessions ("&COUNTIF('Raw - Sessions'!$K$5:$K$292,"BARBOURVILLE / TOURISM")&" sessions, avg ~"&TEXT(AVERAGEIFS('Raw - Sessions'!$D$5:$D$292,'Raw - Sessions'!$K$5:$K$292,"BARBOURVILLE / TOURISM")*60,"0")&" min vs. ~"&TEXT(AVERAGEIFS('Raw - Sessions'!$D$5:$D$292,'Raw - Sessions'!$K$5:$K$292,"BARBOURVILLE / CITY HALL")*60,"0")&" min at City Hall) and can never exceed roughly 7.4 kW, so it behaves more like a top-off-while-you-visit-downtown charger than a fast-charging stop. See the Tourism (Level 2) and City Hall (Level 3) tabs for each charger on its own." -> Two very different chargers: City Hall (Level 3/DCFC) does the vast majority of the volume - 239 of 288 sessions and about 5,824 of 6,217 kWh - while Tourism (Level 2) sees far fewer, longer sessions (49 sessions, avg ~78 min vs. ~38 min at City Hall) and can never exceed roughly 7.4 kW, so it behaves more like a top-off-while-you-visit-downtown charger than a fast-charging stop. See the Tourism (Level 2) and City Hall (Level 3) tabs for each charger on its own.
B9: • Visitors: over a third of sessions with a known ZIP came from outside Kentucky, and the top out-of-state states are neighboring Tennessee, Ohio, and North Carolina - consistent with highway/tourism traffic rather than only local commuters.
B11: Recommendations toward net zero
B12: 1. Get a real solar production number before claiming net zero.
B13: Pull a generation export from the site's solar inverter or utility net-meter (matching the same daily format as the charger's Energy-vs-Time export) and add it to the Raw - Daily Energy tab. Only then can "solar covers X% of charging load" be stated as a verified figure rather than an assumption.
B14: 2. Target daytime charging to match solar production hours.
B15: Solar generates during daylight, but Evening and Night together account for a large share of sessions. If the goal is to maximize solar-matched charging, consider time-of-use pricing (a lower rate 10am-4pm) or signage encouraging daytime top-offs, and re-check the Time of Day tab each quarter to see if the shift is working.
B16: 3. Size any battery storage or added solar off the actual daily energy curve, not an average.
B17: Daily energy delivered swings from 0 kWh (most days) up to ~40-70+ kWh on the busiest days (Raw - Daily Energy tab). A system sized to the daily average will undershoot on peak days; use the observed daily distribution to size for a target percentile (e.g., the busiest 1-in-10 day), not just the mean.
B18: 4. Track the >10kW "active load" share over time as a proxy for charger utilization.
B19: Right now roughly four-fifths of plugged-in time is active high-power draw. If that share drifts down, it can mean more idle "camping" on the charger (cars staying plugged in after they're done) - worth flagging for idle fees or session time limits, which several ChargePoint hosts use to free up the charger for the next driver.
B20: 5. Use the overnight and visitor-origin data in city planning conversations.
B21: Low overnight use suggests the current chargers serve day-trip and pass-through traffic well but are not yet an overnight EV-tourism draw. If the city wants to capture overnight stays (hotel/B&B partnerships), that would likely require a charger sited near lodging, not just City Hall/Tourism.
B23: Suggested talking points for the mayor
B24: ="The Barbourville City Hall / Tourism chargers delivered about "&TEXT(SUM('Raw - Sessions'!$E$5:$E$292),"#,##0")&" kWh and generated about $"&TEXT(SUM('Raw - Sessions'!$P$5:$P$292),"#,##0")&" in gross session revenue over the past 12 months, across "&COUNTA('Raw - Sessions'!$A$5:$A$292)&" charging sessions." -> The Barbourville City Hall / Tourism chargers delivered about 6,217 kWh and generated about $4,036 in gross session revenue over the past 12 months, across 288 charging sessions.
B25: • More than a third of identifiable customers are visiting from outside Kentucky - the charger is functioning as a stop for regional and highway travelers, not just a local amenity.
B26: • Published research on EV charging (MIT/Nature Communications, 2024) links nearby charging infrastructure to measurable upticks in nearby business spending, since drivers often shop or eat during a charging stop - relevant context if the city is considering charger locations near downtown businesses.
B27: • Next investment step: adding solar production monitoring would let the city credibly market these stations as solar-supported, and quantify progress toward a net-zero-charging goal - right now that comparison cannot be made from available data.

Sheet Raw - Sessions
A1: Raw Session-Level Data (288 sessions, Oct 15 2025 - Jul 9 2026)
A2: Every session from the ChargePoint export, merged with billing (ZIP/revenue) and interval power data. All downstream tabs pull from this sheet.
A4: Session ID | B4: Session Start | C4: Session End | D4: Duration (hr) | E4: Energy (kWh) | F4: Peak Power (kW) | G4: Day Segment | H4: Car Load >10kW (session peak) | I4: Overnight (started 22:00-6:00) | J4: % of Session Time >10kW (interval data) | K4: Station | L4: Payment Method | M4: Driver ZIP | N4: Driver County | O4: Est. State | P4: Gross Amount ($) | Q4: Payout Amount ($) | R4: Session Date | S4: First Overnight Session of Night (1/0) | T4: Rate ($/kWh) | U4: Net Session Fee ($) | V4: Calc Energy Cost = Rate x kWh ($) | W4: Fee + Tax Total ($) | X4: Day of Week | Y4: Week Start | Z4: Sales Tax ($) | AA4: Excise Tax ($) | AB4: Other Taxes ($) | AC4: Service Fee Tax ($) | AD4: Flex Billing Service Fee ($) | AE4: Service Fee ($) | AF4: First Active-Energy Session of Date (combined) | AG4: First Active-Energy Session of Date+Station
A5: 4511566811 | B5: 45945.747 | C5: 45945.798 | D5: 1.2102778 | E5: 8.483508 | F5: 7.1494 | G5: Day (12-18) | H5: =FALSE() -> FALSE | I5: =FALSE() -> FALSE | J5: 0 | K5: BARBOURVILLE / TOURISM | L5: membership | M5: 40701 | O5: KY | P5: 2.25 | Q5: 1.91 | R5: =INT(B5) -> 45945 | S5: =IF(AND(I5=TRUE(),COUNTIFS($R$5:R5,R5,$I$5:I5,TRUE())=1),1,0) -> 0 | T5: 0.25 | U5: 2.12 | V5: 2.120877 | W5: =SUM(Z5:AE5) -> 0.34 | X5: Wednesday | Y5: 45943 | Z5: 0.13 | AA5: 0 | AB5: 0 | AC5: 0 | AD5: 0.21 | AE5: 0 | AF5: =IF(AND(E5>0,COUNTIFS($R$5:R5,R5,$E$5:E5,">0")=1),1,0) -> 1 | AG5: =IF(AND(E5>0,COUNTIFS($R$5:R5,R5,$K$5:K5,K5,$E$5:E5,">0")=1),1,0) -> 1
A6: 4523627951 | B6: 45949.697 | C6: 45949.702 | D6: 0.11527778 | E6: 4.8593 | F6: 56.004 | G6: Day (12-18) | H6: =TRUE() -> TRUE | I6: =FALSE() -> FALSE | J6: 1 | K6: BARBOURVILLE / CITY HALL | L6: membership | M6: 40906 | O6: KY | P6: 1.28 | Q6: 1.09 | R6: =INT(B6) -> 45949 | S6: =IF(AND(I6=TRUE(),COUNTIFS($R$5:R6,R6,$I$5:I6,TRUE())=1),1,0) -> 0 | T6: 0.25 | U6: 1.21 | V6: 1.214825 | W6: =SUM(Z6:AE6) -> 0.19 | X6: Sunday | Y6: 45943 | Z6: 0.07 | AA6: 0 | AB6: 0 | AC6: 0 | AD6: 0.12 | AE6: 0 | AF6: =IF(AND(E6>0,COUNTIFS($R$5:R6,R6,$E$5:E6,">0")=1),1,0) -> 1 | AG6: =IF(AND(E6>0,COUNTIFS($R$5:R6,R6,$K$5:K6,K6,$E$5:E6,">0")=1),1,0) -> 1
A7: 4524317961 | B7: 45949.906 | C7: 45949.915 | D7: 0.21333333 | E7: 9.2283 | F7: 0 | G7: Evening (18-22) | H7: =FALSE() -> FALSE | I7: =FALSE() -> FALSE | K7: BARBOURVILLE / CITY HALL | L7: membership | R7: =INT(B7) -> 45949 | S7: =IF(AND(I7=TRUE(),COUNTIFS($R$5:R7,R7,$I$5:I7,TRUE())=1),1,0) -> 0 | W7: =SUM(Z7:AE7) -> 0 | X7: Sunday | Y7: 45943 | AF7: =IF(AND(E7>0,COUNTIFS($R$5:R7,R7,$E$5:E7,">0")=1),1,0) -> 0 | AG7: =IF(AND(E7>0,COUNTIFS($R$5:R7,R7,$K$5:K7,K7,$E$5:E7,">0")=1),1,0) -> 0
A8: 4526984361 | B8: 45950.789 | C8: 45950.79 | D8: 0.018888889 | E8: 0 | F8: 0 | G8: Evening (18-22) | H8: =FALSE() -> FALSE | I8: =FALSE() -> FALSE | K8: BARBOURVILLE / CITY HALL | L8: membership | R8: =INT(B8) -> 45950 | S8: =IF(AND(I8=TRUE(),COUNTIFS($R$5:R8,R8,$I$5:I8,TRUE())=1),1,0) -> 0 | W8: =SUM(Z8:AE8) -> 0 | X8: Monday | Y8: 45950 | AF8: =IF(AND(E8>0,COUNTIFS($R$5:R8,R8,$E$5:E8,">0")=1),1,0) -> 0 | AG8: =IF(AND(E8>0,COUNTIFS($R$5:R8,R8,$K$5:K8,K8,$E$5:E8,">0")=1),1,0) -> 0
A9: 4526989521 | B9: 45950.79 | C9: 45950.839 | D9: 1.16 | E9: 26.1175 | F9: 62.474 | G9: Evening (18-22) | H9: =TRUE() -> TRUE | I9: =FALSE() -> FALSE | J9: 1 | K9: BARBOURVILLE / CITY HALL | L9: membership | M9: 40906 | O9: KY | P9: 6.92 | Q9: 5.88 | R9: =INT(B9) -> 45950 | S9: =IF(AND(I9=TRUE(),COUNTIFS($R$5:R9,R9,$I$5:I9,TRUE())=1),1,0) -> 0 | T9: 0.25 | U9: 6.53 | V9: 6.529375 | W9: =SUM(Z9:AE9) -> 1.04 | X9: Monday | Y9: 45950 | Z9: 0.39 | AA9: 0 | AB9: 0 | AC9: 0 | AD9: 0.65 | AE9: 0 | AF9: =IF(AND(E9>0,COUNTIFS($R$5:R9,R9,$E$5:E9,">0")=1),1,0) -> 1 | AG9: =IF(AND(E9>0,COUNTIFS($R$5:R9,R9,$K$5:K9,K9,$E$5:E9,">0")=1),1,0) -> 1
A10: 4530183221 | B10: 45951.712 | C10: 45951.744 | D10: 0.76611111 | E10: 42.2076 | F10: 61.541 | G10: Day (12-18) | H10: =TRUE() -> TRUE | I10: =FALSE() -> FALSE | J10: 1 | K10: BARBOURVILLE / CITY HALL | L10: membership | M10: 37869 | O10: TN | P10: 11.18 | Q10: 9.5 | R10: =INT(B10) -> 45951 | S10: =IF(AND(I10=TRUE(),COUNTIFS($R$5:R10,R10,$I$5:I10,TRUE())=1),1,0) -> 0 | T10: 0.25 | U10: 10.55 | V10: 10.5519 | W10: =SUM(Z10:AE10) -> 1.68 | X10: Tuesday | Y10: 45950 | Z10: 0.63 | AA10: 0 | AB10: 0 | AC10: 0 | AD10: 1.05 | AE10: 0 | AF10: =IF(AND(E10>0,COUNTIFS($R$5:R10,R10,$E$5:E10,">0")=1),1,0) -> 1 | AG10: =IF(AND(E10>0,COUNTIFS($R$5:R10,R10,$K$5:K10,K10,$E$5:E10,">0")=1),1,0) -> 1
A11: 4530304121 | B11: 45951.744 | C11: 45951.752 | D11: 0.18888889 | E11: 0.583891 | F11: 3.8065 | G11: Day (12-18) | H11: =FALSE() -> FALSE | I11: =FALSE() -> FALSE | J11: 0 | K11: BARBOURVILLE / TOURISM | L11: credit_card_terminal | P11: 0.16 | Q11: 0.14 | R11: =INT(B11) -> 45951 | S11: =IF(AND(I11=TRUE(),COUNTIFS($R$5:R11,R11,$I$5:I11,TRUE())=1),1,0) -> 0 | T11: 0.25 | U11: 0.15 | V11: 0.14597275 | W11: =SUM(Z11:AE11) -> 0.02 | X11: Tuesday | Y11: 45950 | Z11: 0.01 | AA11: 0 | AB11: 0 | AC11: 0 | AD11: 0.01 | AE11: 0 | AF11: =IF(AND(E11>0,COUNTIFS($R$5:R11,R11,$E$5:E11,">0")=1),1,0) -> 0 | AG11: =IF(AND(E11>0,COUNTIFS($R$5:R11,R11,$K$5:K11,K11,$E$5:E11,">0")=1),1,0) -> 1
A12: 4530323111 | B12: 45951.748 | C12: 45951.748 | D12: 0.0038888889 | E12: 0 | G12: Day (12-18) | H12: =FALSE() -> FALSE | I12: =FALSE() -> FALSE | K12: BARBOURVILLE / TOURISM | L12: credit_card_terminal | R12: =INT(B12) -> 45951 | S12: =IF(AND(I12=TRUE(),COUNTIFS($R$5:R12,R12,$I$5:I12,TRUE())=1),1,0) -> 0 | W12: =SUM(Z12:AE12) -> 0 | X12: Tuesday | Y12: 45950 | AF12: =IF(AND(E12>0,COUNTIFS($R$5:R12,R12,$E$5:E12,">0")=1),1,0) -> 0 | AG12: =IF(AND(E12>0,COUNTIFS($R$5:R12,R12,$K$5:K12,K12,$E$5:E12,">0")=1),1,0) -> 0
A13: 4530350941 | B13: 45951.756 | C13: 45951.756 | D13: 0.0011111111 | E13: 0 | G13: Evening (18-22) | H13: =FALSE() -> FALSE | I13: =FALSE() -> FALSE | K13: BARBOURVILLE / TOURISM | L13: credit_card_terminal | R13: =INT(B13) -> 45951 | S13: =IF(AND(I13=TRUE(),COUNTIFS($R$5:R13,R13,$I$5:I13,TRUE())=1),1,0) -> 0 | W13: =SUM(Z13:AE13) -> 0 | X13: Tuesday | Y13: 45950 | AF13: =IF(AND(E13>0,COUNTIFS($R$5:R13,R13,$E$5:E13,">0")=1),1,0) -> 0 | AG13: =IF(AND(E13>0,COUNTIFS($R$5:R13,R13,$K$5:K13,K13,$E$5:E13,">0")=1),1,0) -> 0
A14: 4530386071 | B14: 45951.765 | C14: 45951.997 | D14: 5.5541667 | E14: 12.813871 | F14: 3.7016 | G14: Evening (18-22) | H14: =FALSE() -> FALSE | I14: =FALSE() -> FALSE | J14: 0 | K14: BARBOURVILLE / TOURISM | L14: credit_card_terminal | P14: 3.39 | Q14: 2.88 | R14: =INT(B14) -> 45951 | S14: =IF(AND(I14=TRUE(),COUNTIFS($R$5:R14,R14,$I$5:I14,TRUE())=1),1,0) -> 0 | T14: 0.25 | U14: 3.2 | V14: 3.2034678 | W14: =SUM(Z14:AE14) -> 0.51 | X14: Tuesday | Y14: 45950 | Z14: 0.19 | AA14: 0 | AB14: 0 | AC14: 0 | AD14: 0.32 | AE14: 0 | AF14: =IF(AND(E14>0,COUNTIFS($R$5:R14,R14,$E$5:E14,">0")=1),1,0) -> 0 | AG14: =IF(AND(E14>0,COUNTIFS($R$5:R14,R14,$K$5:K14,K14,$E$5:E14,">0")=1),1,0) -> 0
A15: 4533809491 | B15: 45952.786 | C15: 45952.841 | D15: 1.3133333 | E15: 42.079498 | F15: 62.523 | G15: Evening (18-22) | H15: =TRUE() -> TRUE | I15: =FALSE() -> FALSE | J15: 1 | K15: BARBOURVILLE / CITY HALL | L15: membership | M15: 40906 | O15: KY | P15: 23.09 | Q15: 19.87 | R15: =INT(B15) -> 45952 | S15: =IF(AND(I15=TRUE(),COUNTIFS($R$5:R15,R15,$I$5:I15,TRUE())=1),1,0) -> 0 | T15: 0.4 | U15: 22.08 | V15: 16.831799 | W15: =SUM(Z15:AE15) -> 3.22 | X15: Wednesday | Y15: 45950 | Z15: 1.01 | AA15: 0 | AB15: 0 | AC15: 0 | AD15: 2.21 | AE15: 0 | AF15: =IF(AND(E15>0,COUNTIFS($R$5:R15,R15,$E$5:E15,">0")=1),1,0) -> 1 | AG15: =IF(AND(E15>0,COUNTIFS($R$5:R15,R15,$K$5:K15,K15,$E$5:E15,">0")=1),1,0) -> 1
A16: 4540153751 | B16: 45954.673 | C16: 45954.688 | D16: 0.37 | E16: 8.8275 | F16: 47.125 | G16: Day (12-18) | H16: =TRUE() -> TRUE | I16: =FALSE() -> FALSE | J16: 1 | K16: BARBOURVILLE / CITY HALL | L16: membership | M16: 40801 | N16: Harlan County | O16: KY | P16: 5.22 | Q16: 4.51 | R16: =INT(B16) -> 45954 | S16: =IF(AND(I16=TRUE(),COUNTIFS($R$5:R16,R16,$I$5:I16,TRUE())=1),1,0) -> 0 | T16: 0.4 | U16: 5.01 | V16: 3.531 | W16: =SUM(Z16:AE16) -> 0.71 | X16: Friday | Y16: 45950 | Z16: 0.21 | AA16: 0 | AB16: 0 | AC16: 0 | AD16: 0.5 | AE16: 0 | AF16: =IF(AND(E16>0,COUNTIFS($R$5:R16,R16,$E$5:E16,">0")=1),1,0) -> 1 | AG16: =IF(AND(E16>0,COUNTIFS($R$5:R16,R16,$K$5:K16,K16,$E$5:E16,">0")=1),1,0) -> 1
A17: 4540492661 | B17: 45954.755 | C17: 45954.758 | D17: 0.090555556 | E17: 0 | F17: 0 | G17: Evening (18-22) | H17: =FALSE() -> FALSE | I17: =FALSE() -> FALSE | K17: BARBOURVILLE / CITY HALL | L17: membership | M17: 37934 | N17: Knox County | O17: TN | P17: 0.36 | Q17: 0.32 | R17: =INT(B17) -> 45954 | S17: =IF(AND(I17=TRUE(),COUNTIFS($R$5:R17,R17,$I$5:I17,TRUE())=1),1,0) -> 0 | T17: 0.4 | U17: 0.36 | V17: 0 | W17: =SUM(Z17:AE17) -> 0.04 | X17: Friday | Y17: 45950 | Z17: 0 | AA17: 0 | AB17: 0 | AC17: 0 | AD17: 0.04 | AE17: 0 | AF17: =IF(AND(E17>0,COUNTIFS($R$5:R17,R17,$E$5:E17,">0")=1),1,0) -> 0 | AG17: =IF(AND(E17>0,COUNTIFS($R$5:R17,R17,$K$5:K17,K17,$E$5:E17,">0")=1),1,0) -> 0
A18: 4540515451 | B18: 45954.761 | C18: 45954.762 | D18: 0.024166667 | E18: 0 | F18: 0 | G18: Evening (18-22) | H18: =FALSE() -> FALSE | I18: =FALSE() -> FALSE | K18: BARBOURVILLE / CITY HALL | L18: membership | R18: =INT(B18) -> 45954 | S18: =IF(AND(I18=TRUE(),COUNTIFS($R$5:R18,R18,$I$5:I18,TRUE())=1),1,0) -> 0 | W18: =SUM(Z18:AE18) -> 0 | X18: Friday | Y18: 45950 | AF18: =IF(AND(E18>0,COUNTIFS($R$5:R18,R18,$E$5:E18,">0")=1),1,0) -> 0 | AG18: =IF(AND(E18>0,COUNTIFS($R$5:R18,R18,$K$5:K18,K18,$E$5:E18,">0")=1),1,0) -> 0
A19: 4540546531 | B19: 45954.769 | C19: 45954.802 | D19: 0.81027778 | E19: 46.164501 | F19: 60.907 | G19: Evening (18-22) | H19: =TRUE() -> TRUE | I19: =FALSE() -> FALSE | J19: 1 | K19: BARBOURVILLE / CITY HALL | L19: membership | M19: 37934 | N19: Knox County | O19: TN | P19: 22.82 | Q19: 19.54 | R19: =INT(B19) -> 45954 | S19: =IF(AND(I19=TRUE(),COUNTIFS($R$5:R19,R19,$I$5:I19,TRUE())=1),1,0) -> 0 | T19: 0.4 | U19: 21.71 | V19: 18.4658 | W19: =SUM(Z19:AE19) -> 3.28 | X19: Friday | Y19: 45950 | Z19: 1.11 | AA19: 0 | AB19: 0 | AC19: 0 | AD19: 2.17 | AE19: 0 | AF19: =IF(AND(E19>0,COUNTIFS($R$5:R19,R19,$E$5:E19,">0")=1),1,0) -> 0 | AG19: =IF(AND(E19>0,COUNTIFS($R$5:R19,R19,$K$5:K19,K19,$E$5:E19,">0")=1),1,0) -> 0
A20: 4540698941 | B20: 45954.806 | C20: 45954.821 | D20: 0.37333333 | E20: 21.1 | F20: 62.487 | G20: Evening (18-22) | H20: =TRUE() -> TRUE | I20: =FALSE() -> FALSE | J20: 1 | K20: BARBOURVILLE / CITY HALL | L20: credit_card_terminal | P20: 10.44 | Q20: 8.94 | R20: =INT(B20) -> 45954 | S20: =IF(AND(I20=TRUE(),COUNTIFS($R$5:R20,R20,$I$5:I20,TRUE())=1),1,0) -> 0 | T20: 0.4 | U20: 9.93 | V20: 8.44 | W20: =SUM(Z20:AE20) -> 1.5 | X20: Friday | Y20: 45950 | Z20: 0.51 | AA20: 0 | AB20: 0 | AC20: 0 | AD20: 0.99 | AE20: 0 | AF20: =IF(AND(E20>0,COUNTIFS($R$5:R20,R20,$E$5:E20,">0")=1),1,0) -> 0 | AG20: =IF(AND(E20>0,COUNTIFS($R$5:R20,R20,$K$5:K20,K20,$E$5:E20,">0")=1),1,0) -> 0
A21: 4540773061 | B21: 45954.823 | C21: 45954.85 | D21: 0.66611111 | E21: 14.3674 | F21: 46.875 | G21: Evening (18-22) | H21: =TRUE() -> TRUE | I21: =FALSE() -> FALSE | J21: 0.98360656 | K21: BARBOURVILLE / CITY HALL | L21: membership | M21: 40801 | N21: Harlan County | O21: KY | P21: 8.76 | Q21: 7.57 | R21: =INT(B21) -> 45954 | S21: =IF(AND(I21=TRUE(),COUNTIFS($R$5:R21,R21,$I$5:I21,TRUE())=1),1,0) -> 0 | T21: 0.4 | U21: 8.41 | V21: 5.74696 | W21: =SUM(Z21:AE21) -> 1.19 | X21: Friday | Y21: 45950 | Z21: 0.35 | AA21: 0 | AB21: 0 | AC21: 0 | AD21: 0.84 | AE21: 0 | AF21: =IF(AND(E21>0,COUNTIFS($R$5:R21,R21,$E$5:E21,">0")=1),1,0) -> 0 | AG21: =IF(AND(E21>0,COUNTIFS($R$5:R21,R21,$K$5:K21,K21,$E$5:E21,">0")=1),1,0) -> 0
A22: 4543524101 | B22: 45955.84 | C22: 45955.848 | D22: 0.20222222 | E22: 5.3031 | F22: 48.625 | G22: Evening (18-22) | H22: =TRUE() -> TRUE | I22: =FALSE() -> FALSE | J22: 1 | K22: BARBOURVILLE / CITY HALL | L22: membership | M22: 40701 | O22: KY | P22: 3.06 | Q22: 2.64 | R22: =INT(B22) -> 45955 | S22: =IF(AND(I22=TRUE(),COUNTIFS($R$5:R22,R22,$I$5:I22,TRUE())=1),1,0) -> 0 | T22: 0.4 | U22: 2.93 | V22: 2.12124 | W22: =SUM(Z22:AE22) -> 0.42 | X22: Saturday | Y22: 45950 | Z22: 0.13 | AA22: 0 | AB22: 0 | AC22: 0 | AD22: 0.29 | AE22: 0 | AF22: =IF(AND(E22>0,COUNTIFS($R$5:R22,R22,$E$5:E22,">0")=1),1,0) -> 1 | AG22: =IF(AND(E22>0,COUNTIFS($R$5:R22,R22,$K$5:K22,K22,$E$5:E22,">0")=1),1,0) -> 1
A23: 4545939491 | B23: 45956.882 | C23: 45956.882 | D23: 0.013333333 | E23: 0 | F23: 0 | G23: Evening (18-22) | H23: =FALSE() -> FALSE | I23: =FALSE() -> FALSE | K23: BARBOURVILLE / CITY HALL | L23: membership | R23: =INT(B23) -> 45956 | S23: =IF(AND(I23=TRUE(),COUNTIFS($R$5:R23,R23,$I$5:I23,TRUE())=1),1,0) -> 0 | W23: =SUM(Z23:AE23) -> 0 | X23: Sunday | Y23: 45950 | AF23: =IF(AND(E23>0,COUNTIFS($R$5:R23,R23,$E$5:E23,">0")=1),1,0) -> 0 | AG23: =IF(AND(E23>0,COUNTIFS($R$5:R23,R23,$K$5:K23,K23,$E$5:E23,">0")=1),1,0) -> 0
A24: 4545941821 | B24: 45956.883 | C24: 45956.887 | D24: 0.10666667 | E24: 5.4966 | F24: 58.5 | G24: Evening (18-22) | H24: =TRUE() -> TRUE | I24: =FALSE() -> FALSE | J24: 1 | K24: BARBOURVILLE / CITY HALL | L24: membership | M24: 37937 | O24: TN | P24: 2.76 | Q24: 2.37 | R24: =INT(B24) -> 45956 | S24: =IF(AND(I24=TRUE(),COUNTIFS($R$5:R24,R24,$I$5:I24,TRUE())=1),1,0) -> 0 | T24: 0.4 | U24: 2.63 | V24: 2.19864 | W24: =SUM(Z24:AE24) -> 0.39 | X24: Sunday | Y24: 45950 | Z24: 0.13 | AA24: 0 | AB24: 0 | AC24: 0 | AD24: 0.26 | AE24: 0 | AF24: =IF(AND(E24>0,COUNTIFS($R$5:R24,R24,$E$5:E24,">0")=1),1,0) -> 1 | AG24: =IF(AND(E24>0,COUNTIFS($R$5:R24,R24,$K$5:K24,K24,$E$5:E24,">0")=1),1,0) -> 1
A25: 4547937941 | B25: 45957.642 | C25: 45957.657 | D25: 0.36888889 | E25: 22.2493 | F25: 62.868 | G25: Day (12-18) | H25: =TRUE() -> TRUE | I25: =FALSE() -> FALSE | J25: 1 | K25: BARBOURVILLE / CITY HALL | L25: credit_card_terminal | P25: 10.91 | Q25: 9.34 | R25: =INT(B25) -> 45957 | S25: =IF(AND(I25=TRUE(),COUNTIFS($R$5:R25,R25,$I$5:I25,TRUE())=1),1,0) -> 0 | T25: 0.4 | U25: 10.38 | V25: 8.89972 | W25: =SUM(Z25:AE25) -> 1.57 | X25: Monday | Y25: 45957 | Z25: 0.53 | AA25: 0 | AB25: 0 | AC25: 0 | AD25: 1.04 | AE25: 0 | AF25: =IF(AND(E25>0,COUNTIFS($R$5:R25,R25,$E$5:E25,">0")=1),1,0) -> 1 | AG25: =IF(AND(E25>0,COUNTIFS($R$5:R25,R25,$K$5:K25,K25,$E$5:E25,">0")=1),1,0) -> 1
A26: 4549967281 | B26: 45958.115 | C26: 45958.115 | D26: 0.011388889 | E26: 0 | F26: 0 | G26: Night (22-6) | H26: =FALSE() -> FALSE | I26: =TRUE() -> TRUE | K26: BARBOURVILLE / CITY HALL | L26: membership | R26: =INT(B26) -> 45958 | S26: =IF(AND(I26=TRUE(),COUNTIFS($R$5:R26,R26,$I$5:I26,TRUE())=1),1,0) -> 1 | W26: =SUM(Z26:AE26) -> 0 | X26: Tuesday | Y26: 45957 | AF26: =IF(AND(E26>0,COUNTIFS($R$5:R26,R26,$E$5:E26,">0")=1),1,0) -> 0 | AG26: =IF(AND(E26>0,COUNTIFS($R$5:R26,R26,$K$5:K26,K26,$E$5:E26,">0")=1),1,0) -> 0
A27: 4549969211 | B27: 45958.115 | C27: 45958.147 | D27: 0.75027778 | E27: 28.066799 | F27: 53.549 | G27: Night (22-6) | H27: =TRUE() -> TRUE | I27: =TRUE() -> TRUE | J27: 1 | K27: BARBOURVILLE / CITY HALL | L27: membership | M27: 40220 | N27: Jefferson County | O27: KY | P27: 14.9 | Q27: 12.81 | R27: =INT(B27) -> 45958 | S27: =IF(AND(I27=TRUE(),COUNTIFS($R$5:R27,R27,$I$5:I27,TRUE())=1),1,0) -> 0 | T27: 0.4 | U27: 14.23 | V27: 11.22672 | W27: =SUM(Z27:AE27) -> 2.09 | X27: Tuesday | Y27: 45957 | Z27: 0.67 | AA27: 0 | AB27: 0 | AC27: 0 | AD27: 1.42 | AE27: 0 | AF27: =IF(AND(E27>0,COUNTIFS($R$5:R27,R27,$E$5:E27,">0")=1),1,0) -> 1 | AG27: =IF(AND(E27>0,COUNTIFS($R$5:R27,R27,$K$5:K27,K27,$E$5:E27,">0")=1),1,0) -> 1
A28: 4552702471 | B28: 45958.952 | C28: 45959.031 | D28: 1.9041667 | E28: 66.149902 | F28: 62.474 | G28: Night (22-6) | H28: =TRUE() -> TRUE | I28: =TRUE() -> TRUE | J28: 1 | K28: BARBOURVILLE / CITY HALL | L28: membership | M28: 40906 | O28: KY | P28: 35.67 | Q28: 30.67 | R28: =INT(B28) -> 45958 | S28: =IF(AND(I28=TRUE(),COUNTIFS($R$5:R28,R28,$I$5:I28,TRUE())=1),1,0) -> 0 | T28: 0.4 | U28: 34.08 | V28: 26.459961 | W28: =SUM(Z28:AE28) -> 5 | X28: Tuesday | Y28: 45957 | Z28: 1.59 | AA28: 0 | AB28: 0 | AC28: 0 | AD28: 3.41 | AE28: 0 | AF28: =IF(AND(E28>0,COUNTIFS($R$5:R28,R28,$E$5:E28,">0")=1),1,0) -> 0 | AG28: =IF(AND(E28>0,COUNTIFS($R$5:R28,R28,$K$5:K28,K28,$E$5:E28,">0")=1),1,0) -> 0
A29: 4558258911 | B29: 45960.661 | C29: 45960.717 | D29: 1.3458333 | E29: 20.0424 | F29: 51.695 | G29: Day (12-18) | H29: =TRUE() -> TRUE | I29: =FALSE() -> FALSE | J29: 0.77935769 | K29: BARBOURVILLE / CITY HALL | L29: membership | M29: 40403 | O29: KY | P29: 13.88 | Q29: 12.06 | R29: =INT(B29) -> 45960 | S29: =IF(AND(I29=TRUE(),COUNTIFS($R$5:R29,R29,$I$5:I29,TRUE())=1),1,0) -> 0 | T29: 0.4 | U29: 13.4 | V29: 8.01696 | W29: =SUM(Z29:AE29) -> 1.82 | X29: Thursday | Y29: 45957 | Z29: 0.48 | AA29: 0 | AB29: 0 | AC29: 0 | AD29: 1.34 | AE29: 0 | AF29: =IF(AND(E29>0,COUNTIFS($R$5:R29,R29,$E$5:E29,">0")=1),1,0) -> 1 | AG29: =IF(AND(E29>0,COUNTIFS($R$5:R29,R29,$K$5:K29,K29,$E$5:E29,">0")=1),1,0) -> 1
A30: 4562784681 | B30: 45961.958 | C30: 45961.974 | D30: 0.38861111 | E30: 22.979 | F30: 62.465 | G30: Night (22-6) | H30: =TRUE() -> TRUE | I30: =TRUE() -> TRUE | J30: 1 | K30: BARBOURVILLE / CITY HALL | L30: membership | M30: 79424 | O30: TX | P30: 11.29 | Q30: 9.67 | R30: =INT(B30) -> 45961 | S30: =IF(AND(I30=TRUE(),COUNTIFS($R$5:R30,R30,$I$5:I30,TRUE())=1),1,0) -> 1 | T30: 0.4 | U30: 10.74 | V30: 9.1916 | W30: =SUM(Z30:AE30) -> 1.62 | X30: Friday | Y30: 45957 | Z30: 0.55 | AA30: 0 | AB30: 0 | AC30: 0 | AD30: 1.07 | AE30: 0 | AF30: =IF(AND(E30>0,COUNTIFS($R$5:R30,R30,$E$5:E30,">0")=1),1,0) -> 1 | AG30: =IF(AND(E30>0,COUNTIFS($R$5:R30,R30,$K$5:K30,K30,$E$5:E30,">0")=1),1,0) -> 1
A31: 4562924501 | B31: 45961.999 | C31: 45962.001 | D31: 0.054166667 | E31: 0 | F31: 0 | G31: Night (22-6) | H31: =FALSE() -> FALSE | I31: =TRUE() -> TRUE | J31: 0 | K31: BARBOURVILLE / CITY HALL | L31: membership | M31: 41091-7816 | O31: KY | P31: 0.22 | Q31: 0.2 | R31: =INT(B31) -> 45961 | S31: =IF(AND(I31=TRUE(),COUNTIFS($R$5:R31,R31,$I$5:I31,TRUE())=1),1,0) -> 0 | T31: 0.4 | U31: 0.22 | V31: 0 | W31: =SUM(Z31:AE31) -> 0.02 | X31: Friday | Y31: 45957 | Z31: 0 | AA31: 0 | AB31: 0 | AC31: 0 | AD31: 0.02 | AE31: 0 | AF31: =IF(AND(E31>0,COUNTIFS($R$5:R31,R31,$E$5:E31,">0")=1),1,0) -> 0 | AG31: =IF(AND(E31>0,COUNTIFS($R$5:R31,R31,$K$5:K31,K31,$E$5:E31,">0")=1),1,0) -> 0
A32: 4562936151 | B32: 45962.001 | C32: 45962.033 | D32: 0.75416667 | E32: 30.7314 | F32: 58.744 | G32: Night (22-6) | H32: =TRUE() -> TRUE | I32: =TRUE() -> TRUE | J32: 1 | K32: BARBOURVILLE / CITY HALL | L32: membership | M32: 41091-7816 | O32: KY | P32: 16.05 | Q32: 13.78 | R32: =INT(B32) -> 45962 | S32: =IF(AND(I32=TRUE(),COUNTIFS($R$5:R32,R32,$I$5:I32,TRUE())=1),1,0) -> 1 | T32: 0.4 | U32: 15.31 | V32: 12.29256 | W32: =SUM(Z32:AE32) -> 2.27 | X32: Saturday | Y32: 45957 | Z32: 0.74 | AA32: 0 | AB32: 0 | AC32: 0 | AD32: 1.53 | AE32: 0 | AF32: =IF(AND(E32>0,COUNTIFS($R$5:R32,R32,$E$5:E32,">0")=1),1,0) -> 1 | AG32: =IF(AND(E32>0,COUNTIFS($R$5:R32,R32,$K$5:K32,K32,$E$5:E32,">0")=1),1,0) -> 1
A33: 4563049001 | B33: 45962.036 | C33: 45962.037 | D33: 0.031944444 | E33: 0 | F33: 0 | G33: Night (22-6) | H33: =FALSE() -> FALSE | I33: =TRUE() -> TRUE | K33: BARBOURVILLE / TOURISM | L33: membership | R33: =INT(B33) -> 45962 | S33: =IF(AND(I33=TRUE(),COUNTIFS($R$5:R33,R33,$I$5:I33,TRUE())=1),1,0) -> 0 | W33: =SUM(Z33:AE33) -> 0 | X33: Saturday | Y33: 45957 | AF33: =IF(AND(E33>0,COUNTIFS($R$5:R33,R33,$E$5:E33,">0")=1),1,0) -> 0 | AG33: =IF(AND(E33>0,COUNTIFS($R$5:R33,R33,$K$5:K33,K33,$E$5:E33,">0")=1),1,0) -> 0
A34: 4563050701 | B34: 45962.038 | C34: 45962.072 | D34: 0.80972222 | E34: 33.872002 | F34: 56.159 | G34: Night (22-6) | H34: =TRUE() -> TRUE | I34: =TRUE() -> TRUE | J34: 1 | K34: BARBOURVILLE / CITY HALL | L34: membership | M34: 33957 | N34: Lee County | O34: FL | P34: 17.6 | Q34: 15.11 | R34: =INT(B34) -> 45962 | S34: =IF(AND(I34=TRUE(),COUNTIFS($R$5:R34,R34,$I$5:I34,TRUE())=1),1,0) -> 0 | T34: 0.4 | U34: 16.79 | V34: 13.548801 | W34: =SUM(Z34:AE34) -> 2.49 | X34: Saturday | Y34: 45957 | Z34: 0.81 | AA34: 0 | AB34: 0 | AC34: 0 | AD34: 1.68 | AE34: 0 | AF34: =IF(AND(E34>0,COUNTIFS($R$5:R34,R34,$E$5:E34,">0")=1),1,0) -> 0 | AG34: =IF(AND(E34>0,COUNTIFS($R$5:R34,R34,$K$5:K34,K34,$E$5:E34,">0")=1),1,0) -> 0
A35: 4564233461 | B35: 45962.664 | C35: 45962.673 | D35: 0.21805556 | E35: 11.2005 | F35: 52.571 | G35: Day (12-18) | H35: =TRUE() -> TRUE | I35: =FALSE() -> FALSE | J35: 1 | K35: BARBOURVILLE / CITY HALL | L35: membership | M35: 40906 | O35: KY | P35: 5.62 | Q35: 4.82 | R35: =INT(B35) -> 45962 | S35: =IF(AND(I35=TRUE(),COUNTIFS($R$5:R35,R35,$I$5:I35,TRUE())=1),1,0) -> 0 | T35: 0.4 | U35: 5.35 | V35: 4.4802 | W35: =SUM(Z35:AE35) -> 0.8 | X35: Saturday | Y35: 45957 | Z35: 0.27 | AA35: 0 | AB35: 0 | AC35: 0 | AD35: 0.53 | AE35: 0 | AF35: =IF(AND(E35>0,COUNTIFS($R$5:R35,R35,$E$5:E35,">0")=1),1,0) -> 0 | AG35: =IF(AND(E35>0,COUNTIFS($R$5:R35,R35,$K$5:K35,K35,$E$5:E35,">0")=1),1,0) -> 0
A36: 4572893011 | B36: 45965.818 | C36: 45965.849 | D36: 0.74472222 | E36: 41.457901 | F36: 62.513 | G36: Evening (18-22) | H36: =TRUE() -> TRUE | I36: =FALSE() -> FALSE | J36: 1 | K36: BARBOURVILLE / CITY HALL | L36: membership | M36: 40906 | O36: KY | P36: 20.55 | Q36: 17.6 | R36: =INT(B36) -> 45965 | S36: =IF(AND(I36=TRUE(),COUNTIFS($R$5:R36,R36,$I$5:I36,TRUE())=1),1,0) -> 0 | T36: 0.4 | U36: 19.56 | V36: 16.58316 | W36: =SUM(Z36:AE36) -> 2.95 | X36: Tuesday | Y36: 45964 | Z36: 0.99 | AA36: 0 | AB36: 0 | AC36: 0 | AD36: 1.96 | AE36: 0 | AF36: =IF(AND(E36>0,COUNTIFS($R$5:R36,R36,$E$5:E36,">0")=1),1,0) -> 1 | AG36: =IF(AND(E36>0,COUNTIFS($R$5:R36,R36,$K$5:K36,K36,$E$5:E36,">0")=1),1,0) -> 1
A37: 4581774341 | B37: 45968.611 | C37: 45968.642 | D37: 0.75611111 | E37: 41.336102 | F37: 56.088 | G37: Day (12-18) | H37: =TRUE() -> TRUE | I37: =FALSE() -> FALSE | J37: 1 | K37: BARBOURVILLE / CITY HALL | L37: membership | M37: 40383 | O37: KY | P37: 20.54 | Q37: 17.6 | R37: =INT(B37) -> 45968 | S37: =IF(AND(I37=TRUE(),COUNTIFS($R$5:R37,R37,$I$5:I37,TRUE())=1),1,0) -> 0 | T37: 0.4 | U37: 19.55 | V37: 16.534441 | W37: =SUM(Z37:AE37) -> 2.94 | X37: Friday | Y37: 45964 | Z37: 0.99 | AA37: 0 | AB37: 0 | AC37: 0 | AD37: 1.95 | AE37: 0 | AF37: =IF(AND(E37>0,COUNTIFS($R$5:R37,R37,$E$5:E37,">0")=1),1,0) -> 1 | AG37: =IF(AND(E37>0,COUNTIFS($R$5:R37,R37,$K$5:K37,K37,$E$5:E37,">0")=1),1,0) -> 1
A38: 4582429001 | B38: 45968.752 | C38: 45968.772 | D38: 0.45888889 | E38: 23.511499 | F38: 60.604 | G38: Evening (18-22) | H38: =TRUE() -> TRUE | I38: =FALSE() -> FALSE | J38: 1 | K38: BARBOURVILLE / CITY HALL | L38: membership | M38: 45015 | N38: Butler County | O38: OH | P38: 11.8 | Q38: 10.12 | R38: =INT(B38) -> 45968 | S38: =IF(AND(I38=TRUE(),COUNTIFS($R$5:R38,R38,$I$5:I38,TRUE())=1),1,0) -> 0 | T38: 0.4 | U38: 11.24 | V38: 9.4045996 | W38: =SUM(Z38:AE38) -> 1.68 | X38: Friday | Y38: 45964 | Z38: 0.56 | AA38: 0 | AB38: 0 | AC38: 0 | AD38: 1.12 | AE38: 0 | AF38: =IF(AND(E38>0,COUNTIFS($R$5:R38,R38,$E$5:E38,">0")=1),1,0) -> 0 | AG38: =IF(AND(E38>0,COUNTIFS($R$5:R38,R38,$K$5:K38,K38,$E$5:E38,">0")=1),1,0) -> 0
A39: 4584727751 | B39: 45969.613 | C39: 45969.616 | D39: 0.073055556 | E39: 1.6401 | F39: 26.753 | G39: Day (12-18) | H39: =TRUE() -> TRUE | I39: =FALSE() -> FALSE | J39: 1 | K39: BARBOURVILLE / CITY HALL | L39: other | P39: 0.99 | Q39: 0.86 | R39: =INT(B39) -> 45969 | S39: =IF(AND(I39=TRUE(),COUNTIFS($R$5:R39,R39,$I$5:I39,TRUE())=1),1,0) -> 0 | T39: 0.4 | U39: 0.95 | V39: 0.65604 | W39: =SUM(Z39:AE39) -> 0.13 | X39: Saturday | Y39: 45964 | Z39: 0.04 | AA39: 0 | AB39: 0 | AC39: 0 | AD39: 0.09 | AE39: 0 | AF39: =IF(AND(E39>0,COUNTIFS($R$5:R39,R39,$E$5:E39,">0")=1),1,0) -> 1 | AG39: =IF(AND(E39>0,COUNTIFS($R$5:R39,R39,$K$5:K39,K39,$E$5:E39,">0")=1),1,0) -> 1
A40: 4584735501 | B40: 45969.617 | C40: 45969.63 | D40: 0.3075 | E40: 14.9243 | F40: 53.4 | G40: Day (12-18) | H40: =TRUE() -> TRUE | I40: =FALSE() -> FALSE | J40: 1 | K40: BARBOURVILLE / CITY HALL | L40: other | P40: 7.56 | Q40: 6.48 | R40: =INT(B40) -> 45969 | S40: =IF(AND(I40=TRUE(),COUNTIFS($R$5:R40,R40,$I$5:I40,TRUE())=1),1,0) -> 0 | T40: 0.4 | U40: 7.2 | V40: 5.96972 | W40: =SUM(Z40:AE40) -> 1.08 | X40: Saturday | Y40: 45964 | Z40: 0.36 | AA40: 0 | AB40: 0 | AC40: 0 | AD40: 0.72 | AE40: 0 | AF40: =IF(AND(E40>0,COUNTIFS($R$5:R40,R40,$E$5:E40,">0")=1),1,0) -> 0 | AG40: =IF(AND(E40>0,COUNTIFS($R$5:R40,R40,$K$5:K40,K40,$E$5:E40,">0")=1),1,0) -> 0
A41: 4587521521 | B41: 45970.824 | C41: 45970.884 | D41: 1.435 | E41: 63.373699 | F41: 62.523 | G41: Evening (18-22) | H41: =TRUE() -> TRUE | I41: =FALSE() -> FALSE | J41: 1 | K41: BARBOURVILLE / CITY HALL | L41: membership | M41: 40906 | O41: KY | P41: 32.61 | Q41: 27.98 | R41: =INT(B41) -> 45970 | S41: =IF(AND(I41=TRUE(),COUNTIFS($R$5:R41,R41,$I$5:I41,TRUE())=1),1,0) -> 0 | T41: 0.4 | U41: 31.09 | V41: 25.34948 | W41: =SUM(Z41:AE41) -> 4.63 | X41: Sunday | Y41: 45964 | Z41: 1.52 | AA41: 0 | AB41: 0 | AC41: 0 | AD41: 3.11 | AE41: 0 | AF41: =IF(AND(E41>0,COUNTIFS($R$5:R41,R41,$E$5:E41,">0")=1),1,0) -> 1 | AG41: =IF(AND(E41>0,COUNTIFS($R$5:R41,R41,$K$5:K41,K41,$E$5:E41,">0")=1),1,0) -> 1
A42: 4589744431 | B42: 45971.696 | C42: 45971.722 | D42: 0.62777778 | E42: 36.359001 | F42: 62.41 | G42: Day (12-18) | H42: =TRUE() -> TRUE | I42: =FALSE() -> FALSE | J42: 1 | K42: BARBOURVILLE / CITY HALL | L42: membership | M42: 37813 | O42: TN | P42: 17.92 | Q42: 15.35 | R42: =INT(B42) -> 45971 | S42: =IF(AND(I42=TRUE(),COUNTIFS($R$5:R42,R42,$I$5:I42,TRUE())=1),1,0) -> 0 | T42: 0.4 | U42: 17.05 | V42: 14.5436 | W42: =SUM(Z42:AE42) -> 2.57 | X42: Monday | Y42: 45971 | Z42: 0.87 | AA42: 0 | AB42: 0 | AC42: 0 | AD42: 1.7 | AE42: 0 | AF42: =IF(AND(E42>0,COUNTIFS($R$5:R42,R42,$E$5:E42,">0")=1),1,0) -> 1 | AG42: =IF(AND(E42>0,COUNTIFS($R$5:R42,R42,$K$5:K42,K42,$E$5:E42,">0")=1),1,0) -> 1
A43: 4603051091 | B43: 45975.778 | C43: 45975.822 | D43: 1.0611111 | E43: 62.974098 | F43: 62.882 | G43: Evening (18-22) | H43: =TRUE() -> TRUE | I43: =FALSE() -> FALSE | J43: 1 | K43: BARBOURVILLE / CITY HALL | L43: membership | M43: 40806 | N43: Harlan County | O43: KY | P43: 30.94 | Q43: 26.49 | R43: =INT(B43) -> 45975 | S43: =IF(AND(I43=TRUE(),COUNTIFS($R$5:R43,R43,$I$5:I43,TRUE())=1),1,0) -> 0 | T43: 0.4 | U43: 29.43 | V43: 25.189639 | W43: =SUM(Z43:AE43) -> 4.45 | X43: Friday | Y43: 45971 | Z43: 1.51 | AA43: 0 | AB43: 0 | AC43: 0 | AD43: 2.94 | AE43: 0 | AF43: =IF(AND(E43>0,COUNTIFS($R$5:R43,R43,$E$5:E43,">0")=1),1,0) -> 1 | AG43: =IF(AND(E43>0,COUNTIFS($R$5:R43,R43,$K$5:K43,K43,$E$5:E43,">0")=1),1,0) -> 1
A44: 4605493791 | B44: 45976.718 | C44: 45976.756 | D44: 0.91666667 | E44: 48.506901 | F44: 55.38 | G44: Day (12-18) | H44: =TRUE() -> TRUE | I44: =FALSE() -> FALSE | J44: 1 | K44: BARBOURVILLE / CITY HALL | L44: membership | M44: 40906 | O44: KY | P44: 24.23 | Q44: 20.76 | R44: =INT(B44) -> 45976 | S44: =IF(AND(I44=TRUE(),COUNTIFS($R$5:R44,R44,$I$5:I44,TRUE())=1),1,0) -> 0 | T44: 0.4 | U44: 23.07 | V44: 19.40276 | W44: =SUM(Z44:AE44) -> 3.47 | X44: Saturday | Y44: 45971 | Z44: 1.16 | AA44: 0 | AB44: 0 | AC44: 0 | AD44: 2.31 | AE44: 0 | AF44: =IF(AND(E44>0,COUNTIFS($R$5:R44,R44,$E$5:E44,">0")=1),1,0) -> 1 | AG44: =IF(AND(E44>0,COUNTIFS($R$5:R44,R44,$K$5:K44,K44,$E$5:E44,">0")=1),1,0) -> 1
A45: 4607466511 | B45: 45977.638 | C45: 45977.64 | D45: 0.036666667 | E45: 0 | G45: Day (12-18) | H45: =FALSE() -> FALSE | I45: =FALSE() -> FALSE | K45: BARBOURVILLE / CITY HALL | L45: credit_card_terminal | R45: =INT(B45) -> 45977 | S45: =IF(AND(I45=TRUE(),COUNTIFS($R$5:R45,R45,$I$5:I45,TRUE())=1),1,0) -> 0 | W45: =SUM(Z45:AE45) -> 0 | X45: Sunday | Y45: 45971 | AF45: =IF(AND(E45>0,COUNTIFS($R$5:R45,R45,$E$5:E45,">0")=1),1,0) -> 0 | AG45: =IF(AND(E45>0,COUNTIFS($R$5:R45,R45,$K$5:K45,K45,$E$5:E45,">0")=1),1,0) -> 0
A46: 4608121961 | B46: 45977.87 | C46: 45977.88 | D46: 0.25138889 | E46: 1.656913 | F46: 7.0231 | G46: Evening (18-22) | H46: =FALSE() -> FALSE | I46: =FALSE() -> FALSE | J46: 0 | K46: BARBOURVILLE / TOURISM | L46: credit_card_terminal | P46: 1.71 | Q46: 1.5 | R46: =INT(B46) -> 45977 | S46: =IF(AND(I46=TRUE(),COUNTIFS($R$5:R46,R46,$I$5:I46,TRUE())=1),1,0) -> 0 | T46: 0.4 | U46: 1.67 | V46: 0.6627652 | W46: =SUM(Z46:AE46) -> 0.21 | X46: Sunday | Y46: 45971 | Z46: 0.04 | AA46: 0 | AB46: 0 | AC46: 0 | AD46: 0.17 | AE46: 0 | AF46: =IF(AND(E46>0,COUNTIFS($R$5:R46,R46,$E$5:E46,">0")=1),1,0) -> 1 | AG46: =IF(AND(E46>0,COUNTIFS($R$5:R46,R46,$K$5:K46,K46,$E$5:E46,">0")=1),1,0) -> 1
A47: 4608160281 | B47: 45977.881 | C47: 45977.901 | D47: 0.47888889 | E47: 3.20775 | F47: 6.964 | G47: Evening (18-22) | H47: =FALSE() -> FALSE | I47: =FALSE() -> FALSE | J47: 0 | K47: BARBOURVILLE / TOURISM | L47: credit_card_terminal | P47: 3.28 | Q47: 2.88 | R47: =INT(B47) -> 45977 | S47: =IF(AND(I47=TRUE(),COUNTIFS($R$5:R47,R47,$I$5:I47,TRUE())=1),1,0) -> 0 | T47: 0.4 | U47: 3.2 | V47: 1.2831 | W47: =SUM(Z47:AE47) -> 0.4 | X47: Sunday | Y47: 45971 | Z47: 0.08 | AA47: 0 | AB47: 0 | AC47: 0 | AD47: 0.32 | AE47: 0 | AF47: =IF(AND(E47>0,COUNTIFS($R$5:R47,R47,$E$5:E47,">0")=1),1,0) -> 0 | AG47: =IF(AND(E47>0,COUNTIFS($R$5:R47,R47,$K$5:K47,K47,$E$5:E47,">0")=1),1,0) -> 0
A48: 4608260881 | B48: 45977.91 | C48: 45977.931 | D48: 0.52472222 | E48: 29.381399 | F48: 58.344 | G48: Evening (18-22) | H48: =TRUE() -> TRUE | I48: =FALSE() -> FALSE | J48: 1 | K48: BARBOURVILLE / CITY HALL | L48: credit_card_terminal | P48: 14.56 | Q48: 12.47 | R48: =INT(B48) -> 45977 | S48: =IF(AND(I48=TRUE(),COUNTIFS($R$5:R48,R48,$I$5:I48,TRUE())=1),1,0) -> 0 | T48: 0.4 | U48: 13.85 | V48: 11.75256 | W48: =SUM(Z48:AE48) -> 2.09 | X48: Sunday | Y48: 45971 | Z48: 0.71 | AA48: 0 | AB48: 0 | AC48: 0 | AD48: 1.38 | AE48: 0 | AF48: =IF(AND(E48>0,COUNTIFS($R$5:R48,R48,$E$5:E48,">0")=1),1,0) -> 0 | AG48: =IF(AND(E48>0,COUNTIFS($R$5:R48,R48,$K$5:K48,K48,$E$5:E48,">0")=1),1,0) -> 1
A49: 4614135981 | B49: 45979.825 | C49: 45979.883 | D49: 1.405 | E49: 72.0289 | F49: 62.474 | G49: Evening (18-22) | H49: =TRUE() -> TRUE | I49: =FALSE() -> FALSE | J49: 1 | K49: BARBOURVILLE / CITY HALL | L49: membership | M49: 40906 | O49: KY | P49: 36.16 | Q49: 30.99 | R49: =INT(B49) -> 45979 | S49: =IF(AND(I49=TRUE(),COUNTIFS($R$5:R49,R49,$I$5:I49,TRUE())=1),1,0) -> 0 | T49: 0.4 | U49: 34.43 | V49: 28.81156 | W49: =SUM(Z49:AE49) -> 5.17 | X49: Tuesday | Y49: 45978 | Z49: 1.73 | AA49: 0 | AB49: 0 | AC49: 0 | AD49: 3.44 | AE49: 0 | AF49: =IF(AND(E49>0,COUNTIFS($R$5:R49,R49,$E$5:E49,">0")=1),1,0) -> 1 | AG49: =IF(AND(E49>0,COUNTIFS($R$5:R49,R49,$K$5:K49,K49,$E$5:E49,">0")=1),1,0) -> 1
A50: 4617286741 | B50: 45980.763 | C50: 45980.816 | D50: 1.2611111 | E50: 21.8878 | F50: 18.252 | G50: Evening (18-22) | H50: =TRUE() -> TRUE | I50: =FALSE() -> FALSE | J50: 1 | K50: BARBOURVILLE / CITY HALL | L50: membership | M50: 29615 | N50: Greenville County | O50: SC | P50: 14.33 | Q50: 12.42 | R50: =INT(B50) -> 45980 | S50: =IF(AND(I50=TRUE(),COUNTIFS($R$5:R50,R50,$I$5:I50,TRUE())=1),1,0) -> 0 | T50: 0.4 | U50: 13.8 | V50: 8.75512 | W50: =SUM(Z50:AE50) -> 1.91 | X50: Wednesday | Y50: 45978 | Z50: 0.53 | AA50: 0 | AB50: 0 | AC50: 0 | AD50: 1.38 | AE50: 0 | AF50: =IF(AND(E50>0,COUNTIFS($R$5:R50,R50,$E$5:E50,">0")=1),1,0) -> 1 | AG50: =IF(AND(E50>0,COUNTIFS($R$5:R50,R50,$K$5:K50,K50,$E$5:E50,">0")=1),1,0) -> 1
A51: 4617870451 | B51: 45980.901 | C51: 45980.931 | D51: 0.735 | E51: 40.239601 | F51: 57.251 | G51: Evening (18-22) | H51: =TRUE() -> TRUE | I51: =FALSE() -> FALSE | J51: 1 | K51: BARBOURVILLE / CITY HALL | L51: membership | M51: 27703 | O51: NC | P51: 20.01 | Q51: 17.14 | R51: =INT(B51) -> 45980 | S51: =IF(AND(I51=TRUE(),COUNTIFS($R$5:R51,R51,$I$5:I51,TRUE())=1),1,0) -> 0 | T51: 0.4 | U51: 19.04 | V51: 16.09584 | W51: =SUM(Z51:AE51) -> 2.87 | X51: Wednesday | Y51: 45978 | Z51: 0.97 | AA51: 0 | AB51: 0 | AC51: 0 | AD51: 1.9 | AE51: 0 | AF51: =IF(AND(E51>0,COUNTIFS($R$5:R51,R51,$E$5:E51,">0")=1),1,0) -> 0 | AG51: =IF(AND(E51>0,COUNTIFS($R$5:R51,R51,$K$5:K51,K51,$E$5:E51,">0")=1),1,0) -> 0
A52: 4637998171 | B52: 45987.85 | C52: 45987.851 | D52: 0.031944444 | E52: 0 | F52: 0 | G52: Evening (18-22) | H52: =FALSE() -> FALSE | I52: =FALSE() -> FALSE | K52: BARBOURVILLE / TOURISM | L52: credit_card_terminal | R52: =INT(B52) -> 45987 | S52: =IF(AND(I52=TRUE(),COUNTIFS($R$5:R52,R52,$I$5:I52,TRUE())=1),1,0) -> 0 | W52: =SUM(Z52:AE52) -> 0 | X52: Wednesday | Y52: 45985 | AF52: =IF(AND(E52>0,COUNTIFS($R$5:R52,R52,$E$5:E52,">0")=1),1,0) -> 0 | AG52: =IF(AND(E52>0,COUNTIFS($R$5:R52,R52,$K$5:K52,K52,$E$5:E52,">0")=1),1,0) -> 0
A53: 4641229131 | B53: 45989.557 | C53: 45989.562 | D53: 0.11833333 | E53: 6.229 | F53: 0 | G53: Day (12-18) | H53: =FALSE() -> FALSE | I53: =FALSE() -> FALSE | K53: BARBOURVILLE / CITY HALL | L53: membership | M53: 53221 | N53: Milwaukee County | O53: WI | P53: 3.11 | Q53: 2.66 | R53: =INT(B53) -> 45989 | S53: =IF(AND(I53=TRUE(),COUNTIFS($R$5:R53,R53,$I$5:I53,TRUE())=1),1,0) -> 0 | T53: 0.4 | U53: 2.96 | V53: 2.4916 | W53: =SUM(Z53:AE53) -> 0.45 | X53: Friday | Y53: 45985 | Z53: 0.15 | AA53: 0 | AB53: 0 | AC53: 0 | AD53: 0.3 | AE53: 0 | AF53: =IF(AND(E53>0,COUNTIFS($R$5:R53,R53,$E$5:E53,">0")=1),1,0) -> 1 | AG53: =IF(AND(E53>0,COUNTIFS($R$5:R53,R53,$K$5:K53,K53,$E$5:E53,">0")=1),1,0) -> 1
A54: 4641596451 | B54: 45989.731 | C54: 45989.767 | D54: 0.86083333 | E54: 51.939098 | F54: 62.523 | G54: Day (12-18) | H54: =TRUE() -> TRUE | I54: =FALSE() -> FALSE | J54: 1 | K54: BARBOURVILLE / CITY HALL | L54: membership | M54: 43050 | O54: OH | P54: 25.47 | Q54: 21.8 | R54: =INT(B54) -> 45989 | S54: =IF(AND(I54=TRUE(),COUNTIFS($R$5:R54,R54,$I$5:I54,TRUE())=1),1,0) -> 0 | T54: 0.4 | U54: 24.22 | V54: 20.775639 | W54: =SUM(Z54:AE54) -> 3.67 | X54: Friday | Y54: 45985 | Z54: 1.25 | AA54: 0 | AB54: 0 | AC54: 0 | AD54: 2.42 | AE54: 0 | AF54: =IF(AND(E54>0,COUNTIFS($R$5:R54,R54,$E$5:E54,">0")=1),1,0) -> 0 | AG54: =IF(AND(E54>0,COUNTIFS($R$5:R54,R54,$K$5:K54,K54,$E$5:E54,">0")=1),1,0) -> 0
A55: 4641715541 | B55: 45989.773 | C55: 45989.818 | D55: 1.0627778 | E55: 60.9911 | F55: 62.513 | G55: Evening (18-22) | H55: =TRUE() -> TRUE | I55: =FALSE() -> FALSE | J55: 1 | K55: BARBOURVILLE / CITY HALL | L55: membership | M55: 40906 | O55: KY | P55: 30.11 | Q55: 25.79 | R55: =INT(B55) -> 45989 | S55: =IF(AND(I55=TRUE(),COUNTIFS($R$5:R55,R55,$I$5:I55,TRUE())=1),1,0) -> 0 | T55: 0.4 | U55: 28.65 | V55: 24.39644 | W55: =SUM(Z55:AE55) -> 4.32 | X55: Friday | Y55: 45985 | Z55: 1.46 | AA55: 0 | AB55: 0 | AC55: 0 | AD55: 2.86 | AE55: 0 | AF55: =IF(AND(E55>0,COUNTIFS($R$5:R55,R55,$E$5:E55,">0")=1),1,0) -> 0 | AG55: =IF(AND(E55>0,COUNTIFS($R$5:R55,R55,$K$5:K55,K55,$E$5:E55,">0")=1),1,0) -> 0
A56: 4643802021 | B56: 45990.755 | C56: 45990.769 | D56: 0.32583333 | E56: 2.312983 | F56: 7.3399 | G56: Evening (18-22) | H56: =FALSE() -> FALSE | I56: =FALSE() -> FALSE | J56: 0 | K56: BARBOURVILLE / TOURISM | L56: credit_card_terminal | P56: 2.29 | Q56: 2.01 | R56: =INT(B56) -> 45990 | S56: =IF(AND(I56=TRUE(),COUNTIFS($R$5:R56,R56,$I$5:I56,TRUE())=1),1,0) -> 0 | T56: 0.4 | U56: 2.23 | V56: 0.9251932 | W56: =SUM(Z56:AE56) -> 0.28 | X56: Saturday | Y56: 45985 | Z56: 0.06 | AA56: 0 | AB56: 0 | AC56: 0 | AD56: 0.22 | AE56: 0 | AF56: =IF(AND(E56>0,COUNTIFS($R$5:R56,R56,$E$5:E56,">0")=1),1,0) -> 1 | AG56: =IF(AND(E56>0,COUNTIFS($R$5:R56,R56,$K$5:K56,K56,$E$5:E56,">0")=1),1,0) -> 1
A57: 4644336541 | B57: 45990.928 | C57: 45990.929 | D57: 0.020833333 | E57: 0 | F57: 0 | G57: Night (22-6) | H57: =FALSE() -> FALSE | I57: =TRUE() -> TRUE | K57: BARBOURVILLE / CITY HALL | L57: membership | R57: =INT(B57) -> 45990 | S57: =IF(AND(I57=TRUE(),COUNTIFS($R$5:R57,R57,$I$5:I57,TRUE())=1),1,0) -> 1 | W57: =SUM(Z57:AE57) -> 0 | X57: Saturday | Y57: 45985 | AF57: =IF(AND(E57>0,COUNTIFS($R$5:R57,R57,$E$5:E57,">0")=1),1,0) -> 0 | AG57: =IF(AND(E57>0,COUNTIFS($R$5:R57,R57,$K$5:K57,K57,$E$5:E57,">0")=1),1,0) -> 0
A58: 4644745771 | B58: 45991.058 | C58: 45991.1 | D58: 1.0188889 | E58: 56.687801 | F58: 59.903 | G58: Night (22-6) | H58: =TRUE() -> TRUE | I58: =TRUE() -> TRUE | J58: 1 | K58: BARBOURVILLE / CITY HALL | L58: other | P58: 28.12 | Q58: 24.08 | R58: =INT(B58) -> 45991 | S58: =IF(AND(I58=TRUE(),COUNTIFS($R$5:R58,R58,$I$5:I58,TRUE())=1),1,0) -> 1 | T58: 0.4 | U58: 26.76 | V58: 22.67512 | W58: =SUM(Z58:AE58) -> 4.04 | X58: Sunday | Y58: 45985 | Z58: 1.36 | AA58: 0 | AB58: 0 | AC58: 0 | AD58: 2.68 | AE58: 0 | AF58: =IF(AND(E58>0,COUNTIFS($R$5:R58,R58,$E$5:E58,">0")=1),1,0) -> 1 | AG58: =IF(AND(E58>0,COUNTIFS($R$5:R58,R58,$K$5:K58,K58,$E$5:E58,">0")=1),1,0) -> 1
A59: 4646456341 | B59: 45991.938 | C59: 45991.947 | D59: 0.20722222 | E59: 6.1598 | F59: 0 | G59: Night (22-6) | H59: =FALSE() -> FALSE | I59: =TRUE() -> TRUE | K59: BARBOURVILLE / CITY HALL | L59: membership | M59: 29615 | N59: Greenville County | O59: SC | P59: 3.44 | Q59: 2.96 | R59: =INT(B59) -> 45991 | S59: =IF(AND(I59=TRUE(),COUNTIFS($R$5:R59,R59,$I$5:I59,TRUE())=1),1,0) -> 0 | T59: 0.4 | U59: 3.29 | V59: 2.46392 | W59: =SUM(Z59:AE59) -> 0.48 | X59: Sunday | Y59: 45985 | Z59: 0.15 | AA59: 0 | AB59: 0 | AC59: 0 | AD59: 0.33 | AE59: 0 | AF59: =IF(AND(E59>0,COUNTIFS($R$5:R59,R59,$E$5:E59,">0")=1),1,0) -> 0 | AG59: =IF(AND(E59>0,COUNTIFS($R$5:R59,R59,$K$5:K59,K59,$E$5:E59,">0")=1),1,0) -> 0
A60: 4646520411 | B60: 45991.957 | C60: 45991.995 | D60: 0.90777778 | E60: 20.563 | F60: 28.677 | G60: Night (22-6) | H60: =TRUE() -> TRUE | I60: =TRUE() -> TRUE | J60: 1 | K60: BARBOURVILLE / CITY HALL | L60: membership | M60: 29615 | N60: Greenville County | O60: SC | P60: 12.35 | Q60: 10.67 | R60: =INT(B60) -> 45991 | S60: =IF(AND(I60=TRUE(),COUNTIFS($R$5:R60,R60,$I$5:I60,TRUE())=1),1,0) -> 0 | T60: 0.4 | U60: 11.86 | V60: 8.2252 | W60: =SUM(Z60:AE60) -> 1.68 | X60: Sunday | Y60: 45985 | Z60: 0.49 | AA60: 0 | AB60: 0 | AC60: 0 | AD60: 1.19 | AE60: 0 | AF60: =IF(AND(E60>0,COUNTIFS($R$5:R60,R60,$E$5:E60,">0")=1),1,0) -> 0 | AG60: =IF(AND(E60>0,COUNTIFS($R$5:R60,R60,$K$5:K60,K60,$E$5:E60,">0")=1),1,0) -> 0
A61: 4648087231 | B61: 45992.634 | C61: 45992.634 | D61: 0.0125 | E61: 0 | F61: 0 | G61: Day (12-18) | H61: =FALSE() -> FALSE | I61: =FALSE() -> FALSE | K61: BARBOURVILLE / CITY HALL | L61: membership | R61: =INT(B61) -> 45992 | S61: =IF(AND(I61=TRUE(),COUNTIFS($R$5:R61,R61,$I$5:I61,TRUE())=1),1,0) -> 0 | W61: =SUM(Z61:AE61) -> 0 | X61: Monday | Y61: 45992 | AF61: =IF(AND(E61>0,COUNTIFS($R$5:R61,R61,$E$5:E61,">0")=1),1,0) -> 0 | AG61: =IF(AND(E61>0,COUNTIFS($R$5:R61,R61,$K$5:K61,K61,$E$5:E61,">0")=1),1,0) -> 0
A62: 4648092671 | B62: 45992.635 | C62: 45992.653 | D62: 0.42055556 | E62: 25.139 | F62: 62.799 | G62: Day (12-18) | H62: =TRUE() -> TRUE | I62: =FALSE() -> FALSE | J62: 0.97297297 | K62: BARBOURVILLE / CITY HALL | L62: membership | M62: 43050 | O62: OH | P62: 12.34 | Q62: 10.57 | R62: =INT(B62) -> 45992 | S62: =IF(AND(I62=TRUE(),COUNTIFS($R$5:R62,R62,$I$5:I62,TRUE())=1),1,0) -> 0 | T62: 0.4 | U62: 11.74 | V62: 10.0556 | W62: =SUM(Z62:AE62) -> 1.77 | X62: Monday | Y62: 45992 | Z62: 0.6 | AA62: 0 | AB62: 0 | AC62: 0 | AD62: 1.17 | AE62: 0 | AF62: =IF(AND(E62>0,COUNTIFS($R$5:R62,R62,$E$5:E62,">0")=1),1,0) -> 1 | AG62: =IF(AND(E62>0,COUNTIFS($R$5:R62,R62,$K$5:K62,K62,$E$5:E62,">0")=1),1,0) -> 1
A63: 4660368151 | B63: 45996.086 | C63: 45996.109 | D63: 0.55166667 | E63: 20.3325 | F63: 57.133 | G63: Night (22-6) | H63: =TRUE() -> TRUE | I63: =TRUE() -> TRUE | J63: 1 | K63: BARBOURVILLE / CITY HALL | L63: membership | M63: 37869 | O63: TN | P63: 10.83 | Q63: 9.31 | R63: =INT(B63) -> 45996 | S63: =IF(AND(I63=TRUE(),COUNTIFS($R$5:R63,R63,$I$5:I63,TRUE())=1),1,0) -> 1 | T63: 0.4 | U63: 10.34 | V63: 8.133 | W63: =SUM(Z63:AE63) -> 1.52 | X63: Friday | Y63: 45992 | Z63: 0.49 | AA63: 0 | AB63: 0 | AC63: 0 | AD63: 1.03 | AE63: 0 | AF63: =IF(AND(E63>0,COUNTIFS($R$5:R63,R63,$E$5:E63,">0")=1),1,0) -> 1 | AG63: =IF(AND(E63>0,COUNTIFS($R$5:R63,R63,$K$5:K63,K63,$E$5:E63,">0")=1),1,0) -> 1
A64: 4675208611 | B64: 46001.091 | C64: 46001.126 | D64: 0.82472222 | E64: 49.4212 | F64: 62.487 | G64: Night (22-6) | H64: =TRUE() -> TRUE | I64: =TRUE() -> TRUE | J64: 1 | K64: BARBOURVILLE / CITY HALL | L64: membership | M64: 40356 | N64: Jessamine County | O64: KY | P64: 24.26 | Q64: 20.76 | R64: =INT(B64) -> 46001 | S64: =IF(AND(I64=TRUE(),COUNTIFS($R$5:R64,R64,$I$5:I64,TRUE())=1),1,0) -> 1 | T64: 0.4 | U64: 23.07 | V64: 19.76848 | W64: =SUM(Z64:AE64) -> 3.5 | X64: Wednesday | Y64: 45999 | Z64: 1.19 | AA64: 0 | AB64: 0 | AC64: 0 | AD64: 2.31 | AE64: 0 | AF64: =IF(AND(E64>0,COUNTIFS($R$5:R64,R64,$E$5:E64,">0")=1),1,0) -> 1 | AG64: =IF(AND(E64>0,COUNTIFS($R$5:R64,R64,$K$5:K64,K64,$E$5:E64,">0")=1),1,0) -> 1
A65: 4678805351 | B65: 46002.161 | C65: 46002.183 | D65: 0.50861111 | E65: 29.437799 | F65: 62.472 | G65: Night (22-6) | H65: =TRUE() -> TRUE | I65: =TRUE() -> TRUE | J65: 1 | K65: BARBOURVILLE / CITY HALL | L65: membership | M65: 40806 | N65: Harlan County | O65: KY | P65: 14.52 | Q65: 12.43 | R65: =INT(B65) -> 46002 | S65: =IF(AND(I65=TRUE(),COUNTIFS($R$5:R65,R65,$I$5:I65,TRUE())=1),1,0) -> 1 | T65: 0.4 | U65: 13.81 | V65: 11.77512 | W65: =SUM(Z65:AE65) -> 2.09 | X65: Thursday | Y65: 45999 | Z65: 0.71 | AA65: 0 | AB65: 0 | AC65: 0 | AD65: 1.38 | AE65: 0 | AF65: =IF(AND(E65>0,COUNTIFS($R$5:R65,R65,$E$5:E65,">0")=1),1,0) -> 1 | AG65: =IF(AND(E65>0,COUNTIFS($R$5:R65,R65,$K$5:K65,K65,$E$5:E65,">0")=1),1,0) -> 1
A66: 4684013521 | B66: 46003.805 | C66: 46003.808 | D66: 0.076944444 | E66: 3.4989 | F66: 0 | G66: Evening (18-22) | H66: =FALSE() -> FALSE | I66: =FALSE() -> FALSE | K66: BARBOURVILLE / CITY HALL | L66: membership | M66: 40906 | O66: KY | P66: 1.79 | Q66: 1.54 | R66: =INT(B66) -> 46003 | S66: =IF(AND(I66=TRUE(),COUNTIFS($R$5:R66,R66,$I$5:I66,TRUE())=1),1,0) -> 0 | T66: 0.4 | U66: 1.71 | V66: 1.39956 | W66: =SUM(Z66:AE66) -> 0.25 | X66: Friday | Y66: 45999 | Z66: 0.08 | AA66: 0 | AB66: 0 | AC66: 0 | AD66: 0.17 | AE66: 0 | AF66: =IF(AND(E66>0,COUNTIFS($R$5:R66,R66,$E$5:E66,">0")=1),1,0) -> 1 | AG66: =IF(AND(E66>0,COUNTIFS($R$5:R66,R66,$K$5:K66,K66,$E$5:E66,">0")=1),1,0) -> 1
A67: 4686616141 | B67: 46004.762 | C67: 46005.139 | D67: 9.0588889 | E67: 62.976509 | F67: 7.051 | G67: Evening (18-22) | H67: =FALSE() -> FALSE | I67: =FALSE() -> FALSE | J67: 0 | K67: BARBOURVILLE / TOURISM | L67: phone_online | P67: 63.93 | Q67: 56.18 | R67: =INT(B67) -> 46004 | S67: =IF(AND(I67=TRUE(),COUNTIFS($R$5:R67,R67,$I$5:I67,TRUE())=1),1,0) -> 0 | T67: 0.4 | U67: 61.43 | V67: 25.190604 | W67: =SUM(Z67:AE67) -> 7.75 | X67: Saturday | Y67: 45999 | Z67: 1.51 | AA67: 0 | AB67: 0 | AC67: 0 | AD67: 5.25 | AE67: 0.99 | AF67: =IF(AND(E67>0,COUNTIFS($R$5:R67,R67,$E$5:E67,">0")=1),1,0) -> 1 | AG67: =IF(AND(E67>0,COUNTIFS($R$5:R67,R67,$K$5:K67,K67,$E$5:E67,">0")=1),1,0) -> 1
A68: 4690212021 | B68: 46006.158 | C68: 46006.18 | D68: 0.51583333 | E68: 22.837601 | F68: 48.36 | G68: Night (22-6) | H68: =TRUE() -> TRUE | I68: =TRUE() -> TRUE | J68: 1 | K68: BARBOURVILLE / CITY HALL | L68: membership | M68: 60194 | N68: Cook County | O68: IL | P68: 11.75 | Q68: 10.08 | R68: =INT(B68) -> 46006 | S68: =IF(AND(I68=TRUE(),COUNTIFS($R$5:R68,R68,$I$5:I68,TRUE())=1),1,0) -> 1 | T68: 0.4 | U68: 11.2 | V68: 9.1350404 | W68: =SUM(Z68:AE68) -> 1.67 | X68: Monday | Y68: 46006 | Z68: 0.55 | AA68: 0 | AB68: 0 | AC68: 0 | AD68: 1.12 | AE68: 0 | AF68: =IF(AND(E68>0,COUNTIFS($R$5:R68,R68,$E$5:E68,">0")=1),1,0) -> 1 | AG68: =IF(AND(E68>0,COUNTIFS($R$5:R68,R68,$K$5:K68,K68,$E$5:E68,">0")=1),1,0) -> 1
A69: 4692214171 | B69: 46006.874 | C69: 46006.877 | D69: 0.062222222 | E69: 1.366 | F69: 0 | G69: Evening (18-22) | H69: =FALSE() -> FALSE | I69: =FALSE() -> FALSE | K69: BARBOURVILLE / CITY HALL | L69: credit_card_terminal | P69: 0.83 | Q69: 0.72 | R69: =INT(B69) -> 46006 | S69: =IF(AND(I69=TRUE(),COUNTIFS($R$5:R69,R69,$I$5:I69,TRUE())=1),1,0) -> 0 | T69: 0.4 | U69: 0.8 | V69: 0.5464 | W69: =SUM(Z69:AE69) -> 0.11 | X69: Monday | Y69: 46006 | Z69: 0.03 | AA69: 0 | AB69: 0 | AC69: 0 | AD69: 0.08 | AE69: 0 | AF69: =IF(AND(E69>0,COUNTIFS($R$5:R69,R69,$E$5:E69,">0")=1),1,0) -> 0 | AG69: =IF(AND(E69>0,COUNTIFS($R$5:R69,R69,$K$5:K69,K69,$E$5:E69,">0")=1),1,0) -> 0
A70: 4696438731 | B70: 46008.065 | C70: 46008.1 | D70: 0.83972222 | E70: 39.279499 | F70: 53.4 | G70: Night (22-6) | H70: =TRUE() -> TRUE | I70: =TRUE() -> TRUE | J70: 1 | K70: BARBOURVILLE / CITY HALL | L70: other | P70: 20.01 | Q70: 17.16 | R70: =INT(B70) -> 46008 | S70: =IF(AND(I70=TRUE(),COUNTIFS($R$5:R70,R70,$I$5:I70,TRUE())=1),1,0) -> 1 | T70: 0.4 | U70: 19.07 | V70: 15.7118 | W70: =SUM(Z70:AE70) -> 2.85 | X70: Wednesday | Y70: 46006 | Z70: 0.94 | AA70: 0 | AB70: 0 | AC70: 0 | AD70: 1.91 | AE70: 0 | AF70: =IF(AND(E70>0,COUNTIFS($R$5:R70,R70,$E$5:E70,">0")=1),1,0) -> 1 | AG70: =IF(AND(E70>0,COUNTIFS($R$5:R70,R70,$K$5:K70,K70,$E$5:E70,">0")=1),1,0) -> 1
A71: 4702449141 | B71: 46009.926 | C71: 46009.943 | D71: 0.39972222 | E71: 18.4666 | F71: 47.895 | G71: Night (22-6) | H71: =TRUE() -> TRUE | I71: =TRUE() -> TRUE | J71: 1 | K71: BARBOURVILLE / CITY HALL | L71: membership | M71: 41653 | O71: KY | P71: 9.43 | Q71: 8.09 | R71: =INT(B71) -> 46009 | S71: =IF(AND(I71=TRUE(),COUNTIFS($R$5:R71,R71,$I$5:I71,TRUE())=1),1,0) -> 1 | T71: 0.4 | U71: 8.99 | V71: 7.38664 | W71: =SUM(Z71:AE71) -> 1.34 | X71: Thursday | Y71: 46006 | Z71: 0.44 | AA71: 0 | AB71: 0 | AC71: 0 | AD71: 0.9 | AE71: 0 | AF71: =IF(AND(E71>0,COUNTIFS($R$5:R71,R71,$E$5:E71,">0")=1),1,0) -> 1 | AG71: =IF(AND(E71>0,COUNTIFS($R$5:R71,R71,$K$5:K71,K71,$E$5:E71,">0")=1),1,0) -> 1
A72: 4707150431 | B72: 46011.551 | C72: 46011.577 | D72: 0.63694444 | E72: 34.400398 | F72: 56.939 | G72: Day (12-18) | H72: =TRUE() -> TRUE | I72: =FALSE() -> FALSE | J72: 1 | K72: BARBOURVILLE / CITY HALL | L72: phone_online | P72: 18.28 | Q72: 14.68 | R72: =INT(B72) -> 46011 | S72: =IF(AND(I72=TRUE(),COUNTIFS($R$5:R72,R72,$I$5:I72,TRUE())=1),1,0) -> 0 | T72: 0.4 | U72: 16.31 | V72: 13.760159 | W72: =SUM(Z72:AE72) -> 2.61 | X72: Saturday | Y72: 46006 | Z72: 0.98 | AA72: 0 | AB72: 0 | AC72: 0 | AD72: 0.64 | AE72: 0.99 | AF72: =IF(AND(E72>0,COUNTIFS($R$5:R72,R72,$E$5:E72,">0")=1),1,0) -> 1 | AG72: =IF(AND(E72>0,COUNTIFS($R$5:R72,R72,$K$5:K72,K72,$E$5:E72,">0")=1),1,0) -> 1
A73: 4708308331 | B73: 46011.945 | C73: 46011.946 | D73: 0.036388889 | E73: 0 | G73: Night (22-6) | H73: =FALSE() -> FALSE | I73: =TRUE() -> TRUE | K73: BARBOURVILLE / CITY HALL | L73: credit_card_terminal | R73: =INT(B73) -> 46011 | S73: =IF(AND(I73=TRUE(),COUNTIFS($R$5:R73,R73,$I$5:I73,TRUE())=1),1,0) -> 1 | W73: =SUM(Z73:AE73) -> 0 | X73: Saturday | Y73: 46006 | AF73: =IF(AND(E73>0,COUNTIFS($R$5:R73,R73,$E$5:E73,">0")=1),1,0) -> 0 | AG73: =IF(AND(E73>0,COUNTIFS($R$5:R73,R73,$K$5:K73,K73,$E$5:E73,">0")=1),1,0) -> 0
A74: 4708324491 | B74: 46011.951 | C74: 46012.003 | D74: 1.2705556 | E74: 9.172431 | F74: 7.3299 | G74: Night (22-6) | H74: =FALSE() -> FALSE | I74: =TRUE() -> TRUE | J74: 0 | K74: BARBOURVILLE / TOURISM | L74: credit_card_terminal | P74: 8.97 | Q74: 7.88 | R74: =INT(B74) -> 46011 | S74: =IF(AND(I74=TRUE(),COUNTIFS($R$5:R74,R74,$I$5:I74,TRUE())=1),1,0) -> 0 | T74: 0.4 | U74: 8.75 | V74: 3.6689724 | W74: =SUM(Z74:AE74) -> 1.09 | X74: Saturday | Y74: 46006 | Z74: 0.22 | AA74: 0 | AB74: 0 | AC74: 0 | AD74: 0.87 | AE74: 0 | AF74: =IF(AND(E74>0,COUNTIFS($R$5:R74,R74,$E$5:E74,">0")=1),1,0) -> 0 | AG74: =IF(AND(E74>0,COUNTIFS($R$5:R74,R74,$K$5:K74,K74,$E$5:E74,">0")=1),1,0) -> 1
A75: 4709720391 | B75: 46012.689 | C75: 46012.69 | D75: 0.0275 | E75: 0.0054 | F75: 0 | G75: Day (12-18) | H75: =FALSE() -> FALSE | I75: =FALSE() -> FALSE | K75: BARBOURVILLE / CITY HALL | L75: membership | R75: =INT(B75) -> 46012 | S75: =IF(AND(I75=TRUE(),COUNTIFS($R$5:R75,R75,$I$5:I75,TRUE())=1),1,0) -> 0 | W75: =SUM(Z75:AE75) -> 0 | X75: Sunday | Y75: 46006 | AF75: =IF(AND(E75>0,COUNTIFS($R$5:R75,R75,$E$5:E75,">0")=1),1,0) -> 1 | AG75: =IF(AND(E75>0,COUNTIFS($R$5:R75,R75,$K$5:K75,K75,$E$5:E75,">0")=1),1,0) -> 1
A76: 4709723941 | B76: 46012.69 | C76: 46012.72 | D76: 0.72305556 | E76: 43.850101 | F76: 62.576 | G76: Day (12-18) | H76: =TRUE() -> TRUE | I76: =FALSE() -> FALSE | J76: 1 | K76: BARBOURVILLE / CITY HALL | L76: membership | M76: 34202 | N76: Manatee County | O76: FL | P76: 21.48 | Q76: 18.39 | R76: =INT(B76) -> 46012 | S76: =IF(AND(I76=TRUE(),COUNTIFS($R$5:R76,R76,$I$5:I76,TRUE())=1),1,0) -> 0 | T76: 0.4 | U76: 20.43 | V76: 17.54004 | W76: =SUM(Z76:AE76) -> 3.09 | X76: Sunday | Y76: 46006 | Z76: 1.05 | AA76: 0 | AB76: 0 | AC76: 0 | AD76: 2.04 | AE76: 0 | AF76: =IF(AND(E76>0,COUNTIFS($R$5:R76,R76,$E$5:E76,">0")=1),1,0) -> 0 | AG76: =IF(AND(E76>0,COUNTIFS($R$5:R76,R76,$K$5:K76,K76,$E$5:E76,">0")=1),1,0) -> 0
A77: 4710063501 | B77: 46012.81 | C77: 46012.838 | D77: 0.67111111 | E77: 4.446568 | F77: 7.0803 | G77: Evening (18-22) | H77: =FALSE() -> FALSE | I77: =FALSE() -> FALSE | J77: 0 | K77: BARBOURVILLE / TOURISM | L77: credit_card_terminal | P77: 4.57 | Q77: 4.01 | R77: =INT(B77) -> 46012 | S77: =IF(AND(I77=TRUE(),COUNTIFS($R$5:R77,R77,$I$5:I77,TRUE())=1),1,0) -> 0 | T77: 0.4 | U77: 4.46 | V77: 1.7786272 | W77: =SUM(Z77:AE77) -> 0.56 | X77: Sunday | Y77: 46006 | Z77: 0.11 | AA77: 0 | AB77: 0 | AC77: 0 | AD77: 0.45 | AE77: 0 | AF77: =IF(AND(E77>0,COUNTIFS($R$5:R77,R77,$E$5:E77,">0")=1),1,0) -> 0 | AG77: =IF(AND(E77>0,COUNTIFS($R$5:R77,R77,$K$5:K77,K77,$E$5:E77,">0")=1),1,0) -> 1
A78: 4710216931 | B78: 46012.859 | C78: 46013.117 | D78: 6.1772222 | E78: 43.365398 | F78: 7.0903 | G78: Evening (18-22) | H78: =FALSE() -> FALSE | I78: =FALSE() -> FALSE | J78: 0 | K78: BARBOURVILLE / TOURISM | L78: credit_card_terminal | P78: 43.1 | Q78: 37.85 | R78: =INT(B78) -> 46012 | S78: =IF(AND(I78=TRUE(),COUNTIFS($R$5:R78,R78,$I$5:I78,TRUE())=1),1,0) -> 0 | T78: 0.4 | U78: 42.06 | V78: 17.346159 | W78: =SUM(Z78:AE78) -> 5.25 | X78: Sunday | Y78: 46006 | Z78: 1.04 | AA78: 0 | AB78: 0 | AC78: 0 | AD78: 4.21 | AE78: 0 | AF78: =IF(AND(E78>0,COUNTIFS($R$5:R78,R78,$E$5:E78,">0")=1),1,0) -> 0 | AG78: =IF(AND(E78>0,COUNTIFS($R$5:R78,R78,$K$5:K78,K78,$E$5:E78,">0")=1),1,0) -> 0
A79: 4710729371 | B79: 46013.014 | C79: 46013.038 | D79: 0.56833333 | E79: 31.301399 | F79: 56.549 | G79: Night (22-6) | H79: =TRUE() -> TRUE | I79: =TRUE() -> TRUE | J79: 1 | K79: BARBOURVILLE / CITY HALL | L79: membership | M79: 37601 | O79: TN | P79: 15.54 | Q79: 13.31 | R79: =INT(B79) -> 46013 | S79: =IF(AND(I79=TRUE(),COUNTIFS($R$5:R79,R79,$I$5:I79,TRUE())=1),1,0) -> 1 | T79: 0.4 | U79: 14.79 | V79: 12.52056 | W79: =SUM(Z79:AE79) -> 2.23 | X79: Monday | Y79: 46013 | Z79: 0.75 | AA79: 0 | AB79: 0 | AC79: 0 | AD79: 1.48 | AE79: 0 | AF79: =IF(AND(E79>0,COUNTIFS($R$5:R79,R79,$E$5:E79,">0")=1),1,0) -> 1 | AG79: =IF(AND(E79>0,COUNTIFS($R$5:R79,R79,$K$5:K79,K79,$E$5:E79,">0")=1),1,0) -> 1
A80: 4711406781 | B80: 46013.266 | C80: 46013.268 | D80: 0.040555556 | E80: 0 | F80: 0 | G80: Morning (6-12) | H80: =FALSE() -> FALSE | I80: =FALSE() -> FALSE | K80: BARBOURVILLE / CITY HALL | L80: credit_card_terminal | R80: =INT(B80) -> 46013 | S80: =IF(AND(I80=TRUE(),COUNTIFS($R$5:R80,R80,$I$5:I80,TRUE())=1),1,0) -> 0 | W80: =SUM(Z80:AE80) -> 0 | X80: Monday | Y80: 46013 | AF80: =IF(AND(E80>0,COUNTIFS($R$5:R80,R80,$E$5:E80,">0")=1),1,0) -> 0 | AG80: =IF(AND(E80>0,COUNTIFS($R$5:R80,R80,$K$5:K80,K80,$E$5:E80,">0")=1),1,0) -> 0
A81: 4711421421 | B81: 46013.282 | C81: 46013.359 | D81: 1.8469444 | E81: 45.4538 | F81: 38.976 | G81: Morning (6-12) | H81: =TRUE() -> TRUE | I81: =FALSE() -> FALSE | J81: 0.85490892 | K81: BARBOURVILLE / CITY HALL | L81: credit_card_terminal | P81: 26.66 | Q81: 23.01 | R81: =INT(B81) -> 46013 | S81: =IF(AND(I81=TRUE(),COUNTIFS($R$5:R81,R81,$I$5:I81,TRUE())=1),1,0) -> 0 | T81: 0.4 | U81: 25.57 | V81: 18.18152 | W81: =SUM(Z81:AE81) -> 3.65 | X81: Monday | Y81: 46013 | Z81: 1.09 | AA81: 0 | AB81: 0 | AC81: 0 | AD81: 2.56 | AE81: 0 | AF81: =IF(AND(E81>0,COUNTIFS($R$5:R81,R81,$E$5:E81,">0")=1),1,0) -> 0 | AG81: =IF(AND(E81>0,COUNTIFS($R$5:R81,R81,$K$5:K81,K81,$E$5:E81,">0")=1),1,0) -> 0
A82: 4712182861 | B82: 46013.692 | C82: 46013.693 | D82: 0.031666667 | E82: 0 | F82: 0 | G82: Day (12-18) | H82: =FALSE() -> FALSE | I82: =FALSE() -> FALSE | K82: BARBOURVILLE / TOURISM | L82: phone_online | R82: =INT(B82) -> 46013 | S82: =IF(AND(I82=TRUE(),COUNTIFS($R$5:R82,R82,$I$5:I82,TRUE())=1),1,0) -> 0 | W82: =SUM(Z82:AE82) -> 0 | X82: Monday | Y82: 46013 | AF82: =IF(AND(E82>0,COUNTIFS($R$5:R82,R82,$E$5:E82,">0")=1),1,0) -> 0 | AG82: =IF(AND(E82>0,COUNTIFS($R$5:R82,R82,$K$5:K82,K82,$E$5:E82,">0")=1),1,0) -> 0
A83: 4712260231 | B83: 46013.711 | C83: 46013.749 | D83: 0.925 | E83: 48.287498 | F83: 56.055 | G83: Day (12-18) | H83: =TRUE() -> TRUE | I83: =FALSE() -> FALSE | J83: 1 | K83: BARBOURVILLE / CITY HALL | L83: membership | M83: 40059 | O83: KY | P83: 24.18 | Q83: 20.72 | R83: =INT(B83) -> 46013 | S83: =IF(AND(I83=TRUE(),COUNTIFS($R$5:R83,R83,$I$5:I83,TRUE())=1),1,0) -> 0 | T83: 0.4 | U83: 23.02 | V83: 19.314999 | W83: =SUM(Z83:AE83) -> 3.46 | X83: Monday | Y83: 46013 | Z83: 1.16 | AA83: 0 | AB83: 0 | AC83: 0 | AD83: 2.3 | AE83: 0 | AF83: =IF(AND(E83>0,COUNTIFS($R$5:R83,R83,$E$5:E83,">0")=1),1,0) -> 0 | AG83: =IF(AND(E83>0,COUNTIFS($R$5:R83,R83,$K$5:K83,K83,$E$5:E83,">0")=1),1,0) -> 0
A84: 4712308231 | B84: 46013.722 | C84: 46013.908 | D84: 4.4719444 | E84: 31.527758 | F84: 7.1514 | G84: Day (12-18) | H84: =FALSE() -> FALSE | I84: =FALSE() -> FALSE | J84: 0 | K84: BARBOURVILLE / TOURISM | L84: phone_online | P84: 32.25 | Q84: 28.34 | R84: =INT(B84) -> 46013 | S84: =IF(AND(I84=TRUE(),COUNTIFS($R$5:R84,R84,$I$5:I84,TRUE())=1),1,0) -> 0 | T84: 0.4 | U84: 30.5 | V84: 12.611103 | W84: =SUM(Z84:AE84) -> 3.91 | X84: Monday | Y84: 46013 | Z84: 0.76 | AA84: 0 | AB84: 0 | AC84: 0 | AD84: 2.16 | AE84: 0.99 | AF84: =IF(AND(E84>0,COUNTIFS($R$5:R84,R84,$E$5:E84,">0")=1),1,0) -> 0 | AG84: =IF(AND(E84>0,COUNTIFS($R$5:R84,R84,$K$5:K84,K84,$E$5:E84,">0")=1),1,0) -> 1
A85: 4715306981 | B85: 46014.754 | C85: 46014.945 | D85: 4.57 | E85: 50.118999 | F85: 61.619 | G85: Evening (18-22) | H85: =TRUE() -> TRUE | I85: =FALSE() -> FALSE | J85: 0.26122372 | K85: BARBOURVILLE / CITY HALL | L85: credit_card_terminal | P85: 39.53 | Q85: 34.5 | R85: =INT(B85) -> 46014 | S85: =IF(AND(I85=TRUE(),COUNTIFS($R$5:R85,R85,$I$5:I85,TRUE())=1),1,0) -> 0 | T85: 0.4 | U85: 38.33 | V85: 20.0476 | W85: =SUM(Z85:AE85) -> 5.03 | X85: Tuesday | Y85: 46013 | Z85: 1.2 | AA85: 0 | AB85: 0 | AC85: 0 | AD85: 3.83 | AE85: 0 | AF85: =IF(AND(E85>0,COUNTIFS($R$5:R85,R85,$E$5:E85,">0")=1),1,0) -> 1 | AG85: =IF(AND(E85>0,COUNTIFS($R$5:R85,R85,$K$5:K85,K85,$E$5:E85,">0")=1),1,0) -> 1
A86: 4721588251 | B86: 46017.905 | C86: 46017.906 | D86: 0.015833333 | E86: 0 | F86: 0 | G86: Evening (18-22) | H86: =FALSE() -> FALSE | I86: =FALSE() -> FALSE | K86: BARBOURVILLE / CITY HALL | L86: membership | R86: =INT(B86) -> 46017 | S86: =IF(AND(I86=TRUE(),COUNTIFS($R$5:R86,R86,$I$5:I86,TRUE())=1),1,0) -> 0 | W86: =SUM(Z86:AE86) -> 0 | X86: Friday | Y86: 46013 | AF86: =IF(AND(E86>0,COUNTIFS($R$5:R86,R86,$E$5:E86,">0")=1),1,0) -> 0 | AG86: =IF(AND(E86>0,COUNTIFS($R$5:R86,R86,$K$5:K86,K86,$E$5:E86,">0")=1),1,0) -> 0
A87: 4721591431 | B87: 46017.906 | C87: 46017.908 | D87: 0.036666667 | E87: 0 | F87: 0 | G87: Evening (18-22) | H87: =FALSE() -> FALSE | I87: =FALSE() -> FALSE | K87: BARBOURVILLE / CITY HALL | L87: membership | R87: =INT(B87) -> 46017 | S87: =IF(AND(I87=TRUE(),COUNTIFS($R$5:R87,R87,$I$5:I87,TRUE())=1),1,0) -> 0 | W87: =SUM(Z87:AE87) -> 0 | X87: Friday | Y87: 46013 | AF87: =IF(AND(E87>0,COUNTIFS($R$5:R87,R87,$E$5:E87,">0")=1),1,0) -> 0 | AG87: =IF(AND(E87>0,COUNTIFS($R$5:R87,R87,$K$5:K87,K87,$E$5:E87,">0")=1),1,0) -> 0
A88: 4721599241 | B88: 46017.907 | C88: 46017.909 | D88: 0.031944444 | E88: 0 | F88: 0 | G88: Evening (18-22) | H88: =FALSE() -> FALSE | I88: =FALSE() -> FALSE | K88: BARBOURVILLE / TOURISM | L88: membership | R88: =INT(B88) -> 46017 | S88: =IF(AND(I88=TRUE(),COUNTIFS($R$5:R88,R88,$I$5:I88,TRUE())=1),1,0) -> 0 | W88: =SUM(Z88:AE88) -> 0 | X88: Friday | Y88: 46013 | AF88: =IF(AND(E88>0,COUNTIFS($R$5:R88,R88,$E$5:E88,">0")=1),1,0) -> 0 | AG88: =IF(AND(E88>0,COUNTIFS($R$5:R88,R88,$K$5:K88,K88,$E$5:E88,">0")=1),1,0) -> 0
A89: 4721839241 | B89: 46017.988 | C89: 46018.002 | D89: 0.34416667 | E89: 19.7619 | F89: 61.931 | G89: Night (22-6) | H89: =TRUE() -> TRUE | I89: =TRUE() -> TRUE | J89: 1 | K89: BARBOURVILLE / CITY HALL | L89: credit_card_terminal | P89: 9.75 | Q89: 8.35 | R89: =INT(B89) -> 46017 | S89: =IF(AND(I89=TRUE(),COUNTIFS($R$5:R89,R89,$I$5:I89,TRUE())=1),1,0) -> 1 | T89: 0.4 | U89: 9.28 | V89: 7.90476 | W89: =SUM(Z89:AE89) -> 1.4 | X89: Friday | Y89: 46013 | Z89: 0.47 | AA89: 0 | AB89: 0 | AC89: 0 | AD89: 0.93 | AE89: 0 | AF89: =IF(AND(E89>0,COUNTIFS($R$5:R89,R89,$E$5:E89,">0")=1),1,0) -> 1 | AG89: =IF(AND(E89>0,COUNTIFS($R$5:R89,R89,$K$5:K89,K89,$E$5:E89,">0")=1),1,0) -> 1
A90: 4722921421 | B90: 46018.669 | C90: 46018.704 | D90: 0.8225 | E90: 38.716202 | F90: 53.549 | G90: Day (12-18) | H90: =TRUE() -> TRUE | I90: =FALSE() -> FALSE | J90: 1 | K90: BARBOURVILLE / CITY HALL | L90: membership | M90: 54165 | O90: WI | P90: 19.71 | Q90: 16.9 | R90: =INT(B90) -> 46018 | S90: =IF(AND(I90=TRUE(),COUNTIFS($R$5:R90,R90,$I$5:I90,TRUE())=1),1,0) -> 0 | T90: 0.4 | U90: 18.78 | V90: 15.486481 | W90: =SUM(Z90:AE90) -> 2.81 | X90: Saturday | Y90: 46013 | Z90: 0.93 | AA90: 0 | AB90: 0 | AC90: 0 | AD90: 1.88 | AE90: 0 | AF90: =IF(AND(E90>0,COUNTIFS($R$5:R90,R90,$E$5:E90,">0")=1),1,0) -> 1 | AG90: =IF(AND(E90>0,COUNTIFS($R$5:R90,R90,$K$5:K90,K90,$E$5:E90,">0")=1),1,0) -> 1
A91: 4723077581 | B91: 46018.735 | C91: 46018.79 | D91: 1.3169444 | E91: 42.318802 | F91: 53.639 | G91: Day (12-18) | H91: =TRUE() -> TRUE | I91: =FALSE() -> FALSE | J91: 1 | K91: BARBOURVILLE / CITY HALL | L91: credit_card_terminal | P91: 23.22 | Q91: 19.98 | R91: =INT(B91) -> 46018 | S91: =IF(AND(I91=TRUE(),COUNTIFS($R$5:R91,R91,$I$5:I91,TRUE())=1),1,0) -> 0 | T91: 0.4 | U91: 22.2 | V91: 16.927521 | W91: =SUM(Z91:AE91) -> 3.24 | X91: Saturday | Y91: 46013 | Z91: 1.02 | AA91: 0 | AB91: 0 | AC91: 0 | AD91: 2.22 | AE91: 0 | AF91: =IF(AND(E91>0,COUNTIFS($R$5:R91,R91,$E$5:E91,">0")=1),1,0) -> 0 | AG91: =IF(AND(E91>0,COUNTIFS($R$5:R91,R91,$K$5:K91,K91,$E$5:E91,">0")=1),1,0) -> 0
A92: 4724893031 | B92: 46019.686 | C92: 46019.718 | D92: 0.75611111 | E92: 18.436001 | F92: 41.327 | G92: Day (12-18) | H92: =TRUE() -> TRUE | I92: =FALSE() -> FALSE | J92: 1 | K92: BARBOURVILLE / CITY HALL | L92: credit_card_terminal | P92: 10.83 | Q92: 9.35 | R92: =INT(B92) -> 46019 | S92: =IF(AND(I92=TRUE(),COUNTIFS($R$5:R92,R92,$I$5:I92,TRUE())=1),1,0) -> 0 | T92: 0.4 | U92: 10.39 | V92: 7.3744004 | W92: =SUM(Z92:AE92) -> 1.48 | X92: Sunday | Y92: 46013 | Z92: 0.44 | AA92: 0 | AB92: 0 | AC92: 0 | AD92: 1.04 | AE92: 0 | AF92: =IF(AND(E92>0,COUNTIFS($R$5:R92,R92,$E$5:E92,">0")=1),1,0) -> 1 | AG92: =IF(AND(E92>0,COUNTIFS($R$5:R92,R92,$K$5:K92,K92,$E$5:E92,">0")=1),1,0) -> 1
A93: 4727829791 | B93: 46020.927 | C93: 46020.965 | D93: 0.90666667 | E93: 30.217699 | F93: 39.055 | G93: Night (22-6) | H93: =TRUE() -> TRUE | I93: =TRUE() -> TRUE | J93: 0.66666667 | K93: BARBOURVILLE / CITY HALL | L93: membership | M93: 27045 | O93: NC | P93: 11.89 | Q93: 10.28 | R93: =INT(B93) -> 46020 | S93: =IF(AND(I93=TRUE(),COUNTIFS($R$5:R93,R93,$I$5:I93,TRUE())=1),1,0) -> 1 | T93: 0.4 | U93: 11.42 | V93: 12.08708 | W93: =SUM(Z93:AE93) -> 1.61 | X93: Monday | Y93: 46020 | Z93: 0.47 | AA93: 0 | AB93: 0 | AC93: 0 | AD93: 1.14 | AE93: 0 | AF93: =IF(AND(E93>0,COUNTIFS($R$5:R93,R93,$E$5:E93,">0")=1),1,0) -> 1 | AG93: =IF(AND(E93>0,COUNTIFS($R$5:R93,R93,$K$5:K93,K93,$E$5:E93,">0")=1),1,0) -> 1
A94: 4733856691 | B94: 46023.383 | C94: 46023.383 | D94: 0.016111111 | E94: 0 | F94: 0 | G94: Morning (6-12) | H94: =FALSE() -> FALSE | I94: =FALSE() -> FALSE | K94: BARBOURVILLE / CITY HALL | L94: membership | R94: =INT(B94) -> 46023 | S94: =IF(AND(I94=TRUE(),COUNTIFS($R$5:R94,R94,$I$5:I94,TRUE())=1),1,0) -> 0 | W94: =SUM(Z94:AE94) -> 0 | X94: Thursday | Y94: 46020 | AF94: =IF(AND(E94>0,COUNTIFS($R$5:R94,R94,$E$5:E94,">0")=1),1,0) -> 0 | AG94: =IF(AND(E94>0,COUNTIFS($R$5:R94,R94,$K$5:K94,K94,$E$5:E94,">0")=1),1,0) -> 0
A95: 4733857311 | B95: 46023.384 | C95: 46023.395 | D95: 0.26361111 | E95: 12.3724 | F95: 48.125 | G95: Morning (6-12) | H95: =TRUE() -> TRUE | I95: =FALSE() -> FALSE | J95: 1 | K95: BARBOURVILLE / CITY HALL | L95: membership | M95: 63141 | N95: St. Louis County | O95: MO | P95: 6.36 | Q95: 5.4 | R95: =INT(B95) -> 46023 | S95: =IF(AND(I95=TRUE(),COUNTIFS($R$5:R95,R95,$I$5:I95,TRUE())=1),1,0) -> 0 | T95: 0.4 | U95: 6 | V95: 4.94896 | W95: =SUM(Z95:AE95) -> 0.96 | X95: Thursday | Y95: 46020 | Z95: 0.36 | AA95: 0 | AB95: 0 | AC95: 0 | AD95: 0.6 | AE95: 0 | AF95: =IF(AND(E95>0,COUNTIFS($R$5:R95,R95,$E$5:E95,">0")=1),1,0) -> 1 | AG95: =IF(AND(E95>0,COUNTIFS($R$5:R95,R95,$K$5:K95,K95,$E$5:E95,">0")=1),1,0) -> 1
A96: 4741403081 | B96: 46027.034 | C96: 46027.044 | D96: 0.23611111 | E96: 13.1661 | F96: 59.436 | G96: Night (22-6) | H96: =TRUE() -> TRUE | I96: =TRUE() -> TRUE | J96: 1 | K96: BARBOURVILLE / CITY HALL | L96: credit_card_terminal | P96: 6.59 | Q96: 5.59 | R96: =INT(B96) -> 46027 | S96: =IF(AND(I96=TRUE(),COUNTIFS($R$5:R96,R96,$I$5:I96,TRUE())=1),1,0) -> 1 | T96: 0.4 | U96: 6.21 | V96: 5.26644 | W96: =SUM(Z96:AE96) -> 1 | X96: Monday | Y96: 46027 | Z96: 0.38 | AA96: 0 | AB96: 0 | AC96: 0 | AD96: 0.62 | AE96: 0 | AF96: =IF(AND(E96>0,COUNTIFS($R$5:R96,R96,$E$5:E96,">0")=1),1,0) -> 1 | AG96: =IF(AND(E96>0,COUNTIFS($R$5:R96,R96,$K$5:K96,K96,$E$5:E96,">0")=1),1,0) -> 1
A97: 4761006811 | B97: 46033.816 | C97: 46033.816 | D97: 0.0044444444 | E97: 0 | F97: 0 | G97: Evening (18-22) | H97: =FALSE() -> FALSE | I97: =FALSE() -> FALSE | K97: BARBOURVILLE / CITY HALL | L97: membership | R97: =INT(B97) -> 46033 | S97: =IF(AND(I97=TRUE(),COUNTIFS($R$5:R97,R97,$I$5:I97,TRUE())=1),1,0) -> 0 | W97: =SUM(Z97:AE97) -> 0 | X97: Sunday | Y97: 46027 | AF97: =IF(AND(E97>0,COUNTIFS($R$5:R97,R97,$E$5:E97,">0")=1),1,0) -> 0 | AG97: =IF(AND(E97>0,COUNTIFS($R$5:R97,R97,$K$5:K97,K97,$E$5:E97,">0")=1),1,0) -> 0
A98: 4761007781 | B98: 46033.816 | C98: 46033.85 | D98: 0.79916667 | E98: 40.663502 | F98: 56.472 | G98: Evening (18-22) | H98: =TRUE() -> TRUE | I98: =FALSE() -> FALSE | J98: 1 | K98: BARBOURVILLE / CITY HALL | L98: membership | M98: 40906 | O98: KY | P98: 20.64 | Q98: 17.52 | R98: =INT(B98) -> 46033 | S98: =IF(AND(I98=TRUE(),COUNTIFS($R$5:R98,R98,$I$5:I98,TRUE())=1),1,0) -> 0 | T98: 0.4 | U98: 19.47 | V98: 16.265401 | W98: =SUM(Z98:AE98) -> 3.12 | X98: Sunday | Y98: 46027 | Z98: 1.17 | AA98: 0 | AB98: 0 | AC98: 0 | AD98: 1.95 | AE98: 0 | AF98: =IF(AND(E98>0,COUNTIFS($R$5:R98,R98,$E$5:E98,">0")=1),1,0) -> 1 | AG98: =IF(AND(E98>0,COUNTIFS($R$5:R98,R98,$K$5:K98,K98,$E$5:E98,">0")=1),1,0) -> 1
A99: 4777307511 | B99: 46038.857 | C99: 46038.859 | D99: 0.049444444 | E99: 2.0061 | F99: 0 | G99: Evening (18-22) | H99: =FALSE() -> FALSE | I99: =FALSE() -> FALSE | K99: BARBOURVILLE / CITY HALL | L99: membership | M99: 40906 | O99: KY | P99: 1.06 | Q99: 0.9 | R99: =INT(B99) -> 46038 | S99: =IF(AND(I99=TRUE(),COUNTIFS($R$5:R99,R99,$I$5:I99,TRUE())=1),1,0) -> 0 | T99: 0.4 | U99: 1 | V99: 0.80244 | W99: =SUM(Z99:AE99) -> 0.16 | X99: Friday | Y99: 46034 | Z99: 0.06 | AA99: 0 | AB99: 0 | AC99: 0 | AD99: 0.1 | AE99: 0 | AF99: =IF(AND(E99>0,COUNTIFS($R$5:R99,R99,$E$5:E99,">0")=1),1,0) -> 1 | AG99: =IF(AND(E99>0,COUNTIFS($R$5:R99,R99,$K$5:K99,K99,$E$5:E99,">0")=1),1,0) -> 1
A100: 4777318221 | B100: 46038.859 | C100: 46038.866 | D100: 0.16222222 | E100: 8.3979 | F100: 54.444 | G100: Evening (18-22) | H100: =TRUE() -> TRUE | I100: =FALSE() -> FALSE | J100: 1 | K100: BARBOURVILLE / CITY HALL | L100: membership | M100: 40906 | O100: KY | P100: 4.25 | Q100: 3.61 | R100: =INT(B100) -> 46038 | S100: =IF(AND(I100=TRUE(),COUNTIFS($R$5:R100,R100,$I$5:I100,TRUE())=1),1,0) -> 0 | T100: 0.4 | U100: 4.01 | V100: 3.35916 | W100: =SUM(Z100:AE100) -> 0.64 | X100: Friday | Y100: 46034 | Z100: 0.24 | AA100: 0 | AB100: 0 | AC100: 0 | AD100: 0.4 | AE100: 0 | AF100: =IF(AND(E100>0,COUNTIFS($R$5:R100,R100,$E$5:E100,">0")=1),1,0) -> 0 | AG100: =IF(AND(E100>0,COUNTIFS($R$5:R100,R100,$K$5:K100,K100,$E$5:E100,">0")=1),1,0) -> 0
A101: 4779338971 | B101: 46039.652 | C101: 46039.654 | D101: 0.0525 | E101: 0 | F101: 0 | G101: Day (12-18) | H101: =FALSE() -> FALSE | I101: =FALSE() -> FALSE | K101: BARBOURVILLE / CITY HALL | L101: membership | M101: 40511 | O101: KY | P101: 0.22 | Q101: 0.19 | R101: =INT(B101) -> 46039 | S101: =IF(AND(I101=TRUE(),COUNTIFS($R$5:R101,R101,$I$5:I101,TRUE())=1),1,0) -> 0 | T101: 0.4 | U101: 0.21 | V101: 0 | W101: =SUM(Z101:AE101) -> 0.03 | X101: Saturday | Y101: 46034 | Z101: 0.01 | AA101: 0 | AB101: 0 | AC101: 0 | AD101: 0.02 | AE101: 0 | AF101: =IF(AND(E101>0,COUNTIFS($R$5:R101,R101,$E$5:E101,">0")=1),1,0) -> 0 | AG101: =IF(AND(E101>0,COUNTIFS($R$5:R101,R101,$K$5:K101,K101,$E$5:E101,">0")=1),1,0) -> 0
...

Sheet Raw - Daily Energy
A1: Combined Daily Charger Energy Delivered (365 days)
A2: Deduplicated union of the two Energy-vs-Time exports - same underlying meter, confirmed identical on 191 overlapping days.
A4: Date | B4: Energy Delivered (kWh)
A5: 45850 | B5: 0
A6: 45851 | B6: 0
A7: 45852 | B7: 0
A8: 45853 | B8: 0
A9: 45854 | B9: 0
A10: 45855 | B10: 0
A11: 45856 | B11: 0
A12: 45857 | B12: 0
A13: 45858 | B13: 0
A14: 45859 | B14: 0
A15: 45860 | B15: 0
A16: 45861 | B16: 0
... A369: 46214 | B369: 0

Sheet Raw - Zip-County-State
A1: Visitor Origin - Aggregated by ZIP, County, and Estimated State
A2: Every Sessions/Revenue/Energy figure below is a live COUNTIF/SUMIF formula against Raw - Sessions - editing a session there recalculates these tables automatically. Aggregated from the 165 sessions (of 288) with a driver ZIP code on file; 124 have no ZIP (guest/anonymous checkout) and are excluded.
A4: Driver ZIP | B4: Sessions | C4: Revenue ($) | F4: Driver County | G4: Sessions | H4: Revenue ($) | K4: Est. State | L4: Sessions | M4: Revenue ($) | N4: Energy (kWh)
A5: 40906 | B5: =COUNTIF('Raw - Sessions'!$M$5:$M$292,A5) -> 37 | C5: =SUMIF('Raw - Sessions'!$M$5:$M$292,A5,'Raw - Sessions'!$P$5:$P$292) -> 905.25 | F5: Bell County | G5: =COUNTIF('Raw - Sessions'!$N$5:$N$292,F5) -> 6 | H5: =SUMIF('Raw - Sessions'!$N$5:$N$292,F5,'Raw - Sessions'!$P$5:$P$292) -> 150.06 | K5: KY | L5: =COUNTIF('Raw - Sessions'!$O$5:$O$292,K5) -> 96 | M5: =SUMIF('Raw - Sessions'!$O$5:$O$292,K5,'Raw - Sessions'!$P$5:$P$292) -> 1775.37 | N5: =SUMIF('Raw - Sessions'!$O$5:$O$292,K5,'Raw - Sessions'!$E$5:$E$292) -> 2806.3162
A6: 40965 | B6: =COUNTIF('Raw - Sessions'!$M$5:$M$292,A6) -> 6 | C6: =SUMIF('Raw - Sessions'!$M$5:$M$292,A6,'Raw - Sessions'!$P$5:$P$292) -> 150.06 | F6: Harlan County | G6: =COUNTIF('Raw - Sessions'!$N$5:$N$292,F6) -> 5 | H6: =SUMIF('Raw - Sessions'!$N$5:$N$292,F6,'Raw - Sessions'!$P$5:$P$292) -> 77.86 | K6: TN | L6: =COUNTIF('Raw - Sessions'!$O$5:$O$292,K6) -> 18 | M6: =SUMIF('Raw - Sessions'!$O$5:$O$292,K6,'Raw - Sessions'!$P$5:$P$292) -> 212.02 | N6: =SUMIF('Raw - Sessions'!$O$5:$O$292,K6,'Raw - Sessions'!$E$5:$E$292) -> 378.49361
A7: 37601 | B7: =COUNTIF('Raw - Sessions'!$M$5:$M$292,A7) -> 5 | C7: =SUMIF('Raw - Sessions'!$M$5:$M$292,A7,'Raw - Sessions'!$P$5:$P$292) -> 54.61 | F7: Knox County | G7: =COUNTIF('Raw - Sessions'!$N$5:$N$292,F7) -> 4 | H7: =SUMIF('Raw - Sessions'!$N$5:$N$292,F7,'Raw - Sessions'!$P$5:$P$292) -> 53.98 | K7: OH | L7: =COUNTIF('Raw - Sessions'!$O$5:$O$292,K7) -> 10 | M7: =SUMIF('Raw - Sessions'!$O$5:$O$292,K7,'Raw - Sessions'!$P$5:$P$292) -> 159.73 | N7: =SUMIF('Raw - Sessions'!$O$5:$O$292,K7,'Raw - Sessions'!$E$5:$E$292) -> 264.54778
A8: 40653 | B8: =COUNTIF('Raw - Sessions'!$M$5:$M$292,A8) -> 5 | C8: =SUMIF('Raw - Sessions'!$M$5:$M$292,A8,'Raw - Sessions'!$P$5:$P$292) -> 3.19 | F8: Fayette County | G8: =COUNTIF('Raw - Sessions'!$N$5:$N$292,F8) -> 4 | H8: =SUMIF('Raw - Sessions'!$N$5:$N$292,F8,'Raw - Sessions'!$P$5:$P$292) -> 89.74 | K8: NC | L8: =COUNTIF('Raw - Sessions'!$O$5:$O$292,K8) -> 9 | M8: =SUMIF('Raw - Sessions'!$O$5:$O$292,K8,'Raw - Sessions'!$P$5:$P$292) -> 176.72 | N8: =SUMIF('Raw - Sessions'!$O$5:$O$292,K8,'Raw - Sessions'!$E$5:$E$292) -> 276.5583
A9: 40701 | B9: =COUNTIF('Raw - Sessions'!$M$5:$M$292,A9) -> 5 | C9: =SUMIF('Raw - Sessions'!$M$5:$M$292,A9,'Raw - Sessions'!$P$5:$P$292) -> 25.39 | F9: DuPage County | G9: =COUNTIF('Raw - Sessions'!$N$5:$N$292,F9) -> 4 | H9: =SUMIF('Raw - Sessions'!$N$5:$N$292,F9,'Raw - Sessions'!$P$5:$P$292) -> 25.84 | K9: IL | L9: =COUNTIF('Raw - Sessions'!$O$5:$O$292,K9) -> 5 | M9: =SUMIF('Raw - Sessions'!$O$5:$O$292,K9,'Raw - Sessions'!$P$5:$P$292) -> 37.59 | N9: =SUMIF('Raw - Sessions'!$O$5:$O$292,K9,'Raw - Sessions'!$E$5:$E$292) -> 43.146601
A10: 40977 | B10: =COUNTIF('Raw - Sessions'!$M$5:$M$292,A10) -> 5 | C10: =SUMIF('Raw - Sessions'!$M$5:$M$292,A10,'Raw - Sessions'!$P$5:$P$292) -> 117.31 | F10: Greenville County | G10: =COUNTIF('Raw - Sessions'!$N$5:$N$292,F10) -> 3 | H10: =SUMIF('Raw - Sessions'!$N$5:$N$292,F10,'Raw - Sessions'!$P$5:$P$292) -> 30.12 | K10: FL | L10: =COUNTIF('Raw - Sessions'!$O$5:$O$292,K10) -> 3 | M10: =SUMIF('Raw - Sessions'!$O$5:$O$292,K10,'Raw - Sessions'!$P$5:$P$292) -> 76.03 | N10: =SUMIF('Raw - Sessions'!$O$5:$O$292,K10,'Raw - Sessions'!$E$5:$E$292) -> 150.9546
A11: 60559 | B11: =COUNTIF('Raw - Sessions'!$M$5:$M$292,A11) -> 4 | C11: =SUMIF('Raw - Sessions'!$M$5:$M$292,A11,'Raw - Sessions'!$P$5:$P$292) -> 25.84 | F11: Hamilton County | G11: =COUNTIF('Raw - Sessions'!$N$5:$N$292,F11) -> 3 | H11: =SUMIF('Raw - Sessions'!$N$5:$N$292,F11,'Raw - Sessions'!$P$5:$P$292) -> 57.25 | K11: SC | L11: =COUNTIF('Raw - Sessions'!$O$5:$O$292,K11) -> 3 | M11: =SUMIF('Raw - Sessions'!$O$5:$O$292,K11,'Raw - Sessions'!$P$5:$P$292) -> 30.12 | N11: =SUMIF('Raw - Sessions'!$O$5:$O$292,K11,'Raw - Sessions'!$E$5:$E$292) -> 48.6106
A12: 40511 | B12: =COUNTIF('Raw - Sessions'!$M$5:$M$292,A12) -> 4 | C12: =SUMIF('Raw - Sessions'!$M$5:$M$292,A12,'Raw - Sessions'!$P$5:$P$292) -> 24.32 | F12: Sumner County | G12: =COUNTIF('Raw - Sessions'!$N$5:$N$292,F12) -> 2 | H12: =SUMIF('Raw - Sessions'!$N$5:$N$292,F12,'Raw - Sessions'!$P$5:$P$292) -> 28.02 | K12: MI | L12: =COUNTIF('Raw - Sessions'!$O$5:$O$292,K12) -> 3 | M12: =SUMIF('Raw - Sessions'!$O$5:$O$292,K12,'Raw - Sessions'!$P$5:$P$292) -> 65.07 | N12: =SUMIF('Raw - Sessions'!$O$5:$O$292,K12,'Raw - Sessions'!$E$5:$E$292) -> 109.0732
A13: 29615 | B13: =COUNTIF('Raw - Sessions'!$M$5:$M$292,A13) -> 3 | C13: =SUMIF('Raw - Sessions'!$M$5:$M$292,A13,'Raw - Sessions'!$P$5:$P$292) -> 30.12 | F13: Jefferson County | G13: =COUNTIF('Raw - Sessions'!$N$5:$N$292,F13) -> 2 | H13: =SUMIF('Raw - Sessions'!$N$5:$N$292,F13,'Raw - Sessions'!$P$5:$P$292) -> 31.82 | K13: WI | L13: =COUNTIF('Raw - Sessions'!$O$5:$O$292,K13) -> 3 | M13: =SUMIF('Raw - Sessions'!$O$5:$O$292,K13,'Raw - Sessions'!$P$5:$P$292) -> 50.77 | N13: =SUMIF('Raw - Sessions'!$O$5:$O$292,K13,'Raw - Sessions'!$E$5:$E$292) -> 100.0658
A14: 40403 | B14: =COUNTIF('Raw - Sessions'!$M$5:$M$292,A14) -> 3 | C14: =SUMIF('Raw - Sessions'!$M$5:$M$292,A14,'Raw - Sessions'!$P$5:$P$292) -> 40.43 | F14: DeKalb County | G14: =COUNTIF('Raw - Sessions'!$N$5:$N$292,F14) -> 2 | H14: =SUMIF('Raw - Sessions'!$N$5:$N$292,F14,'Raw - Sessions'!$P$5:$P$292) -> 45.25 | K14: IN | L14: =COUNTIF('Raw - Sessions'!$O$5:$O$292,K14) -> 2 | M14: =SUMIF('Raw - Sessions'!$O$5:$O$292,K14,'Raw - Sessions'!$P$5:$P$292) -> 55.22 | N14: =SUMIF('Raw - Sessions'!$O$5:$O$292,K14,'Raw - Sessions'!$E$5:$E$292) -> 83.8031
A15: 40806 | B15: =COUNTIF('Raw - Sessions'!$M$5:$M$292,A15) -> 3 | C15: =SUMIF('Raw - Sessions'!$M$5:$M$292,A15,'Raw - Sessions'!$P$5:$P$292) -> 63.88 | F15: Montgomery County | G15: =COUNTIF('Raw - Sessions'!$N$5:$N$292,F15) -> 2 | H15: =SUMIF('Raw - Sessions'!$N$5:$N$292,F15,'Raw - Sessions'!$P$5:$P$292) -> 23.3 | K15: GA | L15: =COUNTIF('Raw - Sessions'!$O$5:$O$292,K15) -> 2 | M15: =SUMIF('Raw - Sessions'!$O$5:$O$292,K15,'Raw - Sessions'!$P$5:$P$292) -> 45.25 | N15: =SUMIF('Raw - Sessions'!$O$5:$O$292,K15,'Raw - Sessions'!$E$5:$E$292) -> 66.288899
A16: 40324 | B16: =COUNTIF('Raw - Sessions'!$M$5:$M$292,A16) -> 3 | C16: =SUMIF('Raw - Sessions'!$M$5:$M$292,A16,'Raw - Sessions'!$P$5:$P$292) -> 75.13 | F16: Summit County | G16: =COUNTIF('Raw - Sessions'!$N$5:$N$292,F16) -> 2 | H16: =SUMIF('Raw - Sessions'!$N$5:$N$292,F16,'Raw - Sessions'!$P$5:$P$292) -> 12.83 | K16: TX | L16: =COUNTIF('Raw - Sessions'!$O$5:$O$292,K16) -> 2 | M16: =SUMIF('Raw - Sessions'!$O$5:$O$292,K16,'Raw - Sessions'!$P$5:$P$292) -> 39.78 | N16: =SUMIF('Raw - Sessions'!$O$5:$O$292,K16,'Raw - Sessions'!$E$5:$E$292) -> 68.5376
... A23: 44221 | B23: =COUNTIF('Raw - Sessions'!$M$5:$M$292,A23) -> 2 | C23: =SUMIF('Raw - Sessions'!$M$5:$M$292,A23,'Raw - Sessions'!$P$5:$P$292) -> 12.83 | F23: Livingston County | G23: =COUNTIF('Raw - Sessions'!$N$5:$N$292,F23) -> 1 | H23: =SUMIF('Raw - Sessions'!$N$5:$N$292,F23,'Raw - Sessions'!$P$5:$P$292) -> 8.59 | K23: OK | L23: =COUNTIF('Raw - Sessions'!$O$5:$O$292,K23) -> 1 | M23: =SUMIF('Raw - Sessions'!$O$5:$O$292,K23,'Raw - Sessions'!$P$5:$P$292) -> 8.45 | N23: =SUMIF('Raw - Sessions'!$O$5:$O$292,K23,'Raw - Sessions'!$E$5:$E$292) -> 11.8481
A24: 43050 | B24: =COUNTIF('Raw - Sessions'!$M$5:$M$292,A24) -> 2 | C24: =SUMIF('Raw - Sessions'!$M$5:$M$292,A24,'Raw - Sessions'!$P$5:$P$292) -> 37.81 | F24: Lee County | G24: =COUNTIF('Raw - Sessions'!$N$5:$N$292,F24) -> 1 | H24: =SUMIF('Raw - Sessions'!$N$5:$N$292,F24,'Raw - Sessions'!$P$5:$P$292) -> 17.6
A25: 45205 | B25: =COUNTIF('Raw - Sessions'!$M$5:$M$292,A25) -> 2 | C25: =SUMIF('Raw - Sessions'!$M$5:$M$292,A25,'Raw - Sessions'!$P$5:$P$292) -> 43.31 | F25: Jessamine County | G25: =COUNTIF('Raw - Sessions'!$N$5:$N$292,F25) -> 1 | H25: =SUMIF('Raw - Sessions'!$N$5:$N$292,F25,'Raw - Sessions'!$P$5:$P$292) -> 24.26
A26: 40059 | B26: =COUNTIF('Raw - Sessions'!$M$5:$M$292,A26) -> 2 | C26: =SUMIF('Raw - Sessions'!$M$5:$M$292,A26,'Raw - Sessions'!$P$5:$P$292) -> 33.92 | F26: Harris County | G26: =COUNTIF('Raw - Sessions'!$N$5:$N$292,F26) -> 1 | H26: =SUMIF('Raw - Sessions'!$N$5:$N$292,F26,'Raw - Sessions'!$P$5:$P$292) -> 28.49
A27: 19002 | B27: =COUNTIF('Raw - Sessions'!$M$5:$M$292,A27) -> 2 | C27: =SUMIF('Raw - Sessions'!$M$5:$M$292,A27,'Raw - Sessions'!$P$5:$P$292) -> 23.3 | F27: Mecklenburg County | G27: =COUNTIF('Raw - Sessions'!$N$5:$N$292,F27) -> 1 | H27: =SUMIF('Raw - Sessions'!$N$5:$N$292,F27,'Raw - Sessions'!$P$5:$P$292) -> 15.89
A28: 30032 | B28: =COUNTIF('Raw - Sessions'!$M$5:$M$292,A28) -> 2 | C28: =SUMIF('Raw - Sessions'!$M$5:$M$292,A28,'Raw - Sessions'!$P$5:$P$292) -> 45.25 | F28: Milwaukee County | G28: =COUNTIF('Raw - Sessions'!$N$5:$N$292,F28) -> 1 | H28: =SUMIF('Raw - Sessions'!$N$5:$N$292,F28,'Raw - Sessions'!$P$5:$P$292) -> 3.11
A29: 40509 | B29: =COUNTIF('Raw - Sessions'!$M$5:$M$292,A29) -> 2 | C29: =SUMIF('Raw - Sessions'!$M$5:$M$292,A29,'Raw - Sessions'!$P$5:$P$292) -> 67.38 | F29: Manatee County | G29: =COUNTIF('Raw - Sessions'!$N$5:$N$292,F29) -> 1 | H29: =SUMIF('Raw - Sessions'!$N$5:$N$292,F29,'Raw - Sessions'!$P$5:$P$292) -> 21.48
A30: 37934 | B30: =COUNTIF('Raw - Sessions'!$M$5:$M$292,A30) -> 2 | C30: =SUMIF('Raw - Sessions'!$M$5:$M$292,A30,'Raw - Sessions'!$P$5:$P$292) -> 23.18 | F30: Macon County | G30: =COUNTIF('Raw - Sessions'!$N$5:$N$292,F30) -> 1 | H30: =SUMIF('Raw - Sessions'!$N$5:$N$292,F30,'Raw - Sessions'!$P$5:$P$292) -> 20.15
A31: 40475 | B31: =COUNTIF('Raw - Sessions'!$M$5:$M$292,A31) -> 2 | C31: =SUMIF('Raw - Sessions'!$M$5:$M$292,A31,'Raw - Sessions'!$P$5:$P$292) -> 35.77 | F31: Palm Beach County | G31: =COUNTIF('Raw - Sessions'!$N$5:$N$292,F31) -> 1 | H31: =SUMIF('Raw - Sessions'!$N$5:$N$292,F31,'Raw - Sessions'!$P$5:$P$292) -> 36.95
A32: 37075 | B32: =COUNTIF('Raw - Sessions'!$M$5:$M$292,A32) -> 2 | C32: =SUMIF('Raw - Sessions'!$M$5:$M$292,A32,'Raw - Sessions'!$P$5:$P$292) -> 28.02 | F32: Morgan County | G32: =COUNTIF('Raw - Sessions'!$N$5:$N$292,F32) -> 1 | H32: =SUMIF('Raw - Sessions'!$N$5:$N$292,F32,'Raw - Sessions'!$P$5:$P$292) -> 14.13
A33: 07666 | B33: =COUNTIF('Raw - Sessions'!$M$5:$M$292,A33) -> 1 | C33: =SUMIF('Raw - Sessions'!$M$5:$M$292,A33,'Raw - Sessions'!$P$5:$P$292) -> 11.01 | F33: Pike County | G33: =COUNTIF('Raw - Sessions'!$N$5:$N$292,F33) -> 1 | H33: =SUMIF('Raw - Sessions'!$N$5:$N$292,F33,'Raw - Sessions'!$P$5:$P$292) -> 18.42
A34: 28787 | B34: =COUNTIF('Raw - Sessions'!$M$5:$M$292,A34) -> 1 | C34: =SUMIF('Raw - Sessions'!$M$5:$M$292,A34,'Raw - Sessions'!$P$5:$P$292) -> 32.36 | F34: Sedgwick County | G34: =COUNTIF('Raw - Sessions'!$N$5:$N$292,F34) -> 1 | H34: =SUMIF('Raw - Sessions'!$N$5:$N$292,F34,'Raw - Sessions'!$P$5:$P$292) -> 19.14
A35: 28806 | B35: =COUNTIF('Raw - Sessions'!$M$5:$M$292,A35) -> 1 | C35: =SUMIF('Raw - Sessions'!$M$5:$M$292,A35,'Raw - Sessions'!$P$5:$P$292) -> 11.44 | F35: St. Louis County | G35: =COUNTIF('Raw - Sessions'!$N$5:$N$292,F35) -> 1 | H35: =SUMIF('Raw - Sessions'!$N$5:$N$292,F35,'Raw - Sessions'!$P$5:$P$292) -> 6.36
... A38: 28112 | B38: =COUNTIF('Raw - Sessions'!$M$5:$M$292,A38) -> 1 | C38: =SUMIF('Raw - Sessions'!$M$5:$M$292,A38,'Raw - Sessions'!$P$5:$P$292) -> 17.54 | F38: Washington County | G38: =COUNTIF('Raw - Sessions'!$N$5:$N$292,F38) -> 1 | H38: =SUMIF('Raw - Sessions'!$N$5:$N$292,F38,'Raw - Sessions'!$P$5:$P$292) -> 26.7
A39: 20779 | B39: =COUNTIF('Raw - Sessions'!$M$5:$M$292,A39) -> 1 | C39: =SUMIF('Raw - Sessions'!$M$5:$M$292,A39,'Raw - Sessions'!$P$5:$P$292) -> 20.28
A40: 27045 | B40: =COUNTIF('Raw - Sessions'!$M$5:$M$292,A40) -> 1 | C40: =SUMIF('Raw - Sessions'!$M$5:$M$292,A40,'Raw - Sessions'!$P$5:$P$292) -> 11.89
A41: 27703 | B41: =COUNTIF('Raw - Sessions'!$M$5:$M$292,A41) -> 1 | C41: =SUMIF('Raw - Sessions'!$M$5:$M$292,A41,'Raw - Sessions'!$P$5:$P$292) -> 20.01
A42: 40220 | B42: =COUNTIF('Raw - Sessions'!$M$5:$M$292,A42) -> 1 | C42: =SUMIF('Raw - Sessions'!$M$5:$M$292,A42,'Raw - Sessions'!$P$5:$P$292) -> 14.9
A43: 37937 | B43: =COUNTIF('Raw - Sessions'!$M$5:$M$292,A43) -> 1 | C43: =SUMIF('Raw - Sessions'!$M$5:$M$292,A43,'Raw - Sessions'!$P$5:$P$292) -> 2.76
A44: 37825 | B44: =COUNTIF('Raw - Sessions'!$M$5:$M$292,A44) -> 1 | C44: =SUMIF('Raw - Sessions'!$M$5:$M$292,A44,'Raw - Sessions'!$P$5:$P$292) -> 10.48
A45: 37849 | B45: =COUNTIF('Raw - Sessions'!$M$5:$M$292,A45) -> 1 | C45: =SUMIF('Raw - Sessions'!$M$5:$M$292,A45,'Raw - Sessions'!$P$5:$P$292) -> 25.78
A46: 37813 | B46: =COUNTIF('Raw - Sessions'!$M$5:$M$292,A46) -> 1 | C46: =SUMIF('Raw - Sessions'!$M$5:$M$292,A46,'Raw - Sessions'!$P$5:$P$292) -> 17.92
A47: 34202 | B47: =COUNTIF('Raw - Sessions'!$M$5:$M$292,A47) -> 1 | C47: =SUMIF('Raw - Sessions'!$M$5:$M$292,A47,'Raw - Sessions'!$P$5:$P$292) -> 21.48
A48: 33957 | B48: =COUNTIF('Raw - Sessions'!$M$5:$M$292,A48) -> 1 | C48: =SUMIF('Raw - Sessions'!$M$5:$M$292,A48,'Raw - Sessions'!$P$5:$P$292) -> 17.6
A49: 33467 | B49: =COUNTIF('Raw - Sessions'!$M$5:$M$292,A49) -> 1 | C49: =SUMIF('Raw - Sessions'!$M$5:$M$292,A49,'Raw - Sessions'!$P$5:$P$292) -> 36.95
A50: 40741 | B50: =COUNTIF('Raw - Sessions'!$M$5:$M$292,A50) -> 1 | C50: =SUMIF('Raw - Sessions'!$M$5:$M$292,A50,'Raw - Sessions'!$P$5:$P$292) -> 6.23
... A81: 79424 | B81: =COUNTIF('Raw - Sessions'!$M$5:$M$292,A81) -> 1 | C81: =SUMIF('Raw - Sessions'!$M$5:$M$292,A81,'Raw - Sessions'!$P$5:$P$292) -> 11.29
